Workbook

Sheet A LIRE
A1: Document : | C1: Outil de nomenclature SIAD
A3: Interlocuteurs : | C3: Angéline JACQUINOT | D3: Carole ANDREOTTI
A5: Ce document permet de générer les codes des tables et champs d'une nomenclature ainsi que des libellés anglais. Il est là pour aider à compléter la demande de nomenclature.
A6: Il est décomposé en 4 parties : Tables, Champs, Objets de gestion/Articles et BIB/Type de table/Type de champ
A8: La feuille "Tables" permet de générer le code des tables (Domaine de valeurs et Datamart compris)
A9: À faire : | B9: Complèter les colonnes (par sélection dans la liste déroulante) : Nom du BIB, Type de table et Objet de gestion (jusquà 4 objets de gestion possible par table)
B10: ATTENTION : les colonnes après la barre vertical noire sont générés par du code Excel, merci de ne pas les toucher
A12: La feuille "Champs" permet de générer le code des champs (UID, code et libellé des domaines de valeurs compris).
A13: À faire : | B13: Complèter les colonnes (par sélection dans la liste déroulante) : Nom du BIB, Type de champ, Nature, Article + Objet de gestion et Ordre des trigrammes (jusquà 4 objets de gestion possible par champ)
B14: Ordre des trigrammes : "Normal" pour que le dernier objet de gestion soit au début. Ex : Le code de l'état du contrat > X_CTR_STT_COD > Contract state code "Forcé" pour que l'ordre des trigrammes soit le même que le libelé. Ex : : Le code de l'état du contrat > X_STT_CTR_COD > State contract code
B15: ATTENTION : les colonnes après la barre vertical noire sont générés par du code Excel, merci de ne pas les toucher
A17: Les feuilles "Objets de gestion" et "Articles" sont des référentiels. Ils peuvent être agrémenter de nouvelles lignes mais en aucun cas être mofifiés.
A18: À faire : | B18: Si un Objet de gestion n'est pas présent : - insérer une nouvelle ligne dans le tableau (Ctrl + "+") ou placer vous à la fin du tableau - renseigner la date du jour, le nom français, une description si besoin, le nom anglais et le trigramme (si le trigramme n'est pas présent dans LISABR, le surligner en rouge) - trier la colonne "nom FR" de A à Z Si un Article n'est pas présent : - insérer une nouvelle ligne dans le tableau (Ctrl + "+") ou placer vous à la fin du tableau - renseigner l'article en français et son équivalent anglais - trier sur la colonne "nom FR" de A à Z
A20: Les feuilles "BIB", "Type de table" et "Type de champ" sont des référentiels qui ne doivent pas être modifiés.
B21: Merci de notifier la cellule si une information est manquante.

Sheet Tables
A1: Nom du BIB | B1: Type table | C1: Objet de gestion 1 | D1: Objet de gestion 2 | E1: Objet de gestion 3 | F1: Objet de gestion 4 | G1: Robin | H1: Nb car | I1: Code | J1: Nom français | K1: Nom anglais | L1: Type
A2: tiers | B2: Axe d'analyse | C2: Lien | D2: tiers | E2: chargé de clientèle | G2: =IF(ISBLANK(A2),"",LOOKUP(A2,BIB!A:A,BIB!C:C)) -> IBIA | H2: =IF(AND(ISBLANK(A2),ISBLANK(B2),ISBLANK(C2)),"",IF(OR(ISBLANK(A2),ISBLANK(B2),ISBLANK(C2)),"-",LEN(Tableau4[[#This Row],[Colonne9]]))) -> 19 | I2: =IF(AND(ISBLANK(A2),ISBLANK(B2),ISBLANK(C2)),"",IF(OR(ISBLANK(A2),ISBLANK(B2),ISBLANK(C2)),"à compléter",UPPER(LOOKUP(A2,BIB!A:A,BIB!B:B)&LOOKUP(B2,'Type de table'!C:C,'Type de table'!B:B) &IF(COUNTIF('Objets de gestion'!C:C,F2)=0,"","_"&LOOKUP(F2,'Objets de gestion'!C:C,'Objets de gestion'!F:F)) &IF(COUNTIF('Objets de gestion'!C:C,E2)=0,"","_"&LOOKUP(E2,'Objets de gestion'!C:C,'Objets de gestion'!F:F)) &IF(COUNTIF('Objets de gestion'!C:C,D2)=0,"","_"&LOOKUP(D2,'Objets de gestion'!C:C,'Objets de gestion'!F:F)) &IF(COUNTIF('Objets de gestion'!C:C,C2)=0,"","_"&LOOKUP(C2,'Objets de gestion'!C:C,'Objets de gestion'!F:F)) ))) -> ATIX_ACCMGR_TDP_LNK | J2: =IF(AND(ISBLANK(A2),ISBLANK(B2),ISBLANK(C2)),"",IF(OR(ISBLANK(A2),ISBLANK(B2),ISBLANK(C2)),"-", LOOKUP(B2,'Type de table'!C:C,'Type de table'!E:E) &IF(ISBLANK(C2),""," "&C2) &IF(ISBLANK(D2),""," "&D2) &IF(ISBLANK(E2),""," "&E2) &IF(ISBLANK(F2),""," "&F2) )) -> Axe Lien tiers chargé de clientèle | K2: =IF(AND(ISBLANK(A2),ISBLANK(B2),ISBLANK(C2)),"",IF(OR(ISBLANK(A2),ISBLANK(B2),ISBLANK(C2)),"-", LOOKUP(B2,'Type de table'!C:C,'Type de table'!F:F) &IF(ISBLANK(C2),""," "&LOOKUP(C2,'Objets de gestion'!C:C,'Objets de gestion'!E:E)) &IF(ISBLANK(D2),""," "&LOOKUP(D2,'Objets de gestion'!C:C,'Objets de gestion'!E:E)) &IF(ISBLANK(E2),""," "&LOOKUP(E2,'Objets de gestion'!C:C,'Objets de gestion'!E:E)) &IF(ISBLANK(F2),""," "&LOOKUP(F2,'Objets de gestion'!C:C,'Objets de gestion'!E:E)) )) -> Axis Link third party Account Manager | L2: =IF(AND(ISBLANK(A2),ISBLANK(B2),ISBLANK(C2)),"",IF(OR(ISBLANK(A2),ISBLANK(B2),ISBLANK(C2)),"-",B2)) -> Axe d'analyse
A3: tiers | B3: Relation | C3: chargé de clientèle | D3: client | G3: =IF(ISBLANK(A3),"",LOOKUP(A3,BIB!A:A,BIB!C:C)) -> IBIA | H3: =IF(AND(ISBLANK(A3),ISBLANK(B3),ISBLANK(C3)),"",IF(OR(ISBLANK(A3),ISBLANK(B3),ISBLANK(C3)),"-",LEN(Tableau4[[#This Row],[Colonne9]]))) -> 15 | I3: =IF(AND(ISBLANK(A3),ISBLANK(B3),ISBLANK(C3)),"",IF(OR(ISBLANK(A3),ISBLANK(B3),ISBLANK(C3)),"à compléter",UPPER(LOOKUP(A3,BIB!A:A,BIB!B:B)&LOOKUP(B3,'Type de table'!C:C,'Type de table'!B:B) &IF(COUNTIF('Objets de gestion'!C:C,F3)=0,"","_"&LOOKUP(F3,'Objets de gestion'!C:C,'Objets de gestion'!F:F)) &IF(COUNTIF('Objets de gestion'!C:C,E3)=0,"","_"&LOOKUP(E3,'Objets de gestion'!C:C,'Objets de gestion'!F:F)) &IF(COUNTIF('Objets de gestion'!C:C,D3)=0,"","_"&LOOKUP(D3,'Objets de gestion'!C:C,'Objets de gestion'!F:F)) &IF(COUNTIF('Objets de gestion'!C:C,C3)=0,"","_"&LOOKUP(C3,'Objets de gestion'!C:C,'Objets de gestion'!F:F)) ))) -> ATIL_CUS_ACCMGR | J3: =IF(AND(ISBLANK(A3),ISBLANK(B3),ISBLANK(C3)),"",IF(OR(ISBLANK(A3),ISBLANK(B3),ISBLANK(C3)),"-", LOOKUP(B3,'Type de table'!C:C,'Type de table'!E:E) &IF(ISBLANK(C3),""," "&C3) &IF(ISBLANK(D3),""," "&D3) &IF(ISBLANK(E3),""," "&E3) &IF(ISBLANK(F3),""," "&F3) )) -> Table de lien entre chargé de clientèle client | K3: =IF(AND(ISBLANK(A3),ISBLANK(B3),ISBLANK(C3)),"",IF(OR(ISBLANK(A3),ISBLANK(B3),ISBLANK(C3)),"-", LOOKUP(B3,'Type de table'!C:C,'Type de table'!F:F) &IF(ISBLANK(C3),""," "&LOOKUP(C3,'Objets de gestion'!C:C,'Objets de gestion'!E:E)) &IF(ISBLANK(D3),""," "&LOOKUP(D3,'Objets de gestion'!C:C,'Objets de gestion'!E:E)) &IF(ISBLANK(E3),""," "&LOOKUP(E3,'Objets de gestion'!C:C,'Objets de gestion'!E:E)) &IF(ISBLANK(F3),""," "&LOOKUP(F3,'Objets de gestion'!C:C,'Objets de gestion'!E:E)) )) -> Link table between Account Manager customer | L3: =IF(AND(ISBLANK(A3),ISBLANK(B3),ISBLANK(C3)),"",IF(OR(ISBLANK(A3),ISBLANK(B3),ISBLANK(C3)),"-",B3)) -> Relation
G4: =IF(ISBLANK(A4),"",LOOKUP(A4,BIB!A:A,BIB!C:C))
G5: =IF(ISBLANK(A5),"",LOOKUP(A5,BIB!A:A,BIB!C:C))
G6: =IF(ISBLANK(A6),"",LOOKUP(A6,BIB!A:A,BIB!C:C))
G7: =IF(ISBLANK(A7),"",LOOKUP(A7,BIB!A:A,BIB!C:C))
G8: =IF(ISBLANK(A8),"",LOOKUP(A8,BIB!A:A,BIB!C:C))
G9: =IF(ISBLANK(A9),"",LOOKUP(A9,BIB!A:A,BIB!C:C))
G10: =IF(ISBLANK(A10),"",LOOKUP(A10,BIB!A:A,BIB!C:C))
G11: =IF(ISBLANK(A11),"",LOOKUP(A11,BIB!A:A,BIB!C:C))
G12: =IF(ISBLANK(A12),"",LOOKUP(A12,BIB!A:A,BIB!C:C))
G13: =IF(ISBLANK(A13),"",LOOKUP(A13,BIB!A:A,BIB!C:C))
G14: =IF(ISBLANK(A14),"",LOOKUP(A14,BIB!A:A,BIB!C:C))
G15: =IF(ISBLANK(A15),"",LOOKUP(A15,BIB!A:A,BIB!C:C))
G16: =IF(ISBLANK(A16),"",LOOKUP(A16,BIB!A:A,BIB!C:C)) | H16: =IF(AND(ISBLANK(A16),ISBLANK(B16),ISBLANK(C16)),"",IF(OR(ISBLANK(A16),ISBLANK(B16),ISBLANK(C16)),"-",LEN(Tableau4[[#This Row],[Colonne9]]))) | I16: =IF(AND(ISBLANK(A16),ISBLANK(B16),ISBLANK(C16)),"",IF(OR(ISBLANK(A16),ISBLANK(B16),ISBLANK(C16)),"à compléter",UPPER(LOOKUP(A16,BIB!A:A,BIB!B:B)&LOOKUP(B16,'Type de table'!C:C,'Type de table'!B:B) &IF(COUNTIF('Objets de gestion'!C:C,F16)=0,"","_"&LOOKUP(F16,'Objets de gestion'!C:C,'Objets de gestion'!F:F)) &IF(COUNTIF('Objets de gestion'!C:C,E16)=0,"","_"&LOOKUP(E16,'Objets de gestion'!C:C,'Objets de gestion'!F:F)) &IF(COUNTIF('Objets de gestion'!C:C,D16)=0,"","_"&LOOKUP(D16,'Objets de gestion'!C:C,'Objets de gestion'!F:F)) &IF(COUNTIF('Objets de gestion'!C:C,C16)=0,"","_"&LOOKUP(C16,'Objets de gestion'!C:C,'Objets de gestion'!F:F)) ))) | J16: =IF(AND(ISBLANK(A16),ISBLANK(B16),ISBLANK(C16)),"",IF(OR(ISBLANK(A16),ISBLANK(B16),ISBLANK(C16)),"-", LOOKUP(B16,'Type de table'!C:C,'Type de table'!E:E) &IF(ISBLANK(C16),""," "&C16) &IF(ISBLANK(D16),""," "&D16) &IF(ISBLANK(E16),""," "&E16) &IF(ISBLANK(F16),""," "&F16) )) | K16: =IF(AND(ISBLANK(A16),ISBLANK(B16),ISBLANK(C16)),"",IF(OR(ISBLANK(A16),ISBLANK(B16),ISBLANK(C16)),"-", LOOKUP(B16,'Type de table'!C:C,'Type de table'!F:F) &IF(ISBLANK(C16),""," "&LOOKUP(C16,'Objets de gestion'!C:C,'Objets de gestion'!E:E)) &IF(ISBLANK(D16),""," "&LOOKUP(D16,'Objets de gestion'!C:C,'Objets de gestion'!E:E)) &IF(ISBLANK(E16),""," "&LOOKUP(E16,'Objets de gestion'!C:C,'Objets de gestion'!E:E)) &IF(ISBLANK(F16),""," "&LOOKUP(F16,'Objets de gestion'!C:C,'Objets de gestion'!E:E)) )) | L16: =IF(AND(ISBLANK(A16),ISBLANK(B16),ISBLANK(C16)),"",IF(OR(ISBLANK(A16),ISBLANK(B16),ISBLANK(C16)),"-",B16))
G17: =IF(ISBLANK(A17),"",LOOKUP(A17,BIB!A:A,BIB!C:C)) | H17: =IF(AND(ISBLANK(A17),ISBLANK(B17),ISBLANK(C17)),"",IF(OR(ISBLANK(A17),ISBLANK(B17),ISBLANK(C17)),"-",LEN(Tableau4[[#This Row],[Colonne9]]))) | I17: =IF(AND(ISBLANK(A17),ISBLANK(B17),ISBLANK(C17)),"",IF(OR(ISBLANK(A17),ISBLANK(B17),ISBLANK(C17)),"à compléter",UPPER(LOOKUP(A17,BIB!A:A,BIB!B:B)&LOOKUP(B17,'Type de table'!C:C,'Type de table'!B:B) &IF(COUNTIF('Objets de gestion'!C:C,F17)=0,"","_"&LOOKUP(F17,'Objets de gestion'!C:C,'Objets de gestion'!F:F)) &IF(COUNTIF('Objets de gestion'!C:C,E17)=0,"","_"&LOOKUP(E17,'Objets de gestion'!C:C,'Objets de gestion'!F:F)) &IF(COUNTIF('Objets de gestion'!C:C,D17)=0,"","_"&LOOKUP(D17,'Objets de gestion'!C:C,'Objets de gestion'!F:F)) &IF(COUNTIF('Objets de gestion'!C:C,C17)=0,"","_"&LOOKUP(C17,'Objets de gestion'!C:C,'Objets de gestion'!F:F)) ))) | J17: =IF(AND(ISBLANK(A17),ISBLANK(B17),ISBLANK(C17)),"",IF(OR(ISBLANK(A17),ISBLANK(B17),ISBLANK(C17)),"-", LOOKUP(B17,'Type de table'!C:C,'Type de table'!E:E) &IF(ISBLANK(C17),""," "&C17) &IF(ISBLANK(D17),""," "&D17) &IF(ISBLANK(E17),""," "&E17) &IF(ISBLANK(F17),""," "&F17) )) | K17: =IF(AND(ISBLANK(A17),ISBLANK(B17),ISBLANK(C17)),"",IF(OR(ISBLANK(A17),ISBLANK(B17),ISBLANK(C17)),"-", LOOKUP(B17,'Type de table'!C:C,'Type de table'!F:F) &IF(ISBLANK(C17),""," "&LOOKUP(C17,'Objets de gestion'!C:C,'Objets de gestion'!E:E)) &IF(ISBLANK(D17),""," "&LOOKUP(D17,'Objets de gestion'!C:C,'Objets de gestion'!E:E)) &IF(ISBLANK(E17),""," "&LOOKUP(E17,'Objets de gestion'!C:C,'Objets de gestion'!E:E)) &IF(ISBLANK(F17),""," "&LOOKUP(F17,'Objets de gestion'!C:C,'Objets de gestion'!E:E)) )) | L17: =IF(AND(ISBLANK(A17),ISBLANK(B17),ISBLANK(C17)),"",IF(OR(ISBLANK(A17),ISBLANK(B17),ISBLANK(C17)),"-",B17))
G18: =IF(ISBLANK(A18),"",LOOKUP(A18,BIB!A:A,BIB!C:C)) | H18: =IF(AND(ISBLANK(A18),ISBLANK(B18),ISBLANK(C18)),"",IF(OR(ISBLANK(A18),ISBLANK(B18),ISBLANK(C18)),"-",LEN(Tableau4[[#This Row],[Colonne9]]))) | I18: =IF(AND(ISBLANK(A18),ISBLANK(B18),ISBLANK(C18)),"",IF(OR(ISBLANK(A18),ISBLANK(B18),ISBLANK(C18)),"à compléter",UPPER(LOOKUP(A18,BIB!A:A,BIB!B:B)&LOOKUP(B18,'Type de table'!C:C,'Type de table'!B:B) &IF(COUNTIF('Objets de gestion'!C:C,F18)=0,"","_"&LOOKUP(F18,'Objets de gestion'!C:C,'Objets de gestion'!F:F)) &IF(COUNTIF('Objets de gestion'!C:C,E18)=0,"","_"&LOOKUP(E18,'Objets de gestion'!C:C,'Objets de gestion'!F:F)) &IF(COUNTIF('Objets de gestion'!C:C,D18)=0,"","_"&LOOKUP(D18,'Objets de gestion'!C:C,'Objets de gestion'!F:F)) &IF(COUNTIF('Objets de gestion'!C:C,C18)=0,"","_"&LOOKUP(C18,'Objets de gestion'!C:C,'Objets de gestion'!F:F)) ))) | J18: =IF(AND(ISBLANK(A18),ISBLANK(B18),ISBLANK(C18)),"",IF(OR(ISBLANK(A18),ISBLANK(B18),ISBLANK(C18)),"-", LOOKUP(B18,'Type de table'!C:C,'Type de table'!E:E) &IF(ISBLANK(C18),""," "&C18) &IF(ISBLANK(D18),""," "&D18) &IF(ISBLANK(E18),""," "&E18) &IF(ISBLANK(F18),""," "&F18) )) | K18: =IF(AND(ISBLANK(A18),ISBLANK(B18),ISBLANK(C18)),"",IF(OR(ISBLANK(A18),ISBLANK(B18),ISBLANK(C18)),"-", LOOKUP(B18,'Type de table'!C:C,'Type de table'!F:F) &IF(ISBLANK(C18),""," "&LOOKUP(C18,'Objets de gestion'!C:C,'Objets de gestion'!E:E)) &IF(ISBLANK(D18),""," "&LOOKUP(D18,'Objets de gestion'!C:C,'Objets de gestion'!E:E)) &IF(ISBLANK(E18),""," "&LOOKUP(E18,'Objets de gestion'!C:C,'Objets de gestion'!E:E)) &IF(ISBLANK(F18),""," "&LOOKUP(F18,'Objets de gestion'!C:C,'Objets de gestion'!E:E)) )) | L18: =IF(AND(ISBLANK(A18),ISBLANK(B18),ISBLANK(C18)),"",IF(OR(ISBLANK(A18),ISBLANK(B18),ISBLANK(C18)),"-",B18))
G19: =IF(ISBLANK(A19),"",LOOKUP(A19,BIB!A:A,BIB!C:C)) | H19: =IF(AND(ISBLANK(A19),ISBLANK(B19),ISBLANK(C19)),"",IF(OR(ISBLANK(A19),ISBLANK(B19),ISBLANK(C19)),"-",LEN(Tableau4[[#This Row],[Colonne9]]))) | I19: =IF(AND(ISBLANK(A19),ISBLANK(B19),ISBLANK(C19)),"",IF(OR(ISBLANK(A19),ISBLANK(B19),ISBLANK(C19)),"à compléter",UPPER(LOOKUP(A19,BIB!A:A,BIB!B:B)&LOOKUP(B19,'Type de table'!C:C,'Type de table'!B:B) &IF(COUNTIF('Objets de gestion'!C:C,F19)=0,"","_"&LOOKUP(F19,'Objets de gestion'!C:C,'Objets de gestion'!F:F)) &IF(COUNTIF('Objets de gestion'!C:C,E19)=0,"","_"&LOOKUP(E19,'Objets de gestion'!C:C,'Objets de gestion'!F:F)) &IF(COUNTIF('Objets de gestion'!C:C,D19)=0,"","_"&LOOKUP(D19,'Objets de gestion'!C:C,'Objets de gestion'!F:F)) &IF(COUNTIF('Objets de gestion'!C:C,C19)=0,"","_"&LOOKUP(C19,'Objets de gestion'!C:C,'Objets de gestion'!F:F)) ))) | J19: =IF(AND(ISBLANK(A19),ISBLANK(B19),ISBLANK(C19)),"",IF(OR(ISBLANK(A19),ISBLANK(B19),ISBLANK(C19)),"-", LOOKUP(B19,'Type de table'!C:C,'Type de table'!E:E) &IF(ISBLANK(C19),""," "&C19) &IF(ISBLANK(D19),""," "&D19) &IF(ISBLANK(E19),""," "&E19) &IF(ISBLANK(F19),""," "&F19) )) | K19: =IF(AND(ISBLANK(A19),ISBLANK(B19),ISBLANK(C19)),"",IF(OR(ISBLANK(A19),ISBLANK(B19),ISBLANK(C19)),"-", LOOKUP(B19,'Type de table'!C:C,'Type de table'!F:F) &IF(ISBLANK(C19),""," "&LOOKUP(C19,'Objets de gestion'!C:C,'Objets de gestion'!E:E)) &IF(ISBLANK(D19),""," "&LOOKUP(D19,'Objets de gestion'!C:C,'Objets de gestion'!E:E)) &IF(ISBLANK(E19),""," "&LOOKUP(E19,'Objets de gestion'!C:C,'Objets de gestion'!E:E)) &IF(ISBLANK(F19),""," "&LOOKUP(F19,'Objets de gestion'!C:C,'Objets de gestion'!E:E)) )) | L19: =IF(AND(ISBLANK(A19),ISBLANK(B19),ISBLANK(C19)),"",IF(OR(ISBLANK(A19),ISBLANK(B19),ISBLANK(C19)),"-",B19))
G20: =IF(ISBLANK(A20),"",LOOKUP(A20,BIB!A:A,BIB!C:C)) | H20: =IF(AND(ISBLANK(A20),ISBLANK(B20),ISBLANK(C20)),"",IF(OR(ISBLANK(A20),ISBLANK(B20),ISBLANK(C20)),"-",LEN(Tableau4[[#This Row],[Colonne9]]))) | I20: =IF(AND(ISBLANK(A20),ISBLANK(B20),ISBLANK(C20)),"",IF(OR(ISBLANK(A20),ISBLANK(B20),ISBLANK(C20)),"à compléter",UPPER(LOOKUP(A20,BIB!A:A,BIB!B:B)&LOOKUP(B20,'Type de table'!C:C,'Type de table'!B:B) &IF(COUNTIF('Objets de gestion'!C:C,F20)=0,"","_"&LOOKUP(F20,'Objets de gestion'!C:C,'Objets de gestion'!F:F)) &IF(COUNTIF('Objets de gestion'!C:C,E20)=0,"","_"&LOOKUP(E20,'Objets de gestion'!C:C,'Objets de gestion'!F:F)) &IF(COUNTIF('Objets de gestion'!C:C,D20)=0,"","_"&LOOKUP(D20,'Objets de gestion'!C:C,'Objets de gestion'!F:F)) &IF(COUNTIF('Objets de gestion'!C:C,C20)=0,"","_"&LOOKUP(C20,'Objets de gestion'!C:C,'Objets de gestion'!F:F)) ))) | J20: =IF(AND(ISBLANK(A20),ISBLANK(B20),ISBLANK(C20)),"",IF(OR(ISBLANK(A20),ISBLANK(B20),ISBLANK(C20)),"-", LOOKUP(B20,'Type de table'!C:C,'Type de table'!E:E) &IF(ISBLANK(C20),""," "&C20) &IF(ISBLANK(D20),""," "&D20) &IF(ISBLANK(E20),""," "&E20) &IF(ISBLANK(F20),""," "&F20) )) | K20: =IF(AND(ISBLANK(A20),ISBLANK(B20),ISBLANK(C20)),"",IF(OR(ISBLANK(A20),ISBLANK(B20),ISBLANK(C20)),"-", LOOKUP(B20,'Type de table'!C:C,'Type de table'!F:F) &IF(ISBLANK(C20),""," "&LOOKUP(C20,'Objets de gestion'!C:C,'Objets de gestion'!E:E)) &IF(ISBLANK(D20),""," "&LOOKUP(D20,'Objets de gestion'!C:C,'Objets de gestion'!E:E)) &IF(ISBLANK(E20),""," "&LOOKUP(E20,'Objets de gestion'!C:C,'Objets de gestion'!E:E)) &IF(ISBLANK(F20),""," "&LOOKUP(F20,'Objets de gestion'!C:C,'Objets de gestion'!E:E)) )) | L20: =IF(AND(ISBLANK(A20),ISBLANK(B20),ISBLANK(C20)),"",IF(OR(ISBLANK(A20),ISBLANK(B20),ISBLANK(C20)),"-",B20))
G21: =IF(ISBLANK(A21),"",LOOKUP(A21,BIB!A:A,BIB!C:C)) | H21: =IF(AND(ISBLANK(A21),ISBLANK(B21),ISBLANK(C21)),"",IF(OR(ISBLANK(A21),ISBLANK(B21),ISBLANK(C21)),"-",LEN(Tableau4[[#This Row],[Colonne9]]))) | I21: =IF(AND(ISBLANK(A21),ISBLANK(B21),ISBLANK(C21)),"",IF(OR(ISBLANK(A21),ISBLANK(B21),ISBLANK(C21)),"à compléter",UPPER(LOOKUP(A21,BIB!A:A,BIB!B:B)&LOOKUP(B21,'Type de table'!C:C,'Type de table'!B:B) &IF(COUNTIF('Objets de gestion'!C:C,F21)=0,"","_"&LOOKUP(F21,'Objets de gestion'!C:C,'Objets de gestion'!F:F)) &IF(COUNTIF('Objets de gestion'!C:C,E21)=0,"","_"&LOOKUP(E21,'Objets de gestion'!C:C,'Objets de gestion'!F:F)) &IF(COUNTIF('Objets de gestion'!C:C,D21)=0,"","_"&LOOKUP(D21,'Objets de gestion'!C:C,'Objets de gestion'!F:F)) &IF(COUNTIF('Objets de gestion'!C:C,C21)=0,"","_"&LOOKUP(C21,'Objets de gestion'!C:C,'Objets de gestion'!F:F)) ))) | J21: =IF(AND(ISBLANK(A21),ISBLANK(B21),ISBLANK(C21)),"",IF(OR(ISBLANK(A21),ISBLANK(B21),ISBLANK(C21)),"-", LOOKUP(B21,'Type de table'!C:C,'Type de table'!E:E) &IF(ISBLANK(C21),""," "&C21) &IF(ISBLANK(D21),""," "&D21) &IF(ISBLANK(E21),""," "&E21) &IF(ISBLANK(F21),""," "&F21) )) | K21: =IF(AND(ISBLANK(A21),ISBLANK(B21),ISBLANK(C21)),"",IF(OR(ISBLANK(A21),ISBLANK(B21),ISBLANK(C21)),"-", LOOKUP(B21,'Type de table'!C:C,'Type de table'!F:F) &IF(ISBLANK(C21),""," "&LOOKUP(C21,'Objets de gestion'!C:C,'Objets de gestion'!E:E)) &IF(ISBLANK(D21),""," "&LOOKUP(D21,'Objets de gestion'!C:C,'Objets de gestion'!E:E)) &IF(ISBLANK(E21),""," "&LOOKUP(E21,'Objets de gestion'!C:C,'Objets de gestion'!E:E)) &IF(ISBLANK(F21),""," "&LOOKUP(F21,'Objets de gestion'!C:C,'Objets de gestion'!E:E)) )) | L21: =IF(AND(ISBLANK(A21),ISBLANK(B21),ISBLANK(C21)),"",IF(OR(ISBLANK(A21),ISBLANK(B21),ISBLANK(C21)),"-",B21))
G22: =IF(ISBLANK(A22),"",LOOKUP(A22,BIB!A:A,BIB!C:C)) | H22: =IF(AND(ISBLANK(A22),ISBLANK(B22),ISBLANK(C22)),"",IF(OR(ISBLANK(A22),ISBLANK(B22),ISBLANK(C22)),"-",LEN(Tableau4[[#This Row],[Colonne9]]))) | I22: =IF(AND(ISBLANK(A22),ISBLANK(B22),ISBLANK(C22)),"",IF(OR(ISBLANK(A22),ISBLANK(B22),ISBLANK(C22)),"à compléter",UPPER(LOOKUP(A22,BIB!A:A,BIB!B:B)&LOOKUP(B22,'Type de table'!C:C,'Type de table'!B:B) &IF(COUNTIF('Objets de gestion'!C:C,F22)=0,"","_"&LOOKUP(F22,'Objets de gestion'!C:C,'Objets de gestion'!F:F)) &IF(COUNTIF('Objets de gestion'!C:C,E22)=0,"","_"&LOOKUP(E22,'Objets de gestion'!C:C,'Objets de gestion'!F:F)) &IF(COUNTIF('Objets de gestion'!C:C,D22)=0,"","_"&LOOKUP(D22,'Objets de gestion'!C:C,'Objets de gestion'!F:F)) &IF(COUNTIF('Objets de gestion'!C:C,C22)=0,"","_"&LOOKUP(C22,'Objets de gestion'!C:C,'Objets de gestion'!F:F)) ))) | J22: =IF(AND(ISBLANK(A22),ISBLANK(B22),ISBLANK(C22)),"",IF(OR(ISBLANK(A22),ISBLANK(B22),ISBLANK(C22)),"-", LOOKUP(B22,'Type de table'!C:C,'Type de table'!E:E) &IF(ISBLANK(C22),""," "&C22) &IF(ISBLANK(D22),""," "&D22) &IF(ISBLANK(E22),""," "&E22) &IF(ISBLANK(F22),""," "&F22) )) | K22: =IF(AND(ISBLANK(A22),ISBLANK(B22),ISBLANK(C22)),"",IF(OR(ISBLANK(A22),ISBLANK(B22),ISBLANK(C22)),"-", LOOKUP(B22,'Type de table'!C:C,'Type de table'!F:F) &IF(ISBLANK(C22),""," "&LOOKUP(C22,'Objets de gestion'!C:C,'Objets de gestion'!E:E)) &IF(ISBLANK(D22),""," "&LOOKUP(D22,'Objets de gestion'!C:C,'Objets de gestion'!E:E)) &IF(ISBLANK(E22),""," "&LOOKUP(E22,'Objets de gestion'!C:C,'Objets de gestion'!E:E)) &IF(ISBLANK(F22),""," "&LOOKUP(F22,'Objets de gestion'!C:C,'Objets de gestion'!E:E)) )) | L22: =IF(AND(ISBLANK(A22),ISBLANK(B22),ISBLANK(C22)),"",IF(OR(ISBLANK(A22),ISBLANK(B22),ISBLANK(C22)),"-",B22))
G23: =IF(ISBLANK(A23),"",LOOKUP(A23,BIB!A:A,BIB!C:C)) | H23: =IF(AND(ISBLANK(A23),ISBLANK(B23),ISBLANK(C23)),"",IF(OR(ISBLANK(A23),ISBLANK(B23),ISBLANK(C23)),"-",LEN(Tableau4[[#This Row],[Colonne9]]))) | I23: =IF(AND(ISBLANK(A23),ISBLANK(B23),ISBLANK(C23)),"",IF(OR(ISBLANK(A23),ISBLANK(B23),ISBLANK(C23)),"à compléter",UPPER(LOOKUP(A23,BIB!A:A,BIB!B:B)&LOOKUP(B23,'Type de table'!C:C,'Type de table'!B:B) &IF(COUNTIF('Objets de gestion'!C:C,F23)=0,"","_"&LOOKUP(F23,'Objets de gestion'!C:C,'Objets de gestion'!F:F)) &IF(COUNTIF('Objets de gestion'!C:C,E23)=0,"","_"&LOOKUP(E23,'Objets de gestion'!C:C,'Objets de gestion'!F:F)) &IF(COUNTIF('Objets de gestion'!C:C,D23)=0,"","_"&LOOKUP(D23,'Objets de gestion'!C:C,'Objets de gestion'!F:F)) &IF(COUNTIF('Objets de gestion'!C:C,C23)=0,"","_"&LOOKUP(C23,'Objets de gestion'!C:C,'Objets de gestion'!F:F)) ))) | J23: =IF(AND(ISBLANK(A23),ISBLANK(B23),ISBLANK(C23)),"",IF(OR(ISBLANK(A23),ISBLANK(B23),ISBLANK(C23)),"-", LOOKUP(B23,'Type de table'!C:C,'Type de table'!E:E) &IF(ISBLANK(C23),""," "&C23) &IF(ISBLANK(D23),""," "&D23) &IF(ISBLANK(E23),""," "&E23) &IF(ISBLANK(F23),""," "&F23) )) | K23: =IF(AND(ISBLANK(A23),ISBLANK(B23),ISBLANK(C23)),"",IF(OR(ISBLANK(A23),ISBLANK(B23),ISBLANK(C23)),"-", LOOKUP(B23,'Type de table'!C:C,'Type de table'!F:F) &IF(ISBLANK(C23),""," "&LOOKUP(C23,'Objets de gestion'!C:C,'Objets de gestion'!E:E)) &IF(ISBLANK(D23),""," "&LOOKUP(D23,'Objets de gestion'!C:C,'Objets de gestion'!E:E)) &IF(ISBLANK(E23),""," "&LOOKUP(E23,'Objets de gestion'!C:C,'Objets de gestion'!E:E)) &IF(ISBLANK(F23),""," "&LOOKUP(F23,'Objets de gestion'!C:C,'Objets de gestion'!E:E)) )) | L23: =IF(AND(ISBLANK(A23),ISBLANK(B23),ISBLANK(C23)),"",IF(OR(ISBLANK(A23),ISBLANK(B23),ISBLANK(C23)),"-",B23))
G24: =IF(ISBLANK(A24),"",LOOKUP(A24,BIB!A:A,BIB!C:C)) | H24: =IF(AND(ISBLANK(A24),ISBLANK(B24),ISBLANK(C24)),"",IF(OR(ISBLANK(A24),ISBLANK(B24),ISBLANK(C24)),"-",LEN(Tableau4[[#This Row],[Colonne9]]))) | I24: =IF(AND(ISBLANK(A24),ISBLANK(B24),ISBLANK(C24)),"",IF(OR(ISBLANK(A24),ISBLANK(B24),ISBLANK(C24)),"à compléter",UPPER(LOOKUP(A24,BIB!A:A,BIB!B:B)&LOOKUP(B24,'Type de table'!C:C,'Type de table'!B:B) &IF(COUNTIF('Objets de gestion'!C:C,F24)=0,"","_"&LOOKUP(F24,'Objets de gestion'!C:C,'Objets de gestion'!F:F)) &IF(COUNTIF('Objets de gestion'!C:C,E24)=0,"","_"&LOOKUP(E24,'Objets de gestion'!C:C,'Objets de gestion'!F:F)) &IF(COUNTIF('Objets de gestion'!C:C,D24)=0,"","_"&LOOKUP(D24,'Objets de gestion'!C:C,'Objets de gestion'!F:F)) &IF(COUNTIF('Objets de gestion'!C:C,C24)=0,"","_"&LOOKUP(C24,'Objets de gestion'!C:C,'Objets de gestion'!F:F)) ))) | J24: =IF(AND(ISBLANK(A24),ISBLANK(B24),ISBLANK(C24)),"",IF(OR(ISBLANK(A24),ISBLANK(B24),ISBLANK(C24)),"-", LOOKUP(B24,'Type de table'!C:C,'Type de table'!E:E) &IF(ISBLANK(C24),""," "&C24) &IF(ISBLANK(D24),""," "&D24) &IF(ISBLANK(E24),""," "&E24) &IF(ISBLANK(F24),""," "&F24) )) | K24: =IF(AND(ISBLANK(A24),ISBLANK(B24),ISBLANK(C24)),"",IF(OR(ISBLANK(A24),ISBLANK(B24),ISBLANK(C24)),"-", LOOKUP(B24,'Type de table'!C:C,'Type de table'!F:F) &IF(ISBLANK(C24),""," "&LOOKUP(C24,'Objets de gestion'!C:C,'Objets de gestion'!E:E)) &IF(ISBLANK(D24),""," "&LOOKUP(D24,'Objets de gestion'!C:C,'Objets de gestion'!E:E)) &IF(ISBLANK(E24),""," "&LOOKUP(E24,'Objets de gestion'!C:C,'Objets de gestion'!E:E)) &IF(ISBLANK(F24),""," "&LOOKUP(F24,'Objets de gestion'!C:C,'Objets de gestion'!E:E)) )) | L24: =IF(AND(ISBLANK(A24),ISBLANK(B24),ISBLANK(C24)),"",IF(OR(ISBLANK(A24),ISBLANK(B24),ISBLANK(C24)),"-",B24))
G25: =IF(ISBLANK(A25),"",LOOKUP(A25,BIB!A:A,BIB!C:C)) | H25: =IF(AND(ISBLANK(A25),ISBLANK(B25),ISBLANK(C25)),"",IF(OR(ISBLANK(A25),ISBLANK(B25),ISBLANK(C25)),"-",LEN(Tableau4[[#This Row],[Colonne9]]))) | I25: =IF(AND(ISBLANK(A25),ISBLANK(B25),ISBLANK(C25)),"",IF(OR(ISBLANK(A25),ISBLANK(B25),ISBLANK(C25)),"à compléter",UPPER(LOOKUP(A25,BIB!A:A,BIB!B:B)&LOOKUP(B25,'Type de table'!C:C,'Type de table'!B:B) &IF(COUNTIF('Objets de gestion'!C:C,F25)=0,"","_"&LOOKUP(F25,'Objets de gestion'!C:C,'Objets de gestion'!F:F)) &IF(COUNTIF('Objets de gestion'!C:C,E25)=0,"","_"&LOOKUP(E25,'Objets de gestion'!C:C,'Objets de gestion'!F:F)) &IF(COUNTIF('Objets de gestion'!C:C,D25)=0,"","_"&LOOKUP(D25,'Objets de gestion'!C:C,'Objets de gestion'!F:F)) &IF(COUNTIF('Objets de gestion'!C:C,C25)=0,"","_"&LOOKUP(C25,'Objets de gestion'!C:C,'Objets de gestion'!F:F)) ))) | J25: =IF(AND(ISBLANK(A25),ISBLANK(B25),ISBLANK(C25)),"",IF(OR(ISBLANK(A25),ISBLANK(B25),ISBLANK(C25)),"-", LOOKUP(B25,'Type de table'!C:C,'Type de table'!E:E) &IF(ISBLANK(C25),""," "&C25) &IF(ISBLANK(D25),""," "&D25) &IF(ISBLANK(E25),""," "&E25) &IF(ISBLANK(F25),""," "&F25) )) | K25: =IF(AND(ISBLANK(A25),ISBLANK(B25),ISBLANK(C25)),"",IF(OR(ISBLANK(A25),ISBLANK(B25),ISBLANK(C25)),"-", LOOKUP(B25,'Type de table'!C:C,'Type de table'!F:F) &IF(ISBLANK(C25),""," "&LOOKUP(C25,'Objets de gestion'!C:C,'Objets de gestion'!E:E)) &IF(ISBLANK(D25),""," "&LOOKUP(D25,'Objets de gestion'!C:C,'Objets de gestion'!E:E)) &IF(ISBLANK(E25),""," "&LOOKUP(E25,'Objets de gestion'!C:C,'Objets de gestion'!E:E)) &IF(ISBLANK(F25),""," "&LOOKUP(F25,'Objets de gestion'!C:C,'Objets de gestion'!E:E)) )) | L25: =IF(AND(ISBLANK(A25),ISBLANK(B25),ISBLANK(C25)),"",IF(OR(ISBLANK(A25),ISBLANK(B25),ISBLANK(C25)),"-",B25))
G26: =IF(ISBLANK(A26),"",LOOKUP(A26,BIB!A:A,BIB!C:C)) | H26: =IF(AND(ISBLANK(A26),ISBLANK(B26),ISBLANK(C26)),"",IF(OR(ISBLANK(A26),ISBLANK(B26),ISBLANK(C26)),"-",LEN(Tableau4[[#This Row],[Colonne9]]))) | I26: =IF(AND(ISBLANK(A26),ISBLANK(B26),ISBLANK(C26)),"",IF(OR(ISBLANK(A26),ISBLANK(B26),ISBLANK(C26)),"à compléter",UPPER(LOOKUP(A26,BIB!A:A,BIB!B:B)&LOOKUP(B26,'Type de table'!C:C,'Type de table'!B:B) &IF(COUNTIF('Objets de gestion'!C:C,F26)=0,"","_"&LOOKUP(F26,'Objets de gestion'!C:C,'Objets de gestion'!F:F)) &IF(COUNTIF('Objets de gestion'!C:C,E26)=0,"","_"&LOOKUP(E26,'Objets de gestion'!C:C,'Objets de gestion'!F:F)) &IF(COUNTIF('Objets de gestion'!C:C,D26)=0,"","_"&LOOKUP(D26,'Objets de gestion'!C:C,'Objets de gestion'!F:F)) &IF(COUNTIF('Objets de gestion'!C:C,C26)=0,"","_"&LOOKUP(C26,'Objets de gestion'!C:C,'Objets de gestion'!F:F)) ))) | J26: =IF(AND(ISBLANK(A26),ISBLANK(B26),ISBLANK(C26)),"",IF(OR(ISBLANK(A26),ISBLANK(B26),ISBLANK(C26)),"-", LOOKUP(B26,'Type de table'!C:C,'Type de table'!E:E) &IF(ISBLANK(C26),""," "&C26) &IF(ISBLANK(D26),""," "&D26) &IF(ISBLANK(E26),""," "&E26) &IF(ISBLANK(F26),""," "&F26) )) | K26: =IF(AND(ISBLANK(A26),ISBLANK(B26),ISBLANK(C26)),"",IF(OR(ISBLANK(A26),ISBLANK(B26),ISBLANK(C26)),"-", LOOKUP(B26,'Type de table'!C:C,'Type de table'!F:F) &IF(ISBLANK(C26),""," "&LOOKUP(C26,'Objets de gestion'!C:C,'Objets de gestion'!E:E)) &IF(ISBLANK(D26),""," "&LOOKUP(D26,'Objets de gestion'!C:C,'Objets de gestion'!E:E)) &IF(ISBLANK(E26),""," "&LOOKUP(E26,'Objets de gestion'!C:C,'Objets de gestion'!E:E)) &IF(ISBLANK(F26),""," "&LOOKUP(F26,'Objets de gestion'!C:C,'Objets de gestion'!E:E)) )) | L26: =IF(AND(ISBLANK(A26),ISBLANK(B26),ISBLANK(C26)),"",IF(OR(ISBLANK(A26),ISBLANK(B26),ISBLANK(C26)),"-",B26))
G27: =IF(ISBLANK(A27),"",LOOKUP(A27,BIB!A:A,BIB!C:C)) | H27: =IF(AND(ISBLANK(A27),ISBLANK(B27),ISBLANK(C27)),"",IF(OR(ISBLANK(A27),ISBLANK(B27),ISBLANK(C27)),"-",LEN(Tableau4[[#This Row],[Colonne9]]))) | I27: =IF(AND(ISBLANK(A27),ISBLANK(B27),ISBLANK(C27)),"",IF(OR(ISBLANK(A27),ISBLANK(B27),ISBLANK(C27)),"à compléter",UPPER(LOOKUP(A27,BIB!A:A,BIB!B:B)&LOOKUP(B27,'Type de table'!C:C,'Type de table'!B:B) &IF(COUNTIF('Objets de gestion'!C:C,F27)=0,"","_"&LOOKUP(F27,'Objets de gestion'!C:C,'Objets de gestion'!F:F)) &IF(COUNTIF('Objets de gestion'!C:C,E27)=0,"","_"&LOOKUP(E27,'Objets de gestion'!C:C,'Objets de gestion'!F:F)) &IF(COUNTIF('Objets de gestion'!C:C,D27)=0,"","_"&LOOKUP(D27,'Objets de gestion'!C:C,'Objets de gestion'!F:F)) &IF(COUNTIF('Objets de gestion'!C:C,C27)=0,"","_"&LOOKUP(C27,'Objets de gestion'!C:C,'Objets de gestion'!F:F)) ))) | J27: =IF(AND(ISBLANK(A27),ISBLANK(B27),ISBLANK(C27)),"",IF(OR(ISBLANK(A27),ISBLANK(B27),ISBLANK(C27)),"-", LOOKUP(B27,'Type de table'!C:C,'Type de table'!E:E) &IF(ISBLANK(C27),""," "&C27) &IF(ISBLANK(D27),""," "&D27) &IF(ISBLANK(E27),""," "&E27) &IF(ISBLANK(F27),""," "&F27) )) | K27: =IF(AND(ISBLANK(A27),ISBLANK(B27),ISBLANK(C27)),"",IF(OR(ISBLANK(A27),ISBLANK(B27),ISBLANK(C27)),"-", LOOKUP(B27,'Type de table'!C:C,'Type de table'!F:F) &IF(ISBLANK(C27),""," "&LOOKUP(C27,'Objets de gestion'!C:C,'Objets de gestion'!E:E)) &IF(ISBLANK(D27),""," "&LOOKUP(D27,'Objets de gestion'!C:C,'Objets de gestion'!E:E)) &IF(ISBLANK(E27),""," "&LOOKUP(E27,'Objets de gestion'!C:C,'Objets de gestion'!E:E)) &IF(ISBLANK(F27),""," "&LOOKUP(F27,'Objets de gestion'!C:C,'Objets de gestion'!E:E)) )) | L27: =IF(AND(ISBLANK(A27),ISBLANK(B27),ISBLANK(C27)),"",IF(OR(ISBLANK(A27),ISBLANK(B27),ISBLANK(C27)),"-",B27))
... G74: =IF(ISBLANK(A74),"",LOOKUP(A74,BIB!A:A,BIB!C:C)) | H74: =IF(AND(ISBLANK(A74),ISBLANK(B74),ISBLANK(C74)),"",IF(OR(ISBLANK(A74),ISBLANK(B74),ISBLANK(C74)),"-",LEN(Tableau4[[#This Row],[Colonne9]]))) | I74: =IF(AND(ISBLANK(A74),ISBLANK(B74),ISBLANK(C74)),"",IF(OR(ISBLANK(A74),ISBLANK(B74),ISBLANK(C74)),"à compléter",UPPER(LOOKUP(A74,BIB!A:A,BIB!B:B)&LOOKUP(B74,'Type de table'!C:C,'Type de table'!B:B) &IF(COUNTIF('Objets de gestion'!C:C,F74)=0,"","_"&LOOKUP(F74,'Objets de gestion'!C:C,'Objets de gestion'!F:F)) &IF(COUNTIF('Objets de gestion'!C:C,E74)=0,"","_"&LOOKUP(E74,'Objets de gestion'!C:C,'Objets de gestion'!F:F)) &IF(COUNTIF('Objets de gestion'!C:C,D74)=0,"","_"&LOOKUP(D74,'Objets de gestion'!C:C,'Objets de gestion'!F:F)) &IF(COUNTIF('Objets de gestion'!C:C,C74)=0,"","_"&LOOKUP(C74,'Objets de gestion'!C:C,'Objets de gestion'!F:F)) ))) | J74: =IF(AND(ISBLANK(A74),ISBLANK(B74),ISBLANK(C74)),"",IF(OR(ISBLANK(A74),ISBLANK(B74),ISBLANK(C74)),"-", LOOKUP(B74,'Type de table'!C:C,'Type de table'!E:E) &IF(ISBLANK(C74),""," "&C74) &IF(ISBLANK(D74),""," "&D74) &IF(ISBLANK(E74),""," "&E74) &IF(ISBLANK(F74),""," "&F74) )) | K74: =IF(AND(ISBLANK(A74),ISBLANK(B74),ISBLANK(C74)),"",IF(OR(ISBLANK(A74),ISBLANK(B74),ISBLANK(C74)),"-", LOOKUP(B74,'Type de table'!C:C,'Type de table'!F:F) &IF(ISBLANK(C74),""," "&LOOKUP(C74,'Objets de gestion'!C:C,'Objets de gestion'!E:E)) &IF(ISBLANK(D74),""," "&LOOKUP(D74,'Objets de gestion'!C:C,'Objets de gestion'!E:E)) &IF(ISBLANK(E74),""," "&LOOKUP(E74,'Objets de gestion'!C:C,'Objets de gestion'!E:E)) &IF(ISBLANK(F74),""," "&LOOKUP(F74,'Objets de gestion'!C:C,'Objets de gestion'!E:E)) )) | L74: =IF(AND(ISBLANK(A74),ISBLANK(B74),ISBLANK(C74)),"",IF(OR(ISBLANK(A74),ISBLANK(B74),ISBLANK(C74)),"-",B74))

Sheet Champs
A1: Nom du BIB | B1: Type de champ | C1: Nature | D1: article 1 | E1: Objet de gestion 1 | F1: article 2 | G1: Objet de gestion 2 | H1: article 3 | I1: Objet de gestion 3 | J1: article 4 | K1: Objet de gestion 4 | L1: Ordre trigramme | M1: Nb car | N1: Code | O1: Nom français | P1: Nom anglais | Q1: Type de données | R1: Périmètre
M2: =IF(AND(ISBLANK(A2),ISBLANK(B2),ISBLANK(E2),ISBLANK(G2),ISBLANK(L2)),"",IF(OR(ISBLANK(A2),ISBLANK(B2),ISBLANK(E2),ISBLANK(G2),ISBLANK(L2)),"-",LEN(Tableau47[[#This Row],[Code]]))) | N2: =IF(AND(ISBLANK(A2),ISBLANK(B2),ISBLANK(C2),ISBLANK(E2),ISBLANK(L2)),"",IF(OR(ISBLANK(A2),ISBLANK(B2),ISBLANK(C2),ISBLANK(E2),ISBLANK(L2)),"à compléter", IF(L2="Normal", LOOKUP(B2,'Type de champ'!B:B,'Type de champ'!A:A) &IF(COUNTIF('Objets de gestion'!C:C,K2)=0,"","_"&LOOKUP(K2,'Objets de gestion'!C:C,'Objets de gestion'!F:F)) &IF(COUNTIF('Objets de gestion'!C:C,I2)=0,"","_"&LOOKUP(I2,'Objets de gestion'!C:C,'Objets de gestion'!F:F)) &IF(COUNTIF('Objets de gestion'!C:C,G2)=0,"","_"&LOOKUP(G2,'Objets de gestion'!C:C,'Objets de gestion'!F:F)) &IF(COUNTIF('Objets de gestion'!C:C,E2)=0,"","_"&LOOKUP(E2,'Objets de gestion'!C:C,'Objets de gestion'!F:F)) &IF(OR(C2="booléen",COUNTIF('Objets de gestion'!C:C,C2)=0),"","_"&LOOKUP(C2,'Objets de gestion'!C:C,'Objets de gestion'!F:F)), IF(L2="Forcé", LOOKUP(B2,'Type de champ'!B:B,'Type de champ'!A:A) &IF(COUNTIF('Objets de gestion'!C:C,E2)=0,"","_"&LOOKUP(E2,'Objets de gestion'!C:C,'Objets de gestion'!F:F)) &IF(COUNTIF('Objets de gestion'!C:C,G2)=0,"","_"&LOOKUP(G2,'Objets de gestion'!C:C,'Objets de gestion'!F:F)) &IF(COUNTIF('Objets de gestion'!C:C,I2)=0,"","_"&LOOKUP(I2,'Objets de gestion'!C:C,'Objets de gestion'!F:F)) &IF(COUNTIF('Objets de gestion'!C:C,K2)=0,"","_"&LOOKUP(K2,'Objets de gestion'!C:C,'Objets de gestion'!F:F)) &IF(OR(C2="booléen",COUNTIF('Objets de gestion'!C:C,C2)=0),"","_"&LOOKUP(C2,'Objets de gestion'!C:C,'Objets de gestion'!F:F)) )))) | O2: =IF(AND(ISBLANK(A2),ISBLANK(B2),ISBLANK(C2),ISBLANK(E2),ISBLANK(L2)),"",IF(OR(ISBLANK(A2),ISBLANK(B2),ISBLANK(C2),ISBLANK(E2),ISBLANK(L2)),"-", C2&" "&IF(ISBLANK(E2),"",D2&" "&E2&" ")&IF(ISBLANK(G2),"",F2&" "&G2&" ")&IF(ISBLANK(I2),"",H2&" "&I2&" ")&IF(ISBLANK(K2),"",J2&" "&K2&" "))) | P2: =IF(AND(ISBLANK(A2),ISBLANK(B2),ISBLANK(C2),ISBLANK(E2),ISBLANK(L2)),"",IF(OR(ISBLANK(A2),ISBLANK(B2),ISBLANK(C2),ISBLANK(E2),ISBLANK(L2)),"-", IF(ISBLANK(C2),"",LOOKUP(C2,'Objets de gestion'!C:C,'Objets de gestion'!E:E)) &IF(ISBLANK(D2),""," "&LOOKUP(D2,Articles!A:A,Articles!B:B)) &IF(ISBLANK(E2),""," "&LOOKUP(E2,'Objets de gestion'!C:C,'Objets de gestion'!E:E)) &IF(ISBLANK(F2),""," "&LOOKUP(F2,Articles!A:A,Articles!B:B)) &IF(ISBLANK(G2),""," "&LOOKUP(G2,'Objets de gestion'!C:C,'Objets de gestion'!E:E)) &IF(ISBLANK(H2),""," "&LOOKUP(H2,Articles!A:A,Articles!B:B)) &IF(ISBLANK(I2),""," "&LOOKUP(I2,'Objets de gestion'!C:C,'Objets de gestion'!E:E)) &IF(ISBLANK(J2),""," "&LOOKUP(J2,Articles!A:A,Articles!B:B)) &IF(ISBLANK(K2),""," "&LOOKUP(K2,'Objets de gestion'!C:C,'Objets de gestion'!E:E)) )) | Q2: =IF(AND(ISBLANK(A2),ISBLANK(B2),ISBLANK(C2),ISBLANK(E2),ISBLANK(L2)),"",IF(OR(ISBLANK(A2),ISBLANK(B2),ISBLANK(C2),ISBLANK(E2),ISBLANK(L2)),"-", LOOKUP(B2,'Type de champ'!B:B,'Type de champ'!C:C))) | R2: =IF(AND(ISBLANK(A2),ISBLANK(B2),ISBLANK(E2),ISBLANK(G2),ISBLANK(L2)),"",IF(OR(ISBLANK(A2),ISBLANK(B2),ISBLANK(E2),ISBLANK(G2),ISBLANK(L2)),"-", A2))
M3: =IF(AND(ISBLANK(A3),ISBLANK(B3),ISBLANK(E3),ISBLANK(G3),ISBLANK(L3)),"",IF(OR(ISBLANK(A3),ISBLANK(B3),ISBLANK(E3),ISBLANK(G3),ISBLANK(L3)),"-",LEN(Tableau47[[#This Row],[Code]]))) | N3: =IF(AND(ISBLANK(A3),ISBLANK(B3),ISBLANK(C3),ISBLANK(E3),ISBLANK(L3)),"",IF(OR(ISBLANK(A3),ISBLANK(B3),ISBLANK(C3),ISBLANK(E3),ISBLANK(L3)),"à compléter", IF(L3="Normal", LOOKUP(B3,'Type de champ'!B:B,'Type de champ'!A:A) &IF(COUNTIF('Objets de gestion'!C:C,K3)=0,"","_"&LOOKUP(K3,'Objets de gestion'!C:C,'Objets de gestion'!F:F)) &IF(COUNTIF('Objets de gestion'!C:C,I3)=0,"","_"&LOOKUP(I3,'Objets de gestion'!C:C,'Objets de gestion'!F:F)) &IF(COUNTIF('Objets de gestion'!C:C,G3)=0,"","_"&LOOKUP(G3,'Objets de gestion'!C:C,'Objets de gestion'!F:F)) &IF(COUNTIF('Objets de gestion'!C:C,E3)=0,"","_"&LOOKUP(E3,'Objets de gestion'!C:C,'Objets de gestion'!F:F)) &IF(OR(C3="booléen",COUNTIF('Objets de gestion'!C:C,C3)=0),"","_"&LOOKUP(C3,'Objets de gestion'!C:C,'Objets de gestion'!F:F)), IF(L3="Forcé", LOOKUP(B3,'Type de champ'!B:B,'Type de champ'!A:A) &IF(COUNTIF('Objets de gestion'!C:C,E3)=0,"","_"&LOOKUP(E3,'Objets de gestion'!C:C,'Objets de gestion'!F:F)) &IF(COUNTIF('Objets de gestion'!C:C,G3)=0,"","_"&LOOKUP(G3,'Objets de gestion'!C:C,'Objets de gestion'!F:F)) &IF(COUNTIF('Objets de gestion'!C:C,I3)=0,"","_"&LOOKUP(I3,'Objets de gestion'!C:C,'Objets de gestion'!F:F)) &IF(COUNTIF('Objets de gestion'!C:C,K3)=0,"","_"&LOOKUP(K3,'Objets de gestion'!C:C,'Objets de gestion'!F:F)) &IF(OR(C3="booléen",COUNTIF('Objets de gestion'!C:C,C3)=0),"","_"&LOOKUP(C3,'Objets de gestion'!C:C,'Objets de gestion'!F:F)) )))) | O3: =IF(AND(ISBLANK(A3),ISBLANK(B3),ISBLANK(C3),ISBLANK(E3),ISBLANK(L3)),"",IF(OR(ISBLANK(A3),ISBLANK(B3),ISBLANK(C3),ISBLANK(E3),ISBLANK(L3)),"-", C3&" "&IF(ISBLANK(E3),"",D3&" "&E3&" ")&IF(ISBLANK(G3),"",F3&" "&G3&" ")&IF(ISBLANK(I3),"",H3&" "&I3&" ")&IF(ISBLANK(K3),"",J3&" "&K3&" "))) | P3: =IF(AND(ISBLANK(A3),ISBLANK(B3),ISBLANK(C3),ISBLANK(E3),ISBLANK(L3)),"",IF(OR(ISBLANK(A3),ISBLANK(B3),ISBLANK(C3),ISBLANK(E3),ISBLANK(L3)),"-", IF(ISBLANK(C3),"",LOOKUP(C3,'Objets de gestion'!C:C,'Objets de gestion'!E:E)) &IF(ISBLANK(D3),""," "&LOOKUP(D3,Articles!A:A,Articles!B:B)) &IF(ISBLANK(E3),""," "&LOOKUP(E3,'Objets de gestion'!C:C,'Objets de gestion'!E:E)) &IF(ISBLANK(F3),""," "&LOOKUP(F3,Articles!A:A,Articles!B:B)) &IF(ISBLANK(G3),""," "&LOOKUP(G3,'Objets de gestion'!C:C,'Objets de gestion'!E:E)) &IF(ISBLANK(H3),""," "&LOOKUP(H3,Articles!A:A,Articles!B:B)) &IF(ISBLANK(I3),""," "&LOOKUP(I3,'Objets de gestion'!C:C,'Objets de gestion'!E:E)) &IF(ISBLANK(J3),""," "&LOOKUP(J3,Articles!A:A,Articles!B:B)) &IF(ISBLANK(K3),""," "&LOOKUP(K3,'Objets de gestion'!C:C,'Objets de gestion'!E:E)) )) | Q3: =IF(AND(ISBLANK(A3),ISBLANK(B3),ISBLANK(C3),ISBLANK(E3),ISBLANK(L3)),"",IF(OR(ISBLANK(A3),ISBLANK(B3),ISBLANK(C3),ISBLANK(E3),ISBLANK(L3)),"-", LOOKUP(B3,'Type de champ'!B:B,'Type de champ'!C:C))) | R3: =IF(AND(ISBLANK(A3),ISBLANK(B3),ISBLANK(E3),ISBLANK(G3),ISBLANK(L3)),"",IF(OR(ISBLANK(A3),ISBLANK(B3),ISBLANK(E3),ISBLANK(G3),ISBLANK(L3)),"-", A3))
M4: =IF(AND(ISBLANK(A4),ISBLANK(B4),ISBLANK(E4),ISBLANK(G4),ISBLANK(L4)),"",IF(OR(ISBLANK(A4),ISBLANK(B4),ISBLANK(E4),ISBLANK(G4),ISBLANK(L4)),"-",LEN(Tableau47[[#This Row],[Code]]))) | N4: =IF(AND(ISBLANK(A4),ISBLANK(B4),ISBLANK(C4),ISBLANK(E4),ISBLANK(L4)),"",IF(OR(ISBLANK(A4),ISBLANK(B4),ISBLANK(C4),ISBLANK(E4),ISBLANK(L4)),"à compléter", IF(L4="Normal", LOOKUP(B4,'Type de champ'!B:B,'Type de champ'!A:A) &IF(COUNTIF('Objets de gestion'!C:C,K4)=0,"","_"&LOOKUP(K4,'Objets de gestion'!C:C,'Objets de gestion'!F:F)) &IF(COUNTIF('Objets de gestion'!C:C,I4)=0,"","_"&LOOKUP(I4,'Objets de gestion'!C:C,'Objets de gestion'!F:F)) &IF(COUNTIF('Objets de gestion'!C:C,G4)=0,"","_"&LOOKUP(G4,'Objets de gestion'!C:C,'Objets de gestion'!F:F)) &IF(COUNTIF('Objets de gestion'!C:C,E4)=0,"","_"&LOOKUP(E4,'Objets de gestion'!C:C,'Objets de gestion'!F:F)) &IF(OR(C4="booléen",COUNTIF('Objets de gestion'!C:C,C4)=0),"","_"&LOOKUP(C4,'Objets de gestion'!C:C,'Objets de gestion'!F:F)), IF(L4="Forcé", LOOKUP(B4,'Type de champ'!B:B,'Type de champ'!A:A) &IF(COUNTIF('Objets de gestion'!C:C,E4)=0,"","_"&LOOKUP(E4,'Objets de gestion'!C:C,'Objets de gestion'!F:F)) &IF(COUNTIF('Objets de gestion'!C:C,G4)=0,"","_"&LOOKUP(G4,'Objets de gestion'!C:C,'Objets de gestion'!F:F)) &IF(COUNTIF('Objets de gestion'!C:C,I4)=0,"","_"&LOOKUP(I4,'Objets de gestion'!C:C,'Objets de gestion'!F:F)) &IF(COUNTIF('Objets de gestion'!C:C,K4)=0,"","_"&LOOKUP(K4,'Objets de gestion'!C:C,'Objets de gestion'!F:F)) &IF(OR(C4="booléen",COUNTIF('Objets de gestion'!C:C,C4)=0),"","_"&LOOKUP(C4,'Objets de gestion'!C:C,'Objets de gestion'!F:F)) )))) | O4: =IF(AND(ISBLANK(A4),ISBLANK(B4),ISBLANK(C4),ISBLANK(E4),ISBLANK(L4)),"",IF(OR(ISBLANK(A4),ISBLANK(B4),ISBLANK(C4),ISBLANK(E4),ISBLANK(L4)),"-", C4&" "&IF(ISBLANK(E4),"",D4&" "&E4&" ")&IF(ISBLANK(G4),"",F4&" "&G4&" ")&IF(ISBLANK(I4),"",H4&" "&I4&" ")&IF(ISBLANK(K4),"",J4&" "&K4&" "))) | P4: =IF(AND(ISBLANK(A4),ISBLANK(B4),ISBLANK(C4),ISBLANK(E4),ISBLANK(L4)),"",IF(OR(ISBLANK(A4),ISBLANK(B4),ISBLANK(C4),ISBLANK(E4),ISBLANK(L4)),"-", IF(ISBLANK(C4),"",LOOKUP(C4,'Objets de gestion'!C:C,'Objets de gestion'!E:E)) &IF(ISBLANK(D4),""," "&LOOKUP(D4,Articles!A:A,Articles!B:B)) &IF(ISBLANK(E4),""," "&LOOKUP(E4,'Objets de gestion'!C:C,'Objets de gestion'!E:E)) &IF(ISBLANK(F4),""," "&LOOKUP(F4,Articles!A:A,Articles!B:B)) &IF(ISBLANK(G4),""," "&LOOKUP(G4,'Objets de gestion'!C:C,'Objets de gestion'!E:E)) &IF(ISBLANK(H4),""," "&LOOKUP(H4,Articles!A:A,Articles!B:B)) &IF(ISBLANK(I4),""," "&LOOKUP(I4,'Objets de gestion'!C:C,'Objets de gestion'!E:E)) &IF(ISBLANK(J4),""," "&LOOKUP(J4,Articles!A:A,Articles!B:B)) &IF(ISBLANK(K4),""," "&LOOKUP(K4,'Objets de gestion'!C:C,'Objets de gestion'!E:E)) )) | Q4: =IF(AND(ISBLANK(A4),ISBLANK(B4),ISBLANK(C4),ISBLANK(E4),ISBLANK(L4)),"",IF(OR(ISBLANK(A4),ISBLANK(B4),ISBLANK(C4),ISBLANK(E4),ISBLANK(L4)),"-", LOOKUP(B4,'Type de champ'!B:B,'Type de champ'!C:C))) | R4: =IF(AND(ISBLANK(A4),ISBLANK(B4),ISBLANK(E4),ISBLANK(G4),ISBLANK(L4)),"",IF(OR(ISBLANK(A4),ISBLANK(B4),ISBLANK(E4),ISBLANK(G4),ISBLANK(L4)),"-", A4))
M5: =IF(AND(ISBLANK(A5),ISBLANK(B5),ISBLANK(E5),ISBLANK(G5),ISBLANK(L5)),"",IF(OR(ISBLANK(A5),ISBLANK(B5),ISBLANK(E5),ISBLANK(G5),ISBLANK(L5)),"-",LEN(Tableau47[[#This Row],[Code]]))) | N5: =IF(AND(ISBLANK(A5),ISBLANK(B5),ISBLANK(C5),ISBLANK(E5),ISBLANK(L5)),"",IF(OR(ISBLANK(A5),ISBLANK(B5),ISBLANK(C5),ISBLANK(E5),ISBLANK(L5)),"à compléter", IF(L5="Normal", LOOKUP(B5,'Type de champ'!B:B,'Type de champ'!A:A) &IF(COUNTIF('Objets de gestion'!C:C,K5)=0,"","_"&LOOKUP(K5,'Objets de gestion'!C:C,'Objets de gestion'!F:F)) &IF(COUNTIF('Objets de gestion'!C:C,I5)=0,"","_"&LOOKUP(I5,'Objets de gestion'!C:C,'Objets de gestion'!F:F)) &IF(COUNTIF('Objets de gestion'!C:C,G5)=0,"","_"&LOOKUP(G5,'Objets de gestion'!C:C,'Objets de gestion'!F:F)) &IF(COUNTIF('Objets de gestion'!C:C,E5)=0,"","_"&LOOKUP(E5,'Objets de gestion'!C:C,'Objets de gestion'!F:F)) &IF(OR(C5="booléen",COUNTIF('Objets de gestion'!C:C,C5)=0),"","_"&LOOKUP(C5,'Objets de gestion'!C:C,'Objets de gestion'!F:F)), IF(L5="Forcé", LOOKUP(B5,'Type de champ'!B:B,'Type de champ'!A:A) &IF(COUNTIF('Objets de gestion'!C:C,E5)=0,"","_"&LOOKUP(E5,'Objets de gestion'!C:C,'Objets de gestion'!F:F)) &IF(COUNTIF('Objets de gestion'!C:C,G5)=0,"","_"&LOOKUP(G5,'Objets de gestion'!C:C,'Objets de gestion'!F:F)) &IF(COUNTIF('Objets de gestion'!C:C,I5)=0,"","_"&LOOKUP(I5,'Objets de gestion'!C:C,'Objets de gestion'!F:F)) &IF(COUNTIF('Objets de gestion'!C:C,K5)=0,"","_"&LOOKUP(K5,'Objets de gestion'!C:C,'Objets de gestion'!F:F)) &IF(OR(C5="booléen",COUNTIF('Objets de gestion'!C:C,C5)=0),"","_"&LOOKUP(C5,'Objets de gestion'!C:C,'Objets de gestion'!F:F)) )))) | O5: =IF(AND(ISBLANK(A5),ISBLANK(B5),ISBLANK(C5),ISBLANK(E5),ISBLANK(L5)),"",IF(OR(ISBLANK(A5),ISBLANK(B5),ISBLANK(C5),ISBLANK(E5),ISBLANK(L5)),"-", C5&" "&IF(ISBLANK(E5),"",D5&" "&E5&" ")&IF(ISBLANK(G5),"",F5&" "&G5&" ")&IF(ISBLANK(I5),"",H5&" "&I5&" ")&IF(ISBLANK(K5),"",J5&" "&K5&" "))) | P5: =IF(AND(ISBLANK(A5),ISBLANK(B5),ISBLANK(C5),ISBLANK(E5),ISBLANK(L5)),"",IF(OR(ISBLANK(A5),ISBLANK(B5),ISBLANK(C5),ISBLANK(E5),ISBLANK(L5)),"-", IF(ISBLANK(C5),"",LOOKUP(C5,'Objets de gestion'!C:C,'Objets de gestion'!E:E)) &IF(ISBLANK(D5),""," "&LOOKUP(D5,Articles!A:A,Articles!B:B)) &IF(ISBLANK(E5),""," "&LOOKUP(E5,'Objets de gestion'!C:C,'Objets de gestion'!E:E)) &IF(ISBLANK(F5),""," "&LOOKUP(F5,Articles!A:A,Articles!B:B)) &IF(ISBLANK(G5),""," "&LOOKUP(G5,'Objets de gestion'!C:C,'Objets de gestion'!E:E)) &IF(ISBLANK(H5),""," "&LOOKUP(H5,Articles!A:A,Articles!B:B)) &IF(ISBLANK(I5),""," "&LOOKUP(I5,'Objets de gestion'!C:C,'Objets de gestion'!E:E)) &IF(ISBLANK(J5),""," "&LOOKUP(J5,Articles!A:A,Articles!B:B)) &IF(ISBLANK(K5),""," "&LOOKUP(K5,'Objets de gestion'!C:C,'Objets de gestion'!E:E)) )) | Q5: =IF(AND(ISBLANK(A5),ISBLANK(B5),ISBLANK(C5),ISBLANK(E5),ISBLANK(L5)),"",IF(OR(ISBLANK(A5),ISBLANK(B5),ISBLANK(C5),ISBLANK(E5),ISBLANK(L5)),"-", LOOKUP(B5,'Type de champ'!B:B,'Type de champ'!C:C))) | R5: =IF(AND(ISBLANK(A5),ISBLANK(B5),ISBLANK(E5),ISBLANK(G5),ISBLANK(L5)),"",IF(OR(ISBLANK(A5),ISBLANK(B5),ISBLANK(E5),ISBLANK(G5),ISBLANK(L5)),"-", A5))
M6: =IF(AND(ISBLANK(A6),ISBLANK(B6),ISBLANK(E6),ISBLANK(G6),ISBLANK(L6)),"",IF(OR(ISBLANK(A6),ISBLANK(B6),ISBLANK(E6),ISBLANK(G6),ISBLANK(L6)),"-",LEN(Tableau47[[#This Row],[Code]]))) | N6: =IF(AND(ISBLANK(A6),ISBLANK(B6),ISBLANK(C6),ISBLANK(E6),ISBLANK(L6)),"",IF(OR(ISBLANK(A6),ISBLANK(B6),ISBLANK(C6),ISBLANK(E6),ISBLANK(L6)),"à compléter", IF(L6="Normal", LOOKUP(B6,'Type de champ'!B:B,'Type de champ'!A:A) &IF(COUNTIF('Objets de gestion'!C:C,K6)=0,"","_"&LOOKUP(K6,'Objets de gestion'!C:C,'Objets de gestion'!F:F)) &IF(COUNTIF('Objets de gestion'!C:C,I6)=0,"","_"&LOOKUP(I6,'Objets de gestion'!C:C,'Objets de gestion'!F:F)) &IF(COUNTIF('Objets de gestion'!C:C,G6)=0,"","_"&LOOKUP(G6,'Objets de gestion'!C:C,'Objets de gestion'!F:F)) &IF(COUNTIF('Objets de gestion'!C:C,E6)=0,"","_"&LOOKUP(E6,'Objets de gestion'!C:C,'Objets de gestion'!F:F)) &IF(OR(C6="booléen",COUNTIF('Objets de gestion'!C:C,C6)=0),"","_"&LOOKUP(C6,'Objets de gestion'!C:C,'Objets de gestion'!F:F)), IF(L6="Forcé", LOOKUP(B6,'Type de champ'!B:B,'Type de champ'!A:A) &IF(COUNTIF('Objets de gestion'!C:C,E6)=0,"","_"&LOOKUP(E6,'Objets de gestion'!C:C,'Objets de gestion'!F:F)) &IF(COUNTIF('Objets de gestion'!C:C,G6)=0,"","_"&LOOKUP(G6,'Objets de gestion'!C:C,'Objets de gestion'!F:F)) &IF(COUNTIF('Objets de gestion'!C:C,I6)=0,"","_"&LOOKUP(I6,'Objets de gestion'!C:C,'Objets de gestion'!F:F)) &IF(COUNTIF('Objets de gestion'!C:C,K6)=0,"","_"&LOOKUP(K6,'Objets de gestion'!C:C,'Objets de gestion'!F:F)) &IF(OR(C6="booléen",COUNTIF('Objets de gestion'!C:C,C6)=0),"","_"&LOOKUP(C6,'Objets de gestion'!C:C,'Objets de gestion'!F:F)) )))) | O6: =IF(AND(ISBLANK(A6),ISBLANK(B6),ISBLANK(C6),ISBLANK(E6),ISBLANK(L6)),"",IF(OR(ISBLANK(A6),ISBLANK(B6),ISBLANK(C6),ISBLANK(E6),ISBLANK(L6)),"-", C6&" "&IF(ISBLANK(E6),"",D6&" "&E6&" ")&IF(ISBLANK(G6),"",F6&" "&G6&" ")&IF(ISBLANK(I6),"",H6&" "&I6&" ")&IF(ISBLANK(K6),"",J6&" "&K6&" "))) | P6: =IF(AND(ISBLANK(A6),ISBLANK(B6),ISBLANK(C6),ISBLANK(E6),ISBLANK(L6)),"",IF(OR(ISBLANK(A6),ISBLANK(B6),ISBLANK(C6),ISBLANK(E6),ISBLANK(L6)),"-", IF(ISBLANK(C6),"",LOOKUP(C6,'Objets de gestion'!C:C,'Objets de gestion'!E:E)) &IF(ISBLANK(D6),""," "&LOOKUP(D6,Articles!A:A,Articles!B:B)) &IF(ISBLANK(E6),""," "&LOOKUP(E6,'Objets de gestion'!C:C,'Objets de gestion'!E:E)) &IF(ISBLANK(F6),""," "&LOOKUP(F6,Articles!A:A,Articles!B:B)) &IF(ISBLANK(G6),""," "&LOOKUP(G6,'Objets de gestion'!C:C,'Objets de gestion'!E:E)) &IF(ISBLANK(H6),""," "&LOOKUP(H6,Articles!A:A,Articles!B:B)) &IF(ISBLANK(I6),""," "&LOOKUP(I6,'Objets de gestion'!C:C,'Objets de gestion'!E:E)) &IF(ISBLANK(J6),""," "&LOOKUP(J6,Articles!A:A,Articles!B:B)) &IF(ISBLANK(K6),""," "&LOOKUP(K6,'Objets de gestion'!C:C,'Objets de gestion'!E:E)) )) | Q6: =IF(AND(ISBLANK(A6),ISBLANK(B6),ISBLANK(C6),ISBLANK(E6),ISBLANK(L6)),"",IF(OR(ISBLANK(A6),ISBLANK(B6),ISBLANK(C6),ISBLANK(E6),ISBLANK(L6)),"-", LOOKUP(B6,'Type de champ'!B:B,'Type de champ'!C:C))) | R6: =IF(AND(ISBLANK(A6),ISBLANK(B6),ISBLANK(E6),ISBLANK(G6),ISBLANK(L6)),"",IF(OR(ISBLANK(A6),ISBLANK(B6),ISBLANK(E6),ISBLANK(G6),ISBLANK(L6)),"-", A6))
M7: =IF(AND(ISBLANK(A7),ISBLANK(B7),ISBLANK(E7),ISBLANK(G7),ISBLANK(L7)),"",IF(OR(ISBLANK(A7),ISBLANK(B7),ISBLANK(E7),ISBLANK(G7),ISBLANK(L7)),"-",LEN(Tableau47[[#This Row],[Code]]))) | N7: =IF(AND(ISBLANK(A7),ISBLANK(B7),ISBLANK(C7),ISBLANK(E7),ISBLANK(L7)),"",IF(OR(ISBLANK(A7),ISBLANK(B7),ISBLANK(C7),ISBLANK(E7),ISBLANK(L7)),"à compléter", IF(L7="Normal", LOOKUP(B7,'Type de champ'!B:B,'Type de champ'!A:A) &IF(COUNTIF('Objets de gestion'!C:C,K7)=0,"","_"&LOOKUP(K7,'Objets de gestion'!C:C,'Objets de gestion'!F:F)) &IF(COUNTIF('Objets de gestion'!C:C,I7)=0,"","_"&LOOKUP(I7,'Objets de gestion'!C:C,'Objets de gestion'!F:F)) &IF(COUNTIF('Objets de gestion'!C:C,G7)=0,"","_"&LOOKUP(G7,'Objets de gestion'!C:C,'Objets de gestion'!F:F)) &IF(COUNTIF('Objets de gestion'!C:C,E7)=0,"","_"&LOOKUP(E7,'Objets de gestion'!C:C,'Objets de gestion'!F:F)) &IF(OR(C7="booléen",COUNTIF('Objets de gestion'!C:C,C7)=0),"","_"&LOOKUP(C7,'Objets de gestion'!C:C,'Objets de gestion'!F:F)), IF(L7="Forcé", LOOKUP(B7,'Type de champ'!B:B,'Type de champ'!A:A) &IF(COUNTIF('Objets de gestion'!C:C,E7)=0,"","_"&LOOKUP(E7,'Objets de gestion'!C:C,'Objets de gestion'!F:F)) &IF(COUNTIF('Objets de gestion'!C:C,G7)=0,"","_"&LOOKUP(G7,'Objets de gestion'!C:C,'Objets de gestion'!F:F)) &IF(COUNTIF('Objets de gestion'!C:C,I7)=0,"","_"&LOOKUP(I7,'Objets de gestion'!C:C,'Objets de gestion'!F:F)) &IF(COUNTIF('Objets de gestion'!C:C,K7)=0,"","_"&LOOKUP(K7,'Objets de gestion'!C:C,'Objets de gestion'!F:F)) &IF(OR(C7="booléen",COUNTIF('Objets de gestion'!C:C,C7)=0),"","_"&LOOKUP(C7,'Objets de gestion'!C:C,'Objets de gestion'!F:F)) )))) | O7: =IF(AND(ISBLANK(A7),ISBLANK(B7),ISBLANK(C7),ISBLANK(E7),ISBLANK(L7)),"",IF(OR(ISBLANK(A7),ISBLANK(B7),ISBLANK(C7),ISBLANK(E7),ISBLANK(L7)),"-", C7&" "&IF(ISBLANK(E7),"",D7&" "&E7&" ")&IF(ISBLANK(G7),"",F7&" "&G7&" ")&IF(ISBLANK(I7),"",H7&" "&I7&" ")&IF(ISBLANK(K7),"",J7&" "&K7&" "))) | P7: =IF(AND(ISBLANK(A7),ISBLANK(B7),ISBLANK(C7),ISBLANK(E7),ISBLANK(L7)),"",IF(OR(ISBLANK(A7),ISBLANK(B7),ISBLANK(C7),ISBLANK(E7),ISBLANK(L7)),"-", IF(ISBLANK(C7),"",LOOKUP(C7,'Objets de gestion'!C:C,'Objets de gestion'!E:E)) &IF(ISBLANK(D7),""," "&LOOKUP(D7,Articles!A:A,Articles!B:B)) &IF(ISBLANK(E7),""," "&LOOKUP(E7,'Objets de gestion'!C:C,'Objets de gestion'!E:E)) &IF(ISBLANK(F7),""," "&LOOKUP(F7,Articles!A:A,Articles!B:B)) &IF(ISBLANK(G7),""," "&LOOKUP(G7,'Objets de gestion'!C:C,'Objets de gestion'!E:E)) &IF(ISBLANK(H7),""," "&LOOKUP(H7,Articles!A:A,Articles!B:B)) &IF(ISBLANK(I7),""," "&LOOKUP(I7,'Objets de gestion'!C:C,'Objets de gestion'!E:E)) &IF(ISBLANK(J7),""," "&LOOKUP(J7,Articles!A:A,Articles!B:B)) &IF(ISBLANK(K7),""," "&LOOKUP(K7,'Objets de gestion'!C:C,'Objets de gestion'!E:E)) )) | Q7: =IF(AND(ISBLANK(A7),ISBLANK(B7),ISBLANK(C7),ISBLANK(E7),ISBLANK(L7)),"",IF(OR(ISBLANK(A7),ISBLANK(B7),ISBLANK(C7),ISBLANK(E7),ISBLANK(L7)),"-", LOOKUP(B7,'Type de champ'!B:B,'Type de champ'!C:C))) | R7: =IF(AND(ISBLANK(A7),ISBLANK(B7),ISBLANK(E7),ISBLANK(G7),ISBLANK(L7)),"",IF(OR(ISBLANK(A7),ISBLANK(B7),ISBLANK(E7),ISBLANK(G7),ISBLANK(L7)),"-", A7))
M8: =IF(AND(ISBLANK(A8),ISBLANK(B8),ISBLANK(E8),ISBLANK(G8),ISBLANK(L8)),"",IF(OR(ISBLANK(A8),ISBLANK(B8),ISBLANK(E8),ISBLANK(G8),ISBLANK(L8)),"-",LEN(Tableau47[[#This Row],[Code]]))) | N8: =IF(AND(ISBLANK(A8),ISBLANK(B8),ISBLANK(C8),ISBLANK(E8),ISBLANK(L8)),"",IF(OR(ISBLANK(A8),ISBLANK(B8),ISBLANK(C8),ISBLANK(E8),ISBLANK(L8)),"à compléter", IF(L8="Normal", LOOKUP(B8,'Type de champ'!B:B,'Type de champ'!A:A) &IF(COUNTIF('Objets de gestion'!C:C,K8)=0,"","_"&LOOKUP(K8,'Objets de gestion'!C:C,'Objets de gestion'!F:F)) &IF(COUNTIF('Objets de gestion'!C:C,I8)=0,"","_"&LOOKUP(I8,'Objets de gestion'!C:C,'Objets de gestion'!F:F)) &IF(COUNTIF('Objets de gestion'!C:C,G8)=0,"","_"&LOOKUP(G8,'Objets de gestion'!C:C,'Objets de gestion'!F:F)) &IF(COUNTIF('Objets de gestion'!C:C,E8)=0,"","_"&LOOKUP(E8,'Objets de gestion'!C:C,'Objets de gestion'!F:F)) &IF(OR(C8="booléen",COUNTIF('Objets de gestion'!C:C,C8)=0),"","_"&LOOKUP(C8,'Objets de gestion'!C:C,'Objets de gestion'!F:F)), IF(L8="Forcé", LOOKUP(B8,'Type de champ'!B:B,'Type de champ'!A:A) &IF(COUNTIF('Objets de gestion'!C:C,E8)=0,"","_"&LOOKUP(E8,'Objets de gestion'!C:C,'Objets de gestion'!F:F)) &IF(COUNTIF('Objets de gestion'!C:C,G8)=0,"","_"&LOOKUP(G8,'Objets de gestion'!C:C,'Objets de gestion'!F:F)) &IF(COUNTIF('Objets de gestion'!C:C,I8)=0,"","_"&LOOKUP(I8,'Objets de gestion'!C:C,'Objets de gestion'!F:F)) &IF(COUNTIF('Objets de gestion'!C:C,K8)=0,"","_"&LOOKUP(K8,'Objets de gestion'!C:C,'Objets de gestion'!F:F)) &IF(OR(C8="booléen",COUNTIF('Objets de gestion'!C:C,C8)=0),"","_"&LOOKUP(C8,'Objets de gestion'!C:C,'Objets de gestion'!F:F)) )))) | O8: =IF(AND(ISBLANK(A8),ISBLANK(B8),ISBLANK(C8),ISBLANK(E8),ISBLANK(L8)),"",IF(OR(ISBLANK(A8),ISBLANK(B8),ISBLANK(C8),ISBLANK(E8),ISBLANK(L8)),"-", C8&" "&IF(ISBLANK(E8),"",D8&" "&E8&" ")&IF(ISBLANK(G8),"",F8&" "&G8&" ")&IF(ISBLANK(I8),"",H8&" "&I8&" ")&IF(ISBLANK(K8),"",J8&" "&K8&" "))) | P8: =IF(AND(ISBLANK(A8),ISBLANK(B8),ISBLANK(C8),ISBLANK(E8),ISBLANK(L8)),"",IF(OR(ISBLANK(A8),ISBLANK(B8),ISBLANK(C8),ISBLANK(E8),ISBLANK(L8)),"-", IF(ISBLANK(C8),"",LOOKUP(C8,'Objets de gestion'!C:C,'Objets de gestion'!E:E)) &IF(ISBLANK(D8),""," "&LOOKUP(D8,Articles!A:A,Articles!B:B)) &IF(ISBLANK(E8),""," "&LOOKUP(E8,'Objets de gestion'!C:C,'Objets de gestion'!E:E)) &IF(ISBLANK(F8),""," "&LOOKUP(F8,Articles!A:A,Articles!B:B)) &IF(ISBLANK(G8),""," "&LOOKUP(G8,'Objets de gestion'!C:C,'Objets de gestion'!E:E)) &IF(ISBLANK(H8),""," "&LOOKUP(H8,Articles!A:A,Articles!B:B)) &IF(ISBLANK(I8),""," "&LOOKUP(I8,'Objets de gestion'!C:C,'Objets de gestion'!E:E)) &IF(ISBLANK(J8),""," "&LOOKUP(J8,Articles!A:A,Articles!B:B)) &IF(ISBLANK(K8),""," "&LOOKUP(K8,'Objets de gestion'!C:C,'Objets de gestion'!E:E)) )) | Q8: =IF(AND(ISBLANK(A8),ISBLANK(B8),ISBLANK(C8),ISBLANK(E8),ISBLANK(L8)),"",IF(OR(ISBLANK(A8),ISBLANK(B8),ISBLANK(C8),ISBLANK(E8),ISBLANK(L8)),"-", LOOKUP(B8,'Type de champ'!B:B,'Type de champ'!C:C))) | R8: =IF(AND(ISBLANK(A8),ISBLANK(B8),ISBLANK(E8),ISBLANK(G8),ISBLANK(L8)),"",IF(OR(ISBLANK(A8),ISBLANK(B8),ISBLANK(E8),ISBLANK(G8),ISBLANK(L8)),"-", A8))
M9: =IF(AND(ISBLANK(A9),ISBLANK(B9),ISBLANK(E9),ISBLANK(G9),ISBLANK(L9)),"",IF(OR(ISBLANK(A9),ISBLANK(B9),ISBLANK(E9),ISBLANK(G9),ISBLANK(L9)),"-",LEN(Tableau47[[#This Row],[Code]]))) | N9: =IF(AND(ISBLANK(A9),ISBLANK(B9),ISBLANK(C9),ISBLANK(E9),ISBLANK(L9)),"",IF(OR(ISBLANK(A9),ISBLANK(B9),ISBLANK(C9),ISBLANK(E9),ISBLANK(L9)),"à compléter", IF(L9="Normal", LOOKUP(B9,'Type de champ'!B:B,'Type de champ'!A:A) &IF(COUNTIF('Objets de gestion'!C:C,K9)=0,"","_"&LOOKUP(K9,'Objets de gestion'!C:C,'Objets de gestion'!F:F)) &IF(COUNTIF('Objets de gestion'!C:C,I9)=0,"","_"&LOOKUP(I9,'Objets de gestion'!C:C,'Objets de gestion'!F:F)) &IF(COUNTIF('Objets de gestion'!C:C,G9)=0,"","_"&LOOKUP(G9,'Objets de gestion'!C:C,'Objets de gestion'!F:F)) &IF(COUNTIF('Objets de gestion'!C:C,E9)=0,"","_"&LOOKUP(E9,'Objets de gestion'!C:C,'Objets de gestion'!F:F)) &IF(OR(C9="booléen",COUNTIF('Objets de gestion'!C:C,C9)=0),"","_"&LOOKUP(C9,'Objets de gestion'!C:C,'Objets de gestion'!F:F)), IF(L9="Forcé", LOOKUP(B9,'Type de champ'!B:B,'Type de champ'!A:A) &IF(COUNTIF('Objets de gestion'!C:C,E9)=0,"","_"&LOOKUP(E9,'Objets de gestion'!C:C,'Objets de gestion'!F:F)) &IF(COUNTIF('Objets de gestion'!C:C,G9)=0,"","_"&LOOKUP(G9,'Objets de gestion'!C:C,'Objets de gestion'!F:F)) &IF(COUNTIF('Objets de gestion'!C:C,I9)=0,"","_"&LOOKUP(I9,'Objets de gestion'!C:C,'Objets de gestion'!F:F)) &IF(COUNTIF('Objets de gestion'!C:C,K9)=0,"","_"&LOOKUP(K9,'Objets de gestion'!C:C,'Objets de gestion'!F:F)) &IF(OR(C9="booléen",COUNTIF('Objets de gestion'!C:C,C9)=0),"","_"&LOOKUP(C9,'Objets de gestion'!C:C,'Objets de gestion'!F:F)) )))) | O9: =IF(AND(ISBLANK(A9),ISBLANK(B9),ISBLANK(C9),ISBLANK(E9),ISBLANK(L9)),"",IF(OR(ISBLANK(A9),ISBLANK(B9),ISBLANK(C9),ISBLANK(E9),ISBLANK(L9)),"-", C9&" "&IF(ISBLANK(E9),"",D9&" "&E9&" ")&IF(ISBLANK(G9),"",F9&" "&G9&" ")&IF(ISBLANK(I9),"",H9&" "&I9&" ")&IF(ISBLANK(K9),"",J9&" "&K9&" "))) | P9: =IF(AND(ISBLANK(A9),ISBLANK(B9),ISBLANK(C9),ISBLANK(E9),ISBLANK(L9)),"",IF(OR(ISBLANK(A9),ISBLANK(B9),ISBLANK(C9),ISBLANK(E9),ISBLANK(L9)),"-", IF(ISBLANK(C9),"",LOOKUP(C9,'Objets de gestion'!C:C,'Objets de gestion'!E:E)) &IF(ISBLANK(D9),""," "&LOOKUP(D9,Articles!A:A,Articles!B:B)) &IF(ISBLANK(E9),""," "&LOOKUP(E9,'Objets de gestion'!C:C,'Objets de gestion'!E:E)) &IF(ISBLANK(F9),""," "&LOOKUP(F9,Articles!A:A,Articles!B:B)) &IF(ISBLANK(G9),""," "&LOOKUP(G9,'Objets de gestion'!C:C,'Objets de gestion'!E:E)) &IF(ISBLANK(H9),""," "&LOOKUP(H9,Articles!A:A,Articles!B:B)) &IF(ISBLANK(I9),""," "&LOOKUP(I9,'Objets de gestion'!C:C,'Objets de gestion'!E:E)) &IF(ISBLANK(J9),""," "&LOOKUP(J9,Articles!A:A,Articles!B:B)) &IF(ISBLANK(K9),""," "&LOOKUP(K9,'Objets de gestion'!C:C,'Objets de gestion'!E:E)) )) | Q9: =IF(AND(ISBLANK(A9),ISBLANK(B9),ISBLANK(C9),ISBLANK(E9),ISBLANK(L9)),"",IF(OR(ISBLANK(A9),ISBLANK(B9),ISBLANK(C9),ISBLANK(E9),ISBLANK(L9)),"-", LOOKUP(B9,'Type de champ'!B:B,'Type de champ'!C:C))) | R9: =IF(AND(ISBLANK(A9),ISBLANK(B9),ISBLANK(E9),ISBLANK(G9),ISBLANK(L9)),"",IF(OR(ISBLANK(A9),ISBLANK(B9),ISBLANK(E9),ISBLANK(G9),ISBLANK(L9)),"-", A9))
M10: =IF(AND(ISBLANK(A10),ISBLANK(B10),ISBLANK(E10),ISBLANK(G10),ISBLANK(L10)),"",IF(OR(ISBLANK(A10),ISBLANK(B10),ISBLANK(E10),ISBLANK(G10),ISBLANK(L10)),"-",LEN(Tableau47[[#This Row],[Code]]))) | N10: =IF(AND(ISBLANK(A10),ISBLANK(B10),ISBLANK(C10),ISBLANK(E10),ISBLANK(L10)),"",IF(OR(ISBLANK(A10),ISBLANK(B10),ISBLANK(C10),ISBLANK(E10),ISBLANK(L10)),"à compléter", IF(L10="Normal", LOOKUP(B10,'Type de champ'!B:B,'Type de champ'!A:A) &IF(COUNTIF('Objets de gestion'!C:C,K10)=0,"","_"&LOOKUP(K10,'Objets de gestion'!C:C,'Objets de gestion'!F:F)) &IF(COUNTIF('Objets de gestion'!C:C,I10)=0,"","_"&LOOKUP(I10,'Objets de gestion'!C:C,'Objets de gestion'!F:F)) &IF(COUNTIF('Objets de gestion'!C:C,G10)=0,"","_"&LOOKUP(G10,'Objets de gestion'!C:C,'Objets de gestion'!F:F)) &IF(COUNTIF('Objets de gestion'!C:C,E10)=0,"","_"&LOOKUP(E10,'Objets de gestion'!C:C,'Objets de gestion'!F:F)) &IF(OR(C10="booléen",COUNTIF('Objets de gestion'!C:C,C10)=0),"","_"&LOOKUP(C10,'Objets de gestion'!C:C,'Objets de gestion'!F:F)), IF(L10="Forcé", LOOKUP(B10,'Type de champ'!B:B,'Type de champ'!A:A) &IF(COUNTIF('Objets de gestion'!C:C,E10)=0,"","_"&LOOKUP(E10,'Objets de gestion'!C:C,'Objets de gestion'!F:F)) &IF(COUNTIF('Objets de gestion'!C:C,G10)=0,"","_"&LOOKUP(G10,'Objets de gestion'!C:C,'Objets de gestion'!F:F)) &IF(COUNTIF('Objets de gestion'!C:C,I10)=0,"","_"&LOOKUP(I10,'Objets de gestion'!C:C,'Objets de gestion'!F:F)) &IF(COUNTIF('Objets de gestion'!C:C,K10)=0,"","_"&LOOKUP(K10,'Objets de gestion'!C:C,'Objets de gestion'!F:F)) &IF(OR(C10="booléen",COUNTIF('Objets de gestion'!C:C,C10)=0),"","_"&LOOKUP(C10,'Objets de gestion'!C:C,'Objets de gestion'!F:F)) )))) | O10: =IF(AND(ISBLANK(A10),ISBLANK(B10),ISBLANK(C10),ISBLANK(E10),ISBLANK(L10)),"",IF(OR(ISBLANK(A10),ISBLANK(B10),ISBLANK(C10),ISBLANK(E10),ISBLANK(L10)),"-", C10&" "&IF(ISBLANK(E10),"",D10&" "&E10&" ")&IF(ISBLANK(G10),"",F10&" "&G10&" ")&IF(ISBLANK(I10),"",H10&" "&I10&" ")&IF(ISBLANK(K10),"",J10&" "&K10&" "))) | P10: =IF(AND(ISBLANK(A10),ISBLANK(B10),ISBLANK(C10),ISBLANK(E10),ISBLANK(L10)),"",IF(OR(ISBLANK(A10),ISBLANK(B10),ISBLANK(C10),ISBLANK(E10),ISBLANK(L10)),"-", IF(ISBLANK(C10),"",LOOKUP(C10,'Objets de gestion'!C:C,'Objets de gestion'!E:E)) &IF(ISBLANK(D10),""," "&LOOKUP(D10,Articles!A:A,Articles!B:B)) &IF(ISBLANK(E10),""," "&LOOKUP(E10,'Objets de gestion'!C:C,'Objets de gestion'!E:E)) &IF(ISBLANK(F10),""," "&LOOKUP(F10,Articles!A:A,Articles!B:B)) &IF(ISBLANK(G10),""," "&LOOKUP(G10,'Objets de gestion'!C:C,'Objets de gestion'!E:E)) &IF(ISBLANK(H10),""," "&LOOKUP(H10,Articles!A:A,Articles!B:B)) &IF(ISBLANK(I10),""," "&LOOKUP(I10,'Objets de gestion'!C:C,'Objets de gestion'!E:E)) &IF(ISBLANK(J10),""," "&LOOKUP(J10,Articles!A:A,Articles!B:B)) &IF(ISBLANK(K10),""," "&LOOKUP(K10,'Objets de gestion'!C:C,'Objets de gestion'!E:E)) )) | Q10: =IF(AND(ISBLANK(A10),ISBLANK(B10),ISBLANK(C10),ISBLANK(E10),ISBLANK(L10)),"",IF(OR(ISBLANK(A10),ISBLANK(B10),ISBLANK(C10),ISBLANK(E10),ISBLANK(L10)),"-", LOOKUP(B10,'Type de champ'!B:B,'Type de champ'!C:C))) | R10: =IF(AND(ISBLANK(A10),ISBLANK(B10),ISBLANK(E10),ISBLANK(G10),ISBLANK(L10)),"",IF(OR(ISBLANK(A10),ISBLANK(B10),ISBLANK(E10),ISBLANK(G10),ISBLANK(L10)),"-", A10))
M11: =IF(AND(ISBLANK(A11),ISBLANK(B11),ISBLANK(E11),ISBLANK(G11),ISBLANK(L11)),"",IF(OR(ISBLANK(A11),ISBLANK(B11),ISBLANK(E11),ISBLANK(G11),ISBLANK(L11)),"-",LEN(Tableau47[[#This Row],[Code]]))) | N11: =IF(AND(ISBLANK(A11),ISBLANK(B11),ISBLANK(C11),ISBLANK(E11),ISBLANK(L11)),"",IF(OR(ISBLANK(A11),ISBLANK(B11),ISBLANK(C11),ISBLANK(E11),ISBLANK(L11)),"à compléter", IF(L11="Normal", LOOKUP(B11,'Type de champ'!B:B,'Type de champ'!A:A) &IF(COUNTIF('Objets de gestion'!C:C,K11)=0,"","_"&LOOKUP(K11,'Objets de gestion'!C:C,'Objets de gestion'!F:F)) &IF(COUNTIF('Objets de gestion'!C:C,I11)=0,"","_"&LOOKUP(I11,'Objets de gestion'!C:C,'Objets de gestion'!F:F)) &IF(COUNTIF('Objets de gestion'!C:C,G11)=0,"","_"&LOOKUP(G11,'Objets de gestion'!C:C,'Objets de gestion'!F:F)) &IF(COUNTIF('Objets de gestion'!C:C,E11)=0,"","_"&LOOKUP(E11,'Objets de gestion'!C:C,'Objets de gestion'!F:F)) &IF(OR(C11="booléen",COUNTIF('Objets de gestion'!C:C,C11)=0),"","_"&LOOKUP(C11,'Objets de gestion'!C:C,'Objets de gestion'!F:F)), IF(L11="Forcé", LOOKUP(B11,'Type de champ'!B:B,'Type de champ'!A:A) &IF(COUNTIF('Objets de gestion'!C:C,E11)=0,"","_"&LOOKUP(E11,'Objets de gestion'!C:C,'Objets de gestion'!F:F)) &IF(COUNTIF('Objets de gestion'!C:C,G11)=0,"","_"&LOOKUP(G11,'Objets de gestion'!C:C,'Objets de gestion'!F:F)) &IF(COUNTIF('Objets de gestion'!C:C,I11)=0,"","_"&LOOKUP(I11,'Objets de gestion'!C:C,'Objets de gestion'!F:F)) &IF(COUNTIF('Objets de gestion'!C:C,K11)=0,"","_"&LOOKUP(K11,'Objets de gestion'!C:C,'Objets de gestion'!F:F)) &IF(OR(C11="booléen",COUNTIF('Objets de gestion'!C:C,C11)=0),"","_"&LOOKUP(C11,'Objets de gestion'!C:C,'Objets de gestion'!F:F)) )))) | O11: =IF(AND(ISBLANK(A11),ISBLANK(B11),ISBLANK(C11),ISBLANK(E11),ISBLANK(L11)),"",IF(OR(ISBLANK(A11),ISBLANK(B11),ISBLANK(C11),ISBLANK(E11),ISBLANK(L11)),"-", C11&" "&IF(ISBLANK(E11),"",D11&" "&E11&" ")&IF(ISBLANK(G11),"",F11&" "&G11&" ")&IF(ISBLANK(I11),"",H11&" "&I11&" ")&IF(ISBLANK(K11),"",J11&" "&K11&" "))) | P11: =IF(AND(ISBLANK(A11),ISBLANK(B11),ISBLANK(C11),ISBLANK(E11),ISBLANK(L11)),"",IF(OR(ISBLANK(A11),ISBLANK(B11),ISBLANK(C11),ISBLANK(E11),ISBLANK(L11)),"-", IF(ISBLANK(C11),"",LOOKUP(C11,'Objets de gestion'!C:C,'Objets de gestion'!E:E)) &IF(ISBLANK(D11),""," "&LOOKUP(D11,Articles!A:A,Articles!B:B)) &IF(ISBLANK(E11),""," "&LOOKUP(E11,'Objets de gestion'!C:C,'Objets de gestion'!E:E)) &IF(ISBLANK(F11),""," "&LOOKUP(F11,Articles!A:A,Articles!B:B)) &IF(ISBLANK(G11),""," "&LOOKUP(G11,'Objets de gestion'!C:C,'Objets de gestion'!E:E)) &IF(ISBLANK(H11),""," "&LOOKUP(H11,Articles!A:A,Articles!B:B)) &IF(ISBLANK(I11),""," "&LOOKUP(I11,'Objets de gestion'!C:C,'Objets de gestion'!E:E)) &IF(ISBLANK(J11),""," "&LOOKUP(J11,Articles!A:A,Articles!B:B)) &IF(ISBLANK(K11),""," "&LOOKUP(K11,'Objets de gestion'!C:C,'Objets de gestion'!E:E)) )) | Q11: =IF(AND(ISBLANK(A11),ISBLANK(B11),ISBLANK(C11),ISBLANK(E11),ISBLANK(L11)),"",IF(OR(ISBLANK(A11),ISBLANK(B11),ISBLANK(C11),ISBLANK(E11),ISBLANK(L11)),"-", LOOKUP(B11,'Type de champ'!B:B,'Type de champ'!C:C))) | R11: =IF(AND(ISBLANK(A11),ISBLANK(B11),ISBLANK(E11),ISBLANK(G11),ISBLANK(L11)),"",IF(OR(ISBLANK(A11),ISBLANK(B11),ISBLANK(E11),ISBLANK(G11),ISBLANK(L11)),"-", A11))
A12: Tiers | B12: Clé | C12: Identifiant unique | D12: entre | E12: client | F12: et | G12: chargé de clientèle | L12: Normal | M12: =IF(AND(ISBLANK(A12),ISBLANK(B12),ISBLANK(E12),ISBLANK(G12),ISBLANK(L12)),"",IF(OR(ISBLANK(A12),ISBLANK(B12),ISBLANK(E12),ISBLANK(G12),ISBLANK(L12)),"-",LEN(Tableau47[[#This Row],[Code]]))) -> 16 | N12: =IF(AND(ISBLANK(A12),ISBLANK(B12),ISBLANK(C12),ISBLANK(E12),ISBLANK(L12)),"",IF(OR(ISBLANK(A12),ISBLANK(B12),ISBLANK(C12),ISBLANK(E12),ISBLANK(L12)),"à compléter", IF(L12="Normal", LOOKUP(B12,'Type de champ'!B:B,'Type de champ'!A:A) &IF(COUNTIF('Objets de gestion'!C:C,K12)=0,"","_"&LOOKUP(K12,'Objets de gestion'!C:C,'Objets de gestion'!F:F)) &IF(COUNTIF('Objets de gestion'!C:C,I12)=0,"","_"&LOOKUP(I12,'Objets de gestion'!C:C,'Objets de gestion'!F:F)) &IF(COUNTIF('Objets de gestion'!C:C,G12)=0,"","_"&LOOKUP(G12,'Objets de gestion'!C:C,'Objets de gestion'!F:F)) &IF(COUNTIF('Objets de gestion'!C:C,E12)=0,"","_"&LOOKUP(E12,'Objets de gestion'!C:C,'Objets de gestion'!F:F)) &IF(OR(C12="booléen",COUNTIF('Objets de gestion'!C:C,C12)=0),"","_"&LOOKUP(C12,'Objets de gestion'!C:C,'Objets de gestion'!F:F)), IF(L12="Forcé", LOOKUP(B12,'Type de champ'!B:B,'Type de champ'!A:A) &IF(COUNTIF('Objets de gestion'!C:C,E12)=0,"","_"&LOOKUP(E12,'Objets de gestion'!C:C,'Objets de gestion'!F:F)) &IF(COUNTIF('Objets de gestion'!C:C,G12)=0,"","_"&LOOKUP(G12,'Objets de gestion'!C:C,'Objets de gestion'!F:F)) &IF(COUNTIF('Objets de gestion'!C:C,I12)=0,"","_"&LOOKUP(I12,'Objets de gestion'!C:C,'Objets de gestion'!F:F)) &IF(COUNTIF('Objets de gestion'!C:C,K12)=0,"","_"&LOOKUP(K12,'Objets de gestion'!C:C,'Objets de gestion'!F:F)) &IF(OR(C12="booléen",COUNTIF('Objets de gestion'!C:C,C12)=0),"","_"&LOOKUP(C12,'Objets de gestion'!C:C,'Objets de gestion'!F:F)) )))) -> K_ACCMGR_CUS_UID | O12: =IF(AND(ISBLANK(A12),ISBLANK(B12),ISBLANK(C12),ISBLANK(E12),ISBLANK(L12)),"",IF(OR(ISBLANK(A12),ISBLANK(B12),ISBLANK(C12),ISBLANK(E12),ISBLANK(L12)),"-", C12&" "&IF(ISBLANK(E12),"",D12&" "&E12&" ")&IF(ISBLANK(G12),"",F12&" "&G12&" ")&IF(ISBLANK(I12),"",H12&" "&I12&" ")&IF(ISBLANK(K12),"",J12&" "&K12&" "))) -> Identifiant unique entre client et chargé de clientèle | P12: =IF(AND(ISBLANK(A12),ISBLANK(B12),ISBLANK(C12),ISBLANK(E12),ISBLANK(L12)),"",IF(OR(ISBLANK(A12),ISBLANK(B12),ISBLANK(C12),ISBLANK(E12),ISBLANK(L12)),"-", IF(ISBLANK(C12),"",LOOKUP(C12,'Objets de gestion'!C:C,'Objets de gestion'!E:E)) &IF(ISBLANK(D12),""," "&LOOKUP(D12,Articles!A:A,Articles!B:B)) &IF(ISBLANK(E12),""," "&LOOKUP(E12,'Objets de gestion'!C:C,'Objets de gestion'!E:E)) &IF(ISBLANK(F12),""," "&LOOKUP(F12,Articles!A:A,Articles!B:B)) &IF(ISBLANK(G12),""," "&LOOKUP(G12,'Objets de gestion'!C:C,'Objets de gestion'!E:E)) &IF(ISBLANK(H12),""," "&LOOKUP(H12,Articles!A:A,Articles!B:B)) &IF(ISBLANK(I12),""," "&LOOKUP(I12,'Objets de gestion'!C:C,'Objets de gestion'!E:E)) &IF(ISBLANK(J12),""," "&LOOKUP(J12,Articles!A:A,Articles!B:B)) &IF(ISBLANK(K12),""," "&LOOKUP(K12,'Objets de gestion'!C:C,'Objets de gestion'!E:E)) )) -> Unique Identifier between customer and Account Manager | Q12: =IF(AND(ISBLANK(A12),ISBLANK(B12),ISBLANK(C12),ISBLANK(E12),ISBLANK(L12)),"",IF(OR(ISBLANK(A12),ISBLANK(B12),ISBLANK(C12),ISBLANK(E12),ISBLANK(L12)),"-", LOOKUP(B12,'Type de champ'!B:B,'Type de champ'!C:C))) -> Integer | R12: =IF(AND(ISBLANK(A12),ISBLANK(B12),ISBLANK(E12),ISBLANK(G12),ISBLANK(L12)),"",IF(OR(ISBLANK(A12),ISBLANK(B12),ISBLANK(E12),ISBLANK(G12),ISBLANK(L12)),"-", A12)) -> Tiers
A13: Tiers | B13: Chaine de caractère | C13: Identifiant fonctionnel | D13: entre | E13: client | F13: et | G13: chargé de clientèle | L13: Normal | M13: =IF(AND(ISBLANK(A13),ISBLANK(B13),ISBLANK(E13),ISBLANK(G13),ISBLANK(L13)),"",IF(OR(ISBLANK(A13),ISBLANK(B13),ISBLANK(E13),ISBLANK(G13),ISBLANK(L13)),"-",LEN(Tableau47[[#This Row],[Code]]))) -> 19 | N13: =IF(AND(ISBLANK(A13),ISBLANK(B13),ISBLANK(C13),ISBLANK(E13),ISBLANK(L13)),"",IF(OR(ISBLANK(A13),ISBLANK(B13),ISBLANK(C13),ISBLANK(E13),ISBLANK(L13)),"à compléter", IF(L13="Normal", LOOKUP(B13,'Type de champ'!B:B,'Type de champ'!A:A) &IF(COUNTIF('Objets de gestion'!C:C,K13)=0,"","_"&LOOKUP(K13,'Objets de gestion'!C:C,'Objets de gestion'!F:F)) &IF(COUNTIF('Objets de gestion'!C:C,I13)=0,"","_"&LOOKUP(I13,'Objets de gestion'!C:C,'Objets de gestion'!F:F)) &IF(COUNTIF('Objets de gestion'!C:C,G13)=0,"","_"&LOOKUP(G13,'Objets de gestion'!C:C,'Objets de gestion'!F:F)) &IF(COUNTIF('Objets de gestion'!C:C,E13)=0,"","_"&LOOKUP(E13,'Objets de gestion'!C:C,'Objets de gestion'!F:F)) &IF(OR(C13="booléen",COUNTIF('Objets de gestion'!C:C,C13)=0),"","_"&LOOKUP(C13,'Objets de gestion'!C:C,'Objets de gestion'!F:F)), IF(L13="Forcé", LOOKUP(B13,'Type de champ'!B:B,'Type de champ'!A:A) &IF(COUNTIF('Objets de gestion'!C:C,E13)=0,"","_"&LOOKUP(E13,'Objets de gestion'!C:C,'Objets de gestion'!F:F)) &IF(COUNTIF('Objets de gestion'!C:C,G13)=0,"","_"&LOOKUP(G13,'Objets de gestion'!C:C,'Objets de gestion'!F:F)) &IF(COUNTIF('Objets de gestion'!C:C,I13)=0,"","_"&LOOKUP(I13,'Objets de gestion'!C:C,'Objets de gestion'!F:F)) &IF(COUNTIF('Objets de gestion'!C:C,K13)=0,"","_"&LOOKUP(K13,'Objets de gestion'!C:C,'Objets de gestion'!F:F)) &IF(OR(C13="booléen",COUNTIF('Objets de gestion'!C:C,C13)=0),"","_"&LOOKUP(C13,'Objets de gestion'!C:C,'Objets de gestion'!F:F)) )))) -> X_ACCMGR_CUS_FCTIDT | O13: =IF(AND(ISBLANK(A13),ISBLANK(B13),ISBLANK(C13),ISBLANK(E13),ISBLANK(L13)),"",IF(OR(ISBLANK(A13),ISBLANK(B13),ISBLANK(C13),ISBLANK(E13),ISBLANK(L13)),"-", C13&" "&IF(ISBLANK(E13),"",D13&" "&E13&" ")&IF(ISBLANK(G13),"",F13&" "&G13&" ")&IF(ISBLANK(I13),"",H13&" "&I13&" ")&IF(ISBLANK(K13),"",J13&" "&K13&" "))) -> Identifiant fonctionnel entre client et chargé de clientèle | P13: =IF(AND(ISBLANK(A13),ISBLANK(B13),ISBLANK(C13),ISBLANK(E13),ISBLANK(L13)),"",IF(OR(ISBLANK(A13),ISBLANK(B13),ISBLANK(C13),ISBLANK(E13),ISBLANK(L13)),"-", IF(ISBLANK(C13),"",LOOKUP(C13,'Objets de gestion'!C:C,'Objets de gestion'!E:E)) &IF(ISBLANK(D13),""," "&LOOKUP(D13,Articles!A:A,Articles!B:B)) &IF(ISBLANK(E13),""," "&LOOKUP(E13,'Objets de gestion'!C:C,'Objets de gestion'!E:E)) &IF(ISBLANK(F13),""," "&LOOKUP(F13,Articles!A:A,Articles!B:B)) &IF(ISBLANK(G13),""," "&LOOKUP(G13,'Objets de gestion'!C:C,'Objets de gestion'!E:E)) &IF(ISBLANK(H13),""," "&LOOKUP(H13,Articles!A:A,Articles!B:B)) &IF(ISBLANK(I13),""," "&LOOKUP(I13,'Objets de gestion'!C:C,'Objets de gestion'!E:E)) &IF(ISBLANK(J13),""," "&LOOKUP(J13,Articles!A:A,Articles!B:B)) &IF(ISBLANK(K13),""," "&LOOKUP(K13,'Objets de gestion'!C:C,'Objets de gestion'!E:E)) )) -> functional identifier between customer and Account Manager | Q13: =IF(AND(ISBLANK(A13),ISBLANK(B13),ISBLANK(C13),ISBLANK(E13),ISBLANK(L13)),"",IF(OR(ISBLANK(A13),ISBLANK(B13),ISBLANK(C13),ISBLANK(E13),ISBLANK(L13)),"-", LOOKUP(B13,'Type de champ'!B:B,'Type de champ'!C:C))) -> Varchar(??) | R13: =IF(AND(ISBLANK(A13),ISBLANK(B13),ISBLANK(E13),ISBLANK(G13),ISBLANK(L13)),"",IF(OR(ISBLANK(A13),ISBLANK(B13),ISBLANK(E13),ISBLANK(G13),ISBLANK(L13)),"-", A13)) -> Tiers
A14: Tiers | B14: Date, Heure, Timestamp | C14: Date de début de l'identifiant unique | D14: entre | E14: client | F14: et | G14: chargé de clientèle | L14: Normal | M14: =IF(AND(ISBLANK(A14),ISBLANK(B14),ISBLANK(E14),ISBLANK(G14),ISBLANK(L14)),"",IF(OR(ISBLANK(A14),ISBLANK(B14),ISBLANK(E14),ISBLANK(G14),ISBLANK(L14)),"-",LEN(Tableau47[[#This Row],[Code]]))) -> 19 | N14: =IF(AND(ISBLANK(A14),ISBLANK(B14),ISBLANK(C14),ISBLANK(E14),ISBLANK(L14)),"",IF(OR(ISBLANK(A14),ISBLANK(B14),ISBLANK(C14),ISBLANK(E14),ISBLANK(L14)),"à compléter", IF(L14="Normal", LOOKUP(B14,'Type de champ'!B:B,'Type de champ'!A:A) &IF(COUNTIF('Objets de gestion'!C:C,K14)=0,"","_"&LOOKUP(K14,'Objets de gestion'!C:C,'Objets de gestion'!F:F)) &IF(COUNTIF('Objets de gestion'!C:C,I14)=0,"","_"&LOOKUP(I14,'Objets de gestion'!C:C,'Objets de gestion'!F:F)) &IF(COUNTIF('Objets de gestion'!C:C,G14)=0,"","_"&LOOKUP(G14,'Objets de gestion'!C:C,'Objets de gestion'!F:F)) &IF(COUNTIF('Objets de gestion'!C:C,E14)=0,"","_"&LOOKUP(E14,'Objets de gestion'!C:C,'Objets de gestion'!F:F)) &IF(OR(C14="booléen",COUNTIF('Objets de gestion'!C:C,C14)=0),"","_"&LOOKUP(C14,'Objets de gestion'!C:C,'Objets de gestion'!F:F)), IF(L14="Forcé", LOOKUP(B14,'Type de champ'!B:B,'Type de champ'!A:A) &IF(COUNTIF('Objets de gestion'!C:C,E14)=0,"","_"&LOOKUP(E14,'Objets de gestion'!C:C,'Objets de gestion'!F:F)) &IF(COUNTIF('Objets de gestion'!C:C,G14)=0,"","_"&LOOKUP(G14,'Objets de gestion'!C:C,'Objets de gestion'!F:F)) &IF(COUNTIF('Objets de gestion'!C:C,I14)=0,"","_"&LOOKUP(I14,'Objets de gestion'!C:C,'Objets de gestion'!F:F)) &IF(COUNTIF('Objets de gestion'!C:C,K14)=0,"","_"&LOOKUP(K14,'Objets de gestion'!C:C,'Objets de gestion'!F:F)) &IF(OR(C14="booléen",COUNTIF('Objets de gestion'!C:C,C14)=0),"","_"&LOOKUP(C14,'Objets de gestion'!C:C,'Objets de gestion'!F:F)) )))) -> T_ACCMGR_CUS_SDAUID | O14: =IF(AND(ISBLANK(A14),ISBLANK(B14),ISBLANK(C14),ISBLANK(E14),ISBLANK(L14)),"",IF(OR(ISBLANK(A14),ISBLANK(B14),ISBLANK(C14),ISBLANK(E14),ISBLANK(L14)),"-", C14&" "&IF(ISBLANK(E14),"",D14&" "&E14&" ")&IF(ISBLANK(G14),"",F14&" "&G14&" ")&IF(ISBLANK(I14),"",H14&" "&I14&" ")&IF(ISBLANK(K14),"",J14&" "&K14&" "))) -> Date de début de l'identifiant unique entre client et chargé de clientèle | P14: =IF(AND(ISBLANK(A14),ISBLANK(B14),ISBLANK(C14),ISBLANK(E14),ISBLANK(L14)),"",IF(OR(ISBLANK(A14),ISBLANK(B14),ISBLANK(C14),ISBLANK(E14),ISBLANK(L14)),"-", IF(ISBLANK(C14),"",LOOKUP(C14,'Objets de gestion'!C:C,'Objets de gestion'!E:E)) &IF(ISBLANK(D14),""," "&LOOKUP(D14,Articles!A:A,Articles!B:B)) &IF(ISBLANK(E14),""," "&LOOKUP(E14,'Objets de gestion'!C:C,'Objets de gestion'!E:E)) &IF(ISBLANK(F14),""," "&LOOKUP(F14,Articles!A:A,Articles!B:B)) &IF(ISBLANK(G14),""," "&LOOKUP(G14,'Objets de gestion'!C:C,'Objets de gestion'!E:E)) &IF(ISBLANK(H14),""," "&LOOKUP(H14,Articles!A:A,Articles!B:B)) &IF(ISBLANK(I14),""," "&LOOKUP(I14,'Objets de gestion'!C:C,'Objets de gestion'!E:E)) &IF(ISBLANK(J14),""," "&LOOKUP(J14,Articles!A:A,Articles!B:B)) &IF(ISBLANK(K14),""," "&LOOKUP(K14,'Objets de gestion'!C:C,'Objets de gestion'!E:E)) )) -> Start date of UID between customer and Account Manager | Q14: =IF(AND(ISBLANK(A14),ISBLANK(B14),ISBLANK(C14),ISBLANK(E14),ISBLANK(L14)),"",IF(OR(ISBLANK(A14),ISBLANK(B14),ISBLANK(C14),ISBLANK(E14),ISBLANK(L14)),"-", LOOKUP(B14,'Type de champ'!B:B,'Type de champ'!C:C))) -> Date | R14: =IF(AND(ISBLANK(A14),ISBLANK(B14),ISBLANK(E14),ISBLANK(G14),ISBLANK(L14)),"",IF(OR(ISBLANK(A14),ISBLANK(B14),ISBLANK(E14),ISBLANK(G14),ISBLANK(L14)),"-", A14)) -> Tiers
A15: Tiers | B15: Date, Heure, Timestamp | C15: Date de fin de l'identifiant unique | D15: entre | E15: client | F15: et | G15: chargé de clientèle | L15: Normal | M15: =IF(AND(ISBLANK(A15),ISBLANK(B15),ISBLANK(E15),ISBLANK(G15),ISBLANK(L15)),"",IF(OR(ISBLANK(A15),ISBLANK(B15),ISBLANK(E15),ISBLANK(G15),ISBLANK(L15)),"-",LEN(Tableau47[[#This Row],[Code]]))) -> 19 | N15: =IF(AND(ISBLANK(A15),ISBLANK(B15),ISBLANK(C15),ISBLANK(E15),ISBLANK(L15)),"",IF(OR(ISBLANK(A15),ISBLANK(B15),ISBLANK(C15),ISBLANK(E15),ISBLANK(L15)),"à compléter", IF(L15="Normal", LOOKUP(B15,'Type de champ'!B:B,'Type de champ'!A:A) &IF(COUNTIF('Objets de gestion'!C:C,K15)=0,"","_"&LOOKUP(K15,'Objets de gestion'!C:C,'Objets de gestion'!F:F)) &IF(COUNTIF('Objets de gestion'!C:C,I15)=0,"","_"&LOOKUP(I15,'Objets de gestion'!C:C,'Objets de gestion'!F:F)) &IF(COUNTIF('Objets de gestion'!C:C,G15)=0,"","_"&LOOKUP(G15,'Objets de gestion'!C:C,'Objets de gestion'!F:F)) &IF(COUNTIF('Objets de gestion'!C:C,E15)=0,"","_"&LOOKUP(E15,'Objets de gestion'!C:C,'Objets de gestion'!F:F)) &IF(OR(C15="booléen",COUNTIF('Objets de gestion'!C:C,C15)=0),"","_"&LOOKUP(C15,'Objets de gestion'!C:C,'Objets de gestion'!F:F)), IF(L15="Forcé", LOOKUP(B15,'Type de champ'!B:B,'Type de champ'!A:A) &IF(COUNTIF('Objets de gestion'!C:C,E15)=0,"","_"&LOOKUP(E15,'Objets de gestion'!C:C,'Objets de gestion'!F:F)) &IF(COUNTIF('Objets de gestion'!C:C,G15)=0,"","_"&LOOKUP(G15,'Objets de gestion'!C:C,'Objets de gestion'!F:F)) &IF(COUNTIF('Objets de gestion'!C:C,I15)=0,"","_"&LOOKUP(I15,'Objets de gestion'!C:C,'Objets de gestion'!F:F)) &IF(COUNTIF('Objets de gestion'!C:C,K15)=0,"","_"&LOOKUP(K15,'Objets de gestion'!C:C,'Objets de gestion'!F:F)) &IF(OR(C15="booléen",COUNTIF('Objets de gestion'!C:C,C15)=0),"","_"&LOOKUP(C15,'Objets de gestion'!C:C,'Objets de gestion'!F:F)) )))) -> T_ACCMGR_CUS_EDAUID | O15: =IF(AND(ISBLANK(A15),ISBLANK(B15),ISBLANK(C15),ISBLANK(E15),ISBLANK(L15)),"",IF(OR(ISBLANK(A15),ISBLANK(B15),ISBLANK(C15),ISBLANK(E15),ISBLANK(L15)),"-", C15&" "&IF(ISBLANK(E15),"",D15&" "&E15&" ")&IF(ISBLANK(G15),"",F15&" "&G15&" ")&IF(ISBLANK(I15),"",H15&" "&I15&" ")&IF(ISBLANK(K15),"",J15&" "&K15&" "))) -> Date de fin de l'identifiant unique entre client et chargé de clientèle | P15: =IF(AND(ISBLANK(A15),ISBLANK(B15),ISBLANK(C15),ISBLANK(E15),ISBLANK(L15)),"",IF(OR(ISBLANK(A15),ISBLANK(B15),ISBLANK(C15),ISBLANK(E15),ISBLANK(L15)),"-", IF(ISBLANK(C15),"",LOOKUP(C15,'Objets de gestion'!C:C,'Objets de gestion'!E:E)) &IF(ISBLANK(D15),""," "&LOOKUP(D15,Articles!A:A,Articles!B:B)) &IF(ISBLANK(E15),""," "&LOOKUP(E15,'Objets de gestion'!C:C,'Objets de gestion'!E:E)) &IF(ISBLANK(F15),""," "&LOOKUP(F15,Articles!A:A,Articles!B:B)) &IF(ISBLANK(G15),""," "&LOOKUP(G15,'Objets de gestion'!C:C,'Objets de gestion'!E:E)) &IF(ISBLANK(H15),""," "&LOOKUP(H15,Articles!A:A,Articles!B:B)) &IF(ISBLANK(I15),""," "&LOOKUP(I15,'Objets de gestion'!C:C,'Objets de gestion'!E:E)) &IF(ISBLANK(J15),""," "&LOOKUP(J15,Articles!A:A,Articles!B:B)) &IF(ISBLANK(K15),""," "&LOOKUP(K15,'Objets de gestion'!C:C,'Objets de gestion'!E:E)) )) -> End date of UID between customer and Account Manager | Q15: =IF(AND(ISBLANK(A15),ISBLANK(B15),ISBLANK(C15),ISBLANK(E15),ISBLANK(L15)),"",IF(OR(ISBLANK(A15),ISBLANK(B15),ISBLANK(C15),ISBLANK(E15),ISBLANK(L15)),"-", LOOKUP(B15,'Type de champ'!B:B,'Type de champ'!C:C))) -> Date | R15: =IF(AND(ISBLANK(A15),ISBLANK(B15),ISBLANK(E15),ISBLANK(G15),ISBLANK(L15)),"",IF(OR(ISBLANK(A15),ISBLANK(B15),ISBLANK(E15),ISBLANK(G15),ISBLANK(L15)),"-", A15)) -> Tiers
A16: Tiers | B16: Booléen | C16: Booléen | D16: de | E16: dernière image | F16: entre | G16: client | H16: et | I16: chargé de clientèle | L16: Normal | M16: =IF(AND(ISBLANK(A16),ISBLANK(B16),ISBLANK(E16),ISBLANK(G16),ISBLANK(L16)),"",IF(OR(ISBLANK(A16),ISBLANK(B16),ISBLANK(E16),ISBLANK(G16),ISBLANK(L16)),"-",LEN(Tableau47[[#This Row],[Code]]))) -> 16 | N16: =IF(AND(ISBLANK(A16),ISBLANK(B16),ISBLANK(C16),ISBLANK(E16),ISBLANK(L16)),"",IF(OR(ISBLANK(A16),ISBLANK(B16),ISBLANK(C16),ISBLANK(E16),ISBLANK(L16)),"à compléter", IF(L16="Normal", LOOKUP(B16,'Type de champ'!B:B,'Type de champ'!A:A) &IF(COUNTIF('Objets de gestion'!C:C,K16)=0,"","_"&LOOKUP(K16,'Objets de gestion'!C:C,'Objets de gestion'!F:F)) &IF(COUNTIF('Objets de gestion'!C:C,I16)=0,"","_"&LOOKUP(I16,'Objets de gestion'!C:C,'Objets de gestion'!F:F)) &IF(COUNTIF('Objets de gestion'!C:C,G16)=0,"","_"&LOOKUP(G16,'Objets de gestion'!C:C,'Objets de gestion'!F:F)) &IF(COUNTIF('Objets de gestion'!C:C,E16)=0,"","_"&LOOKUP(E16,'Objets de gestion'!C:C,'Objets de gestion'!F:F)) &IF(OR(C16="booléen",COUNTIF('Objets de gestion'!C:C,C16)=0),"","_"&LOOKUP(C16,'Objets de gestion'!C:C,'Objets de gestion'!F:F)), IF(L16="Forcé", LOOKUP(B16,'Type de champ'!B:B,'Type de champ'!A:A) &IF(COUNTIF('Objets de gestion'!C:C,E16)=0,"","_"&LOOKUP(E16,'Objets de gestion'!C:C,'Objets de gestion'!F:F)) &IF(COUNTIF('Objets de gestion'!C:C,G16)=0,"","_"&LOOKUP(G16,'Objets de gestion'!C:C,'Objets de gestion'!F:F)) &IF(COUNTIF('Objets de gestion'!C:C,I16)=0,"","_"&LOOKUP(I16,'Objets de gestion'!C:C,'Objets de gestion'!F:F)) &IF(COUNTIF('Objets de gestion'!C:C,K16)=0,"","_"&LOOKUP(K16,'Objets de gestion'!C:C,'Objets de gestion'!F:F)) &IF(OR(C16="booléen",COUNTIF('Objets de gestion'!C:C,C16)=0),"","_"&LOOKUP(C16,'Objets de gestion'!C:C,'Objets de gestion'!F:F)) )))) -> B_ACCMGR_CUS_LTI | O16: =IF(AND(ISBLANK(A16),ISBLANK(B16),ISBLANK(C16),ISBLANK(E16),ISBLANK(L16)),"",IF(OR(ISBLANK(A16),ISBLANK(B16),ISBLANK(C16),ISBLANK(E16),ISBLANK(L16)),"-", C16&" "&IF(ISBLANK(E16),"",D16&" "&E16&" ")&IF(ISBLANK(G16),"",F16&" "&G16&" ")&IF(ISBLANK(I16),"",H16&" "&I16&" ")&IF(ISBLANK(K16),"",J16&" "&K16&" "))) -> Booléen de dernière image entre client et chargé de clientèle | P16: =IF(AND(ISBLANK(A16),ISBLANK(B16),ISBLANK(C16),ISBLANK(E16),ISBLANK(L16)),"",IF(OR(ISBLANK(A16),ISBLANK(B16),ISBLANK(C16),ISBLANK(E16),ISBLANK(L16)),"-", IF(ISBLANK(C16),"",LOOKUP(C16,'Objets de gestion'!C:C,'Objets de gestion'!E:E)) &IF(ISBLANK(D16),""," "&LOOKUP(D16,Articles!A:A,Articles!B:B)) &IF(ISBLANK(E16),""," "&LOOKUP(E16,'Objets de gestion'!C:C,'Objets de gestion'!E:E)) &IF(ISBLANK(F16),""," "&LOOKUP(F16,Articles!A:A,Articles!B:B)) &IF(ISBLANK(G16),""," "&LOOKUP(G16,'Objets de gestion'!C:C,'Objets de gestion'!E:E)) &IF(ISBLANK(H16),""," "&LOOKUP(H16,Articles!A:A,Articles!B:B)) &IF(ISBLANK(I16),""," "&LOOKUP(I16,'Objets de gestion'!C:C,'Objets de gestion'!E:E)) &IF(ISBLANK(J16),""," "&LOOKUP(J16,Articles!A:A,Articles!B:B)) &IF(ISBLANK(K16),""," "&LOOKUP(K16,'Objets de gestion'!C:C,'Objets de gestion'!E:E)) )) -> boolean of the last image between customer and Account Manager | Q16: =IF(AND(ISBLANK(A16),ISBLANK(B16),ISBLANK(C16),ISBLANK(E16),ISBLANK(L16)),"",IF(OR(ISBLANK(A16),ISBLANK(B16),ISBLANK(C16),ISBLANK(E16),ISBLANK(L16)),"-", LOOKUP(B16,'Type de champ'!B:B,'Type de champ'!C:C))) -> Boolean | R16: =IF(AND(ISBLANK(A16),ISBLANK(B16),ISBLANK(E16),ISBLANK(G16),ISBLANK(L16)),"",IF(OR(ISBLANK(A16),ISBLANK(B16),ISBLANK(E16),ISBLANK(G16),ISBLANK(L16)),"-", A16)) -> Tiers
A17: tiers | B17: Chaine de caractère | C17: code SAS | D17: du | E17: chargé de clientèle | L17: Normal | M17: =IF(AND(ISBLANK(A17),ISBLANK(B17),ISBLANK(E17),ISBLANK(G17),ISBLANK(L17)),"",IF(OR(ISBLANK(A17),ISBLANK(B17),ISBLANK(E17),ISBLANK(G17),ISBLANK(L17)),"-",LEN(Tableau47[[#This Row],[Code]]))) -> - | N17: =IF(AND(ISBLANK(A17),ISBLANK(B17),ISBLANK(C17),ISBLANK(E17),ISBLANK(L17)),"",IF(OR(ISBLANK(A17),ISBLANK(B17),ISBLANK(C17),ISBLANK(E17),ISBLANK(L17)),"à compléter", IF(L17="Normal", LOOKUP(B17,'Type de champ'!B:B,'Type de champ'!A:A) &IF(COUNTIF('Objets de gestion'!C:C,K17)=0,"","_"&LOOKUP(K17,'Objets de gestion'!C:C,'Objets de gestion'!F:F)) &IF(COUNTIF('Objets de gestion'!C:C,I17)=0,"","_"&LOOKUP(I17,'Objets de gestion'!C:C,'Objets de gestion'!F:F)) &IF(COUNTIF('Objets de gestion'!C:C,G17)=0,"","_"&LOOKUP(G17,'Objets de gestion'!C:C,'Objets de gestion'!F:F)) &IF(COUNTIF('Objets de gestion'!C:C,E17)=0,"","_"&LOOKUP(E17,'Objets de gestion'!C:C,'Objets de gestion'!F:F)) &IF(OR(C17="booléen",COUNTIF('Objets de gestion'!C:C,C17)=0),"","_"&LOOKUP(C17,'Objets de gestion'!C:C,'Objets de gestion'!F:F)), IF(L17="Forcé", LOOKUP(B17,'Type de champ'!B:B,'Type de champ'!A:A) &IF(COUNTIF('Objets de gestion'!C:C,E17)=0,"","_"&LOOKUP(E17,'Objets de gestion'!C:C,'Objets de gestion'!F:F)) &IF(COUNTIF('Objets de gestion'!C:C,G17)=0,"","_"&LOOKUP(G17,'Objets de gestion'!C:C,'Objets de gestion'!F:F)) &IF(COUNTIF('Objets de gestion'!C:C,I17)=0,"","_"&LOOKUP(I17,'Objets de gestion'!C:C,'Objets de gestion'!F:F)) &IF(COUNTIF('Objets de gestion'!C:C,K17)=0,"","_"&LOOKUP(K17,'Objets de gestion'!C:C,'Objets de gestion'!F:F)) &IF(OR(C17="booléen",COUNTIF('Objets de gestion'!C:C,C17)=0),"","_"&LOOKUP(C17,'Objets de gestion'!C:C,'Objets de gestion'!F:F)) )))) -> X_ACCMGR_SASCOD | O17: =IF(AND(ISBLANK(A17),ISBLANK(B17),ISBLANK(C17),ISBLANK(E17),ISBLANK(L17)),"",IF(OR(ISBLANK(A17),ISBLANK(B17),ISBLANK(C17),ISBLANK(E17),ISBLANK(L17)),"-", C17&" "&IF(ISBLANK(E17),"",D17&" "&E17&" ")&IF(ISBLANK(G17),"",F17&" "&G17&" ")&IF(ISBLANK(I17),"",H17&" "&I17&" ")&IF(ISBLANK(K17),"",J17&" "&K17&" "))) -> code SAS du chargé de clientèle | P17: =IF(AND(ISBLANK(A17),ISBLANK(B17),ISBLANK(C17),ISBLANK(E17),ISBLANK(L17)),"",IF(OR(ISBLANK(A17),ISBLANK(B17),ISBLANK(C17),ISBLANK(E17),ISBLANK(L17)),"-", IF(ISBLANK(C17),"",LOOKUP(C17,'Objets de gestion'!C:C,'Objets de gestion'!E:E)) &IF(ISBLANK(D17),""," "&LOOKUP(D17,Articles!A:A,Articles!B:B)) &IF(ISBLANK(E17),""," "&LOOKUP(E17,'Objets de gestion'!C:C,'Objets de gestion'!E:E)) &IF(ISBLANK(F17),""," "&LOOKUP(F17,Articles!A:A,Articles!B:B)) &IF(ISBLANK(G17),""," "&LOOKUP(G17,'Objets de gestion'!C:C,'Objets de gestion'!E:E)) &IF(ISBLANK(H17),""," "&LOOKUP(H17,Articles!A:A,Articles!B:B)) &IF(ISBLANK(I17),""," "&LOOKUP(I17,'Objets de gestion'!C:C,'Objets de gestion'!E:E)) &IF(ISBLANK(J17),""," "&LOOKUP(J17,Articles!A:A,Articles!B:B)) &IF(ISBLANK(K17),""," "&LOOKUP(K17,'Objets de gestion'!C:C,'Objets de gestion'!E:E)) )) -> SAS code of the Account Manager | Q17: =IF(AND(ISBLANK(A17),ISBLANK(B17),ISBLANK(C17),ISBLANK(E17),ISBLANK(L17)),"",IF(OR(ISBLANK(A17),ISBLANK(B17),ISBLANK(C17),ISBLANK(E17),ISBLANK(L17)),"-", LOOKUP(B17,'Type de champ'!B:B,'Type de champ'!C:C))) -> Varchar(??) | R17: =IF(AND(ISBLANK(A17),ISBLANK(B17),ISBLANK(E17),ISBLANK(G17),ISBLANK(L17)),"",IF(OR(ISBLANK(A17),ISBLANK(B17),ISBLANK(E17),ISBLANK(G17),ISBLANK(L17)),"-", A17)) -> -
A18: tiers | B18: Chaine de caractère | C18: code | D18: de l' | E18: Entité gestionnaire | F18: du | G18: tiers | L18: Normal | M18: =IF(AND(ISBLANK(A18),ISBLANK(B18),ISBLANK(E18),ISBLANK(G18),ISBLANK(L18)),"",IF(OR(ISBLANK(A18),ISBLANK(B18),ISBLANK(E18),ISBLANK(G18),ISBLANK(L18)),"-",LEN(Tableau47[[#This Row],[Code]]))) -> 16 | N18: =IF(AND(ISBLANK(A18),ISBLANK(B18),ISBLANK(C18),ISBLANK(E18),ISBLANK(L18)),"",IF(OR(ISBLANK(A18),ISBLANK(B18),ISBLANK(C18),ISBLANK(E18),ISBLANK(L18)),"à compléter", IF(L18="Normal", LOOKUP(B18,'Type de champ'!B:B,'Type de champ'!A:A) &IF(COUNTIF('Objets de gestion'!C:C,K18)=0,"","_"&LOOKUP(K18,'Objets de gestion'!C:C,'Objets de gestion'!F:F)) &IF(COUNTIF('Objets de gestion'!C:C,I18)=0,"","_"&LOOKUP(I18,'Objets de gestion'!C:C,'Objets de gestion'!F:F)) &IF(COUNTIF('Objets de gestion'!C:C,G18)=0,"","_"&LOOKUP(G18,'Objets de gestion'!C:C,'Objets de gestion'!F:F)) &IF(COUNTIF('Objets de gestion'!C:C,E18)=0,"","_"&LOOKUP(E18,'Objets de gestion'!C:C,'Objets de gestion'!F:F)) &IF(OR(C18="booléen",COUNTIF('Objets de gestion'!C:C,C18)=0),"","_"&LOOKUP(C18,'Objets de gestion'!C:C,'Objets de gestion'!F:F)), IF(L18="Forcé", LOOKUP(B18,'Type de champ'!B:B,'Type de champ'!A:A) &IF(COUNTIF('Objets de gestion'!C:C,E18)=0,"","_"&LOOKUP(E18,'Objets de gestion'!C:C,'Objets de gestion'!F:F)) &IF(COUNTIF('Objets de gestion'!C:C,G18)=0,"","_"&LOOKUP(G18,'Objets de gestion'!C:C,'Objets de gestion'!F:F)) &IF(COUNTIF('Objets de gestion'!C:C,I18)=0,"","_"&LOOKUP(I18,'Objets de gestion'!C:C,'Objets de gestion'!F:F)) &IF(COUNTIF('Objets de gestion'!C:C,K18)=0,"","_"&LOOKUP(K18,'Objets de gestion'!C:C,'Objets de gestion'!F:F)) &IF(OR(C18="booléen",COUNTIF('Objets de gestion'!C:C,C18)=0),"","_"&LOOKUP(C18,'Objets de gestion'!C:C,'Objets de gestion'!F:F)) )))) -> X_TDP_NTTMGT_COD | O18: =IF(AND(ISBLANK(A18),ISBLANK(B18),ISBLANK(C18),ISBLANK(E18),ISBLANK(L18)),"",IF(OR(ISBLANK(A18),ISBLANK(B18),ISBLANK(C18),ISBLANK(E18),ISBLANK(L18)),"-", C18&" "&IF(ISBLANK(E18),"",D18&" "&E18&" ")&IF(ISBLANK(G18),"",F18&" "&G18&" ")&IF(ISBLANK(I18),"",H18&" "&I18&" ")&IF(ISBLANK(K18),"",J18&" "&K18&" "))) -> code de l' Entité gestionnaire du tiers | P18: =IF(AND(ISBLANK(A18),ISBLANK(B18),ISBLANK(C18),ISBLANK(E18),ISBLANK(L18)),"",IF(OR(ISBLANK(A18),ISBLANK(B18),ISBLANK(C18),ISBLANK(E18),ISBLANK(L18)),"-", IF(ISBLANK(C18),"",LOOKUP(C18,'Objets de gestion'!C:C,'Objets de gestion'!E:E)) &IF(ISBLANK(D18),""," "&LOOKUP(D18,Articles!A:A,Articles!B:B)) &IF(ISBLANK(E18),""," "&LOOKUP(E18,'Objets de gestion'!C:C,'Objets de gestion'!E:E)) &IF(ISBLANK(F18),""," "&LOOKUP(F18,Articles!A:A,Articles!B:B)) &IF(ISBLANK(G18),""," "&LOOKUP(G18,'Objets de gestion'!C:C,'Objets de gestion'!E:E)) &IF(ISBLANK(H18),""," "&LOOKUP(H18,Articles!A:A,Articles!B:B)) &IF(ISBLANK(I18),""," "&LOOKUP(I18,'Objets de gestion'!C:C,'Objets de gestion'!E:E)) &IF(ISBLANK(J18),""," "&LOOKUP(J18,Articles!A:A,Articles!B:B)) &IF(ISBLANK(K18),""," "&LOOKUP(K18,'Objets de gestion'!C:C,'Objets de gestion'!E:E)) )) -> code of the Management Entity of the third party | Q18: =IF(AND(ISBLANK(A18),ISBLANK(B18),ISBLANK(C18),ISBLANK(E18),ISBLANK(L18)),"",IF(OR(ISBLANK(A18),ISBLANK(B18),ISBLANK(C18),ISBLANK(E18),ISBLANK(L18)),"-", LOOKUP(B18,'Type de champ'!B:B,'Type de champ'!C:C))) -> Varchar(??) | R18: =IF(AND(ISBLANK(A18),ISBLANK(B18),ISBLANK(E18),ISBLANK(G18),ISBLANK(L18)),"",IF(OR(ISBLANK(A18),ISBLANK(B18),ISBLANK(E18),ISBLANK(G18),ISBLANK(L18)),"-", A18)) -> tiers
A19: tiers | B19: Chaine de caractère | C19: identifiant fonctionnel | D19: du | E19: tiers | L19: Normal | M19: =IF(AND(ISBLANK(A19),ISBLANK(B19),ISBLANK(E19),ISBLANK(G19),ISBLANK(L19)),"",IF(OR(ISBLANK(A19),ISBLANK(B19),ISBLANK(E19),ISBLANK(G19),ISBLANK(L19)),"-",LEN(Tableau47[[#This Row],[Code]]))) -> - | N19: =IF(AND(ISBLANK(A19),ISBLANK(B19),ISBLANK(C19),ISBLANK(E19),ISBLANK(L19)),"",IF(OR(ISBLANK(A19),ISBLANK(B19),ISBLANK(C19),ISBLANK(E19),ISBLANK(L19)),"à compléter", IF(L19="Normal", LOOKUP(B19,'Type de champ'!B:B,'Type de champ'!A:A) &IF(COUNTIF('Objets de gestion'!C:C,K19)=0,"","_"&LOOKUP(K19,'Objets de gestion'!C:C,'Objets de gestion'!F:F)) &IF(COUNTIF('Objets de gestion'!C:C,I19)=0,"","_"&LOOKUP(I19,'Objets de gestion'!C:C,'Objets de gestion'!F:F)) &IF(COUNTIF('Objets de gestion'!C:C,G19)=0,"","_"&LOOKUP(G19,'Objets de gestion'!C:C,'Objets de gestion'!F:F)) &IF(COUNTIF('Objets de gestion'!C:C,E19)=0,"","_"&LOOKUP(E19,'Objets de gestion'!C:C,'Objets de gestion'!F:F)) &IF(OR(C19="booléen",COUNTIF('Objets de gestion'!C:C,C19)=0),"","_"&LOOKUP(C19,'Objets de gestion'!C:C,'Objets de gestion'!F:F)), IF(L19="Forcé", LOOKUP(B19,'Type de champ'!B:B,'Type de champ'!A:A) &IF(COUNTIF('Objets de gestion'!C:C,E19)=0,"","_"&LOOKUP(E19,'Objets de gestion'!C:C,'Objets de gestion'!F:F)) &IF(COUNTIF('Objets de gestion'!C:C,G19)=0,"","_"&LOOKUP(G19,'Objets de gestion'!C:C,'Objets de gestion'!F:F)) &IF(COUNTIF('Objets de gestion'!C:C,I19)=0,"","_"&LOOKUP(I19,'Objets de gestion'!C:C,'Objets de gestion'!F:F)) &IF(COUNTIF('Objets de gestion'!C:C,K19)=0,"","_"&LOOKUP(K19,'Objets de gestion'!C:C,'Objets de gestion'!F:F)) &IF(OR(C19="booléen",COUNTIF('Objets de gestion'!C:C,C19)=0),"","_"&LOOKUP(C19,'Objets de gestion'!C:C,'Objets de gestion'!F:F)) )))) -> X_TDP_FCTIDT | O19: =IF(AND(ISBLANK(A19),ISBLANK(B19),ISBLANK(C19),ISBLANK(E19),ISBLANK(L19)),"",IF(OR(ISBLANK(A19),ISBLANK(B19),ISBLANK(C19),ISBLANK(E19),ISBLANK(L19)),"-", C19&" "&IF(ISBLANK(E19),"",D19&" "&E19&" ")&IF(ISBLANK(G19),"",F19&" "&G19&" ")&IF(ISBLANK(I19),"",H19&" "&I19&" ")&IF(ISBLANK(K19),"",J19&" "&K19&" "))) -> identifiant fonctionnel du tiers | P19: =IF(AND(ISBLANK(A19),ISBLANK(B19),ISBLANK(C19),ISBLANK(E19),ISBLANK(L19)),"",IF(OR(ISBLANK(A19),ISBLANK(B19),ISBLANK(C19),ISBLANK(E19),ISBLANK(L19)),"-", IF(ISBLANK(C19),"",LOOKUP(C19,'Objets de gestion'!C:C,'Objets de gestion'!E:E)) &IF(ISBLANK(D19),""," "&LOOKUP(D19,Articles!A:A,Articles!B:B)) &IF(ISBLANK(E19),""," "&LOOKUP(E19,'Objets de gestion'!C:C,'Objets de gestion'!E:E)) &IF(ISBLANK(F19),""," "&LOOKUP(F19,Articles!A:A,Articles!B:B)) &IF(ISBLANK(G19),""," "&LOOKUP(G19,'Objets de gestion'!C:C,'Objets de gestion'!E:E)) &IF(ISBLANK(H19),""," "&LOOKUP(H19,Articles!A:A,Articles!B:B)) &IF(ISBLANK(I19),""," "&LOOKUP(I19,'Objets de gestion'!C:C,'Objets de gestion'!E:E)) &IF(ISBLANK(J19),""," "&LOOKUP(J19,Articles!A:A,Articles!B:B)) &IF(ISBLANK(K19),""," "&LOOKUP(K19,'Objets de gestion'!C:C,'Objets de gestion'!E:E)) )) -> functional identifier of the third party | Q19: =IF(AND(ISBLANK(A19),ISBLANK(B19),ISBLANK(C19),ISBLANK(E19),ISBLANK(L19)),"",IF(OR(ISBLANK(A19),ISBLANK(B19),ISBLANK(C19),ISBLANK(E19),ISBLANK(L19)),"-", LOOKUP(B19,'Type de champ'!B:B,'Type de champ'!C:C))) -> Varchar(??) | R19: =IF(AND(ISBLANK(A19),ISBLANK(B19),ISBLANK(E19),ISBLANK(G19),ISBLANK(L19)),"",IF(OR(ISBLANK(A19),ISBLANK(B19),ISBLANK(E19),ISBLANK(G19),ISBLANK(L19)),"-", A19)) -> -
A20: tiers | B20: Chaine de caractère | C20: code | D20: de la | E20: fédération | F20: du | G20: tiers | L20: Normal | M20: =IF(AND(ISBLANK(A20),ISBLANK(B20),ISBLANK(E20),ISBLANK(G20),ISBLANK(L20)),"",IF(OR(ISBLANK(A20),ISBLANK(B20),ISBLANK(E20),ISBLANK(G20),ISBLANK(L20)),"-",LEN(Tableau47[[#This Row],[Code]]))) -> 13 | N20: =IF(AND(ISBLANK(A20),ISBLANK(B20),ISBLANK(C20),ISBLANK(E20),ISBLANK(L20)),"",IF(OR(ISBLANK(A20),ISBLANK(B20),ISBLANK(C20),ISBLANK(E20),ISBLANK(L20)),"à compléter", IF(L20="Normal", LOOKUP(B20,'Type de champ'!B:B,'Type de champ'!A:A) &IF(COUNTIF('Objets de gestion'!C:C,K20)=0,"","_"&LOOKUP(K20,'Objets de gestion'!C:C,'Objets de gestion'!F:F)) &IF(COUNTIF('Objets de gestion'!C:C,I20)=0,"","_"&LOOKUP(I20,'Objets de gestion'!C:C,'Objets de gestion'!F:F)) &IF(COUNTIF('Objets de gestion'!C:C,G20)=0,"","_"&LOOKUP(G20,'Objets de gestion'!C:C,'Objets de gestion'!F:F)) &IF(COUNTIF('Objets de gestion'!C:C,E20)=0,"","_"&LOOKUP(E20,'Objets de gestion'!C:C,'Objets de gestion'!F:F)) &IF(OR(C20="booléen",COUNTIF('Objets de gestion'!C:C,C20)=0),"","_"&LOOKUP(C20,'Objets de gestion'!C:C,'Objets de gestion'!F:F)), IF(L20="Forcé", LOOKUP(B20,'Type de champ'!B:B,'Type de champ'!A:A) &IF(COUNTIF('Objets de gestion'!C:C,E20)=0,"","_"&LOOKUP(E20,'Objets de gestion'!C:C,'Objets de gestion'!F:F)) &IF(COUNTIF('Objets de gestion'!C:C,G20)=0,"","_"&LOOKUP(G20,'Objets de gestion'!C:C,'Objets de gestion'!F:F)) &IF(COUNTIF('Objets de gestion'!C:C,I20)=0,"","_"&LOOKUP(I20,'Objets de gestion'!C:C,'Objets de gestion'!F:F)) &IF(COUNTIF('Objets de gestion'!C:C,K20)=0,"","_"&LOOKUP(K20,'Objets de gestion'!C:C,'Objets de gestion'!F:F)) &IF(OR(C20="booléen",COUNTIF('Objets de gestion'!C:C,C20)=0),"","_"&LOOKUP(C20,'Objets de gestion'!C:C,'Objets de gestion'!F:F)) )))) -> X_TDP_FED_COD | O20: =IF(AND(ISBLANK(A20),ISBLANK(B20),ISBLANK(C20),ISBLANK(E20),ISBLANK(L20)),"",IF(OR(ISBLANK(A20),ISBLANK(B20),ISBLANK(C20),ISBLANK(E20),ISBLANK(L20)),"-", C20&" "&IF(ISBLANK(E20),"",D20&" "&E20&" ")&IF(ISBLANK(G20),"",F20&" "&G20&" ")&IF(ISBLANK(I20),"",H20&" "&I20&" ")&IF(ISBLANK(K20),"",J20&" "&K20&" "))) -> code de la fédération du tiers | P20: =IF(AND(ISBLANK(A20),ISBLANK(B20),ISBLANK(C20),ISBLANK(E20),ISBLANK(L20)),"",IF(OR(ISBLANK(A20),ISBLANK(B20),ISBLANK(C20),ISBLANK(E20),ISBLANK(L20)),"-", IF(ISBLANK(C20),"",LOOKUP(C20,'Objets de gestion'!C:C,'Objets de gestion'!E:E)) &IF(ISBLANK(D20),""," "&LOOKUP(D20,Articles!A:A,Articles!B:B)) &IF(ISBLANK(E20),""," "&LOOKUP(E20,'Objets de gestion'!C:C,'Objets de gestion'!E:E)) &IF(ISBLANK(F20),""," "&LOOKUP(F20,Articles!A:A,Articles!B:B)) &IF(ISBLANK(G20),""," "&LOOKUP(G20,'Objets de gestion'!C:C,'Objets de gestion'!E:E)) &IF(ISBLANK(H20),""," "&LOOKUP(H20,Articles!A:A,Articles!B:B)) &IF(ISBLANK(I20),""," "&LOOKUP(I20,'Objets de gestion'!C:C,'Objets de gestion'!E:E)) &IF(ISBLANK(J20),""," "&LOOKUP(J20,Articles!A:A,Articles!B:B)) &IF(ISBLANK(K20),""," "&LOOKUP(K20,'Objets de gestion'!C:C,'Objets de gestion'!E:E)) )) -> code of the Federation of the third party | Q20: =IF(AND(ISBLANK(A20),ISBLANK(B20),ISBLANK(C20),ISBLANK(E20),ISBLANK(L20)),"",IF(OR(ISBLANK(A20),ISBLANK(B20),ISBLANK(C20),ISBLANK(E20),ISBLANK(L20)),"-", LOOKUP(B20,'Type de champ'!B:B,'Type de champ'!C:C))) -> Varchar(??) | R20: =IF(AND(ISBLANK(A20),ISBLANK(B20),ISBLANK(E20),ISBLANK(G20),ISBLANK(L20)),"",IF(OR(ISBLANK(A20),ISBLANK(B20),ISBLANK(E20),ISBLANK(G20),ISBLANK(L20)),"-", A20)) -> tiers
A21: tiers | B21: Chaine de caractère | C21: code | D21: de l' | E21: établissement | F21: du | G21: tiers | L21: Normal | M21: =IF(AND(ISBLANK(A21),ISBLANK(B21),ISBLANK(E21),ISBLANK(G21),ISBLANK(L21)),"",IF(OR(ISBLANK(A21),ISBLANK(B21),ISBLANK(E21),ISBLANK(G21),ISBLANK(L21)),"-",LEN(Tableau47[[#This Row],[Code]]))) -> 13 | N21: =IF(AND(ISBLANK(A21),ISBLANK(B21),ISBLANK(C21),ISBLANK(E21),ISBLANK(L21)),"",IF(OR(ISBLANK(A21),ISBLANK(B21),ISBLANK(C21),ISBLANK(E21),ISBLANK(L21)),"à compléter", IF(L21="Normal", LOOKUP(B21,'Type de champ'!B:B,'Type de champ'!A:A) &IF(COUNTIF('Objets de gestion'!C:C,K21)=0,"","_"&LOOKUP(K21,'Objets de gestion'!C:C,'Objets de gestion'!F:F)) &IF(COUNTIF('Objets de gestion'!C:C,I21)=0,"","_"&LOOKUP(I21,'Objets de gestion'!C:C,'Objets de gestion'!F:F)) &IF(COUNTIF('Objets de gestion'!C:C,G21)=0,"","_"&LOOKUP(G21,'Objets de gestion'!C:C,'Objets de gestion'!F:F)) &IF(COUNTIF('Objets de gestion'!C:C,E21)=0,"","_"&LOOKUP(E21,'Objets de gestion'!C:C,'Objets de gestion'!F:F)) &IF(OR(C21="booléen",COUNTIF('Objets de gestion'!C:C,C21)=0),"","_"&LOOKUP(C21,'Objets de gestion'!C:C,'Objets de gestion'!F:F)), IF(L21="Forcé", LOOKUP(B21,'Type de champ'!B:B,'Type de champ'!A:A) &IF(COUNTIF('Objets de gestion'!C:C,E21)=0,"","_"&LOOKUP(E21,'Objets de gestion'!C:C,'Objets de gestion'!F:F)) &IF(COUNTIF('Objets de gestion'!C:C,G21)=0,"","_"&LOOKUP(G21,'Objets de gestion'!C:C,'Objets de gestion'!F:F)) &IF(COUNTIF('Objets de gestion'!C:C,I21)=0,"","_"&LOOKUP(I21,'Objets de gestion'!C:C,'Objets de gestion'!F:F)) &IF(COUNTIF('Objets de gestion'!C:C,K21)=0,"","_"&LOOKUP(K21,'Objets de gestion'!C:C,'Objets de gestion'!F:F)) &IF(OR(C21="booléen",COUNTIF('Objets de gestion'!C:C,C21)=0),"","_"&LOOKUP(C21,'Objets de gestion'!C:C,'Objets de gestion'!F:F)) )))) -> X_TDP_EST_COD | O21: =IF(AND(ISBLANK(A21),ISBLANK(B21),ISBLANK(C21),ISBLANK(E21),ISBLANK(L21)),"",IF(OR(ISBLANK(A21),ISBLANK(B21),ISBLANK(C21),ISBLANK(E21),ISBLANK(L21)),"-", C21&" "&IF(ISBLANK(E21),"",D21&" "&E21&" ")&IF(ISBLANK(G21),"",F21&" "&G21&" ")&IF(ISBLANK(I21),"",H21&" "&I21&" ")&IF(ISBLANK(K21),"",J21&" "&K21&" "))) -> code de l' établissement du tiers | P21: =IF(AND(ISBLANK(A21),ISBLANK(B21),ISBLANK(C21),ISBLANK(E21),ISBLANK(L21)),"",IF(OR(ISBLANK(A21),ISBLANK(B21),ISBLANK(C21),ISBLANK(E21),ISBLANK(L21)),"-", IF(ISBLANK(C21),"",LOOKUP(C21,'Objets de gestion'!C:C,'Objets de gestion'!E:E)) &IF(ISBLANK(D21),""," "&LOOKUP(D21,Articles!A:A,Articles!B:B)) &IF(ISBLANK(E21),""," "&LOOKUP(E21,'Objets de gestion'!C:C,'Objets de gestion'!E:E)) &IF(ISBLANK(F21),""," "&LOOKUP(F21,Articles!A:A,Articles!B:B)) &IF(ISBLANK(G21),""," "&LOOKUP(G21,'Objets de gestion'!C:C,'Objets de gestion'!E:E)) &IF(ISBLANK(H21),""," "&LOOKUP(H21,Articles!A:A,Articles!B:B)) &IF(ISBLANK(I21),""," "&LOOKUP(I21,'Objets de gestion'!C:C,'Objets de gestion'!E:E)) &IF(ISBLANK(J21),""," "&LOOKUP(J21,Articles!A:A,Articles!B:B)) &IF(ISBLANK(K21),""," "&LOOKUP(K21,'Objets de gestion'!C:C,'Objets de gestion'!E:E)) )) -> code of the establishment of the third party | Q21: =IF(AND(ISBLANK(A21),ISBLANK(B21),ISBLANK(C21),ISBLANK(E21),ISBLANK(L21)),"",IF(OR(ISBLANK(A21),ISBLANK(B21),ISBLANK(C21),ISBLANK(E21),ISBLANK(L21)),"-", LOOKUP(B21,'Type de champ'!B:B,'Type de champ'!C:C))) -> Varchar(??) | R21: =IF(AND(ISBLANK(A21),ISBLANK(B21),ISBLANK(E21),ISBLANK(G21),ISBLANK(L21)),"",IF(OR(ISBLANK(A21),ISBLANK(B21),ISBLANK(E21),ISBLANK(G21),ISBLANK(L21)),"-", A21)) -> tiers
A22: tiers | B22: Chaine de caractère | C22: code | D22: du | E22: guichet | F22: du | G22: tiers | L22: Normal | M22: =IF(AND(ISBLANK(A22),ISBLANK(B22),ISBLANK(E22),ISBLANK(G22),ISBLANK(L22)),"",IF(OR(ISBLANK(A22),ISBLANK(B22),ISBLANK(E22),ISBLANK(G22),ISBLANK(L22)),"-",LEN(Tableau47[[#This Row],[Code]]))) -> 13 | N22: =IF(AND(ISBLANK(A22),ISBLANK(B22),ISBLANK(C22),ISBLANK(E22),ISBLANK(L22)),"",IF(OR(ISBLANK(A22),ISBLANK(B22),ISBLANK(C22),ISBLANK(E22),ISBLANK(L22)),"à compléter", IF(L22="Normal", LOOKUP(B22,'Type de champ'!B:B,'Type de champ'!A:A) &IF(COUNTIF('Objets de gestion'!C:C,K22)=0,"","_"&LOOKUP(K22,'Objets de gestion'!C:C,'Objets de gestion'!F:F)) &IF(COUNTIF('Objets de gestion'!C:C,I22)=0,"","_"&LOOKUP(I22,'Objets de gestion'!C:C,'Objets de gestion'!F:F)) &IF(COUNTIF('Objets de gestion'!C:C,G22)=0,"","_"&LOOKUP(G22,'Objets de gestion'!C:C,'Objets de gestion'!F:F)) &IF(COUNTIF('Objets de gestion'!C:C,E22)=0,"","_"&LOOKUP(E22,'Objets de gestion'!C:C,'Objets de gestion'!F:F)) &IF(OR(C22="booléen",COUNTIF('Objets de gestion'!C:C,C22)=0),"","_"&LOOKUP(C22,'Objets de gestion'!C:C,'Objets de gestion'!F:F)), IF(L22="Forcé", LOOKUP(B22,'Type de champ'!B:B,'Type de champ'!A:A) &IF(COUNTIF('Objets de gestion'!C:C,E22)=0,"","_"&LOOKUP(E22,'Objets de gestion'!C:C,'Objets de gestion'!F:F)) &IF(COUNTIF('Objets de gestion'!C:C,G22)=0,"","_"&LOOKUP(G22,'Objets de gestion'!C:C,'Objets de gestion'!F:F)) &IF(COUNTIF('Objets de gestion'!C:C,I22)=0,"","_"&LOOKUP(I22,'Objets de gestion'!C:C,'Objets de gestion'!F:F)) &IF(COUNTIF('Objets de gestion'!C:C,K22)=0,"","_"&LOOKUP(K22,'Objets de gestion'!C:C,'Objets de gestion'!F:F)) &IF(OR(C22="booléen",COUNTIF('Objets de gestion'!C:C,C22)=0),"","_"&LOOKUP(C22,'Objets de gestion'!C:C,'Objets de gestion'!F:F)) )))) -> X_TDP_BRC_COD | O22: =IF(AND(ISBLANK(A22),ISBLANK(B22),ISBLANK(C22),ISBLANK(E22),ISBLANK(L22)),"",IF(OR(ISBLANK(A22),ISBLANK(B22),ISBLANK(C22),ISBLANK(E22),ISBLANK(L22)),"-", C22&" "&IF(ISBLANK(E22),"",D22&" "&E22&" ")&IF(ISBLANK(G22),"",F22&" "&G22&" ")&IF(ISBLANK(I22),"",H22&" "&I22&" ")&IF(ISBLANK(K22),"",J22&" "&K22&" "))) -> code du guichet du tiers | P22: =IF(AND(ISBLANK(A22),ISBLANK(B22),ISBLANK(C22),ISBLANK(E22),ISBLANK(L22)),"",IF(OR(ISBLANK(A22),ISBLANK(B22),ISBLANK(C22),ISBLANK(E22),ISBLANK(L22)),"-", IF(ISBLANK(C22),"",LOOKUP(C22,'Objets de gestion'!C:C,'Objets de gestion'!E:E)) &IF(ISBLANK(D22),""," "&LOOKUP(D22,Articles!A:A,Articles!B:B)) &IF(ISBLANK(E22),""," "&LOOKUP(E22,'Objets de gestion'!C:C,'Objets de gestion'!E:E)) &IF(ISBLANK(F22),""," "&LOOKUP(F22,Articles!A:A,Articles!B:B)) &IF(ISBLANK(G22),""," "&LOOKUP(G22,'Objets de gestion'!C:C,'Objets de gestion'!E:E)) &IF(ISBLANK(H22),""," "&LOOKUP(H22,Articles!A:A,Articles!B:B)) &IF(ISBLANK(I22),""," "&LOOKUP(I22,'Objets de gestion'!C:C,'Objets de gestion'!E:E)) &IF(ISBLANK(J22),""," "&LOOKUP(J22,Articles!A:A,Articles!B:B)) &IF(ISBLANK(K22),""," "&LOOKUP(K22,'Objets de gestion'!C:C,'Objets de gestion'!E:E)) )) -> code of the branches of the third party | Q22: =IF(AND(ISBLANK(A22),ISBLANK(B22),ISBLANK(C22),ISBLANK(E22),ISBLANK(L22)),"",IF(OR(ISBLANK(A22),ISBLANK(B22),ISBLANK(C22),ISBLANK(E22),ISBLANK(L22)),"-", LOOKUP(B22,'Type de champ'!B:B,'Type de champ'!C:C))) -> Varchar(??) | R22: =IF(AND(ISBLANK(A22),ISBLANK(B22),ISBLANK(E22),ISBLANK(G22),ISBLANK(L22)),"",IF(OR(ISBLANK(A22),ISBLANK(B22),ISBLANK(E22),ISBLANK(G22),ISBLANK(L22)),"-", A22)) -> tiers
A23: tiers | B23: Chaine de caractère | C23: code | D23: du | E23: bureau | F23: du | G23: tiers | L23: Normal | M23: =IF(AND(ISBLANK(A23),ISBLANK(B23),ISBLANK(E23),ISBLANK(G23),ISBLANK(L23)),"",IF(OR(ISBLANK(A23),ISBLANK(B23),ISBLANK(E23),ISBLANK(G23),ISBLANK(L23)),"-",LEN(Tableau47[[#This Row],[Code]]))) -> 13 | N23: =IF(AND(ISBLANK(A23),ISBLANK(B23),ISBLANK(C23),ISBLANK(E23),ISBLANK(L23)),"",IF(OR(ISBLANK(A23),ISBLANK(B23),ISBLANK(C23),ISBLANK(E23),ISBLANK(L23)),"à compléter", IF(L23="Normal", LOOKUP(B23,'Type de champ'!B:B,'Type de champ'!A:A) &IF(COUNTIF('Objets de gestion'!C:C,K23)=0,"","_"&LOOKUP(K23,'Objets de gestion'!C:C,'Objets de gestion'!F:F)) &IF(COUNTIF('Objets de gestion'!C:C,I23)=0,"","_"&LOOKUP(I23,'Objets de gestion'!C:C,'Objets de gestion'!F:F)) &IF(COUNTIF('Objets de gestion'!C:C,G23)=0,"","_"&LOOKUP(G23,'Objets de gestion'!C:C,'Objets de gestion'!F:F)) &IF(COUNTIF('Objets de gestion'!C:C,E23)=0,"","_"&LOOKUP(E23,'Objets de gestion'!C:C,'Objets de gestion'!F:F)) &IF(OR(C23="booléen",COUNTIF('Objets de gestion'!C:C,C23)=0),"","_"&LOOKUP(C23,'Objets de gestion'!C:C,'Objets de gestion'!F:F)), IF(L23="Forcé", LOOKUP(B23,'Type de champ'!B:B,'Type de champ'!A:A) &IF(COUNTIF('Objets de gestion'!C:C,E23)=0,"","_"&LOOKUP(E23,'Objets de gestion'!C:C,'Objets de gestion'!F:F)) &IF(COUNTIF('Objets de gestion'!C:C,G23)=0,"","_"&LOOKUP(G23,'Objets de gestion'!C:C,'Objets de gestion'!F:F)) &IF(COUNTIF('Objets de gestion'!C:C,I23)=0,"","_"&LOOKUP(I23,'Objets de gestion'!C:C,'Objets de gestion'!F:F)) &IF(COUNTIF('Objets de gestion'!C:C,K23)=0,"","_"&LOOKUP(K23,'Objets de gestion'!C:C,'Objets de gestion'!F:F)) &IF(OR(C23="booléen",COUNTIF('Objets de gestion'!C:C,C23)=0),"","_"&LOOKUP(C23,'Objets de gestion'!C:C,'Objets de gestion'!F:F)) )))) -> X_TDP_OFC_COD | O23: =IF(AND(ISBLANK(A23),ISBLANK(B23),ISBLANK(C23),ISBLANK(E23),ISBLANK(L23)),"",IF(OR(ISBLANK(A23),ISBLANK(B23),ISBLANK(C23),ISBLANK(E23),ISBLANK(L23)),"-", C23&" "&IF(ISBLANK(E23),"",D23&" "&E23&" ")&IF(ISBLANK(G23),"",F23&" "&G23&" ")&IF(ISBLANK(I23),"",H23&" "&I23&" ")&IF(ISBLANK(K23),"",J23&" "&K23&" "))) -> code du bureau du tiers | P23: =IF(AND(ISBLANK(A23),ISBLANK(B23),ISBLANK(C23),ISBLANK(E23),ISBLANK(L23)),"",IF(OR(ISBLANK(A23),ISBLANK(B23),ISBLANK(C23),ISBLANK(E23),ISBLANK(L23)),"-", IF(ISBLANK(C23),"",LOOKUP(C23,'Objets de gestion'!C:C,'Objets de gestion'!E:E)) &IF(ISBLANK(D23),""," "&LOOKUP(D23,Articles!A:A,Articles!B:B)) &IF(ISBLANK(E23),""," "&LOOKUP(E23,'Objets de gestion'!C:C,'Objets de gestion'!E:E)) &IF(ISBLANK(F23),""," "&LOOKUP(F23,Articles!A:A,Articles!B:B)) &IF(ISBLANK(G23),""," "&LOOKUP(G23,'Objets de gestion'!C:C,'Objets de gestion'!E:E)) &IF(ISBLANK(H23),""," "&LOOKUP(H23,Articles!A:A,Articles!B:B)) &IF(ISBLANK(I23),""," "&LOOKUP(I23,'Objets de gestion'!C:C,'Objets de gestion'!E:E)) &IF(ISBLANK(J23),""," "&LOOKUP(J23,Articles!A:A,Articles!B:B)) &IF(ISBLANK(K23),""," "&LOOKUP(K23,'Objets de gestion'!C:C,'Objets de gestion'!E:E)) )) -> code of the office of the third party | Q23: =IF(AND(ISBLANK(A23),ISBLANK(B23),ISBLANK(C23),ISBLANK(E23),ISBLANK(L23)),"",IF(OR(ISBLANK(A23),ISBLANK(B23),ISBLANK(C23),ISBLANK(E23),ISBLANK(L23)),"-", LOOKUP(B23,'Type de champ'!B:B,'Type de champ'!C:C))) -> Varchar(??) | R23: =IF(AND(ISBLANK(A23),ISBLANK(B23),ISBLANK(E23),ISBLANK(G23),ISBLANK(L23)),"",IF(OR(ISBLANK(A23),ISBLANK(B23),ISBLANK(E23),ISBLANK(G23),ISBLANK(L23)),"-", A23)) -> tiers
A24: tiers | B24: Chaine de caractère | C24: code | D24: du | E24: portefeuille | F24: de | G24: rattachement | L24: Normal | M24: =IF(AND(ISBLANK(A24),ISBLANK(B24),ISBLANK(E24),ISBLANK(G24),ISBLANK(L24)),"",IF(OR(ISBLANK(A24),ISBLANK(B24),ISBLANK(E24),ISBLANK(G24),ISBLANK(L24)),"-",LEN(Tableau47[[#This Row],[Code]]))) -> 13 | N24: =IF(AND(ISBLANK(A24),ISBLANK(B24),ISBLANK(C24),ISBLANK(E24),ISBLANK(L24)),"",IF(OR(ISBLANK(A24),ISBLANK(B24),ISBLANK(C24),ISBLANK(E24),ISBLANK(L24)),"à compléter", IF(L24="Normal", LOOKUP(B24,'Type de champ'!B:B,'Type de champ'!A:A) &IF(COUNTIF('Objets de gestion'!C:C,K24)=0,"","_"&LOOKUP(K24,'Objets de gestion'!C:C,'Objets de gestion'!F:F)) &IF(COUNTIF('Objets de gestion'!C:C,I24)=0,"","_"&LOOKUP(I24,'Objets de gestion'!C:C,'Objets de gestion'!F:F)) &IF(COUNTIF('Objets de gestion'!C:C,G24)=0,"","_"&LOOKUP(G24,'Objets de gestion'!C:C,'Objets de gestion'!F:F)) &IF(COUNTIF('Objets de gestion'!C:C,E24)=0,"","_"&LOOKUP(E24,'Objets de gestion'!C:C,'Objets de gestion'!F:F)) &IF(OR(C24="booléen",COUNTIF('Objets de gestion'!C:C,C24)=0),"","_"&LOOKUP(C24,'Objets de gestion'!C:C,'Objets de gestion'!F:F)), IF(L24="Forcé", LOOKUP(B24,'Type de champ'!B:B,'Type de champ'!A:A) &IF(COUNTIF('Objets de gestion'!C:C,E24)=0,"","_"&LOOKUP(E24,'Objets de gestion'!C:C,'Objets de gestion'!F:F)) &IF(COUNTIF('Objets de gestion'!C:C,G24)=0,"","_"&LOOKUP(G24,'Objets de gestion'!C:C,'Objets de gestion'!F:F)) &IF(COUNTIF('Objets de gestion'!C:C,I24)=0,"","_"&LOOKUP(I24,'Objets de gestion'!C:C,'Objets de gestion'!F:F)) &IF(COUNTIF('Objets de gestion'!C:C,K24)=0,"","_"&LOOKUP(K24,'Objets de gestion'!C:C,'Objets de gestion'!F:F)) &IF(OR(C24="booléen",COUNTIF('Objets de gestion'!C:C,C24)=0),"","_"&LOOKUP(C24,'Objets de gestion'!C:C,'Objets de gestion'!F:F)) )))) -> X_ATT_PTF_COD | O24: =IF(AND(ISBLANK(A24),ISBLANK(B24),ISBLANK(C24),ISBLANK(E24),ISBLANK(L24)),"",IF(OR(ISBLANK(A24),ISBLANK(B24),ISBLANK(C24),ISBLANK(E24),ISBLANK(L24)),"-", C24&" "&IF(ISBLANK(E24),"",D24&" "&E24&" ")&IF(ISBLANK(G24),"",F24&" "&G24&" ")&IF(ISBLANK(I24),"",H24&" "&I24&" ")&IF(ISBLANK(K24),"",J24&" "&K24&" "))) -> code du portefeuille de rattachement | P24: =IF(AND(ISBLANK(A24),ISBLANK(B24),ISBLANK(C24),ISBLANK(E24),ISBLANK(L24)),"",IF(OR(ISBLANK(A24),ISBLANK(B24),ISBLANK(C24),ISBLANK(E24),ISBLANK(L24)),"-", IF(ISBLANK(C24),"",LOOKUP(C24,'Objets de gestion'!C:C,'Objets de gestion'!E:E)) &IF(ISBLANK(D24),""," "&LOOKUP(D24,Articles!A:A,Articles!B:B)) &IF(ISBLANK(E24),""," "&LOOKUP(E24,'Objets de gestion'!C:C,'Objets de gestion'!E:E)) &IF(ISBLANK(F24),""," "&LOOKUP(F24,Articles!A:A,Articles!B:B)) &IF(ISBLANK(G24),""," "&LOOKUP(G24,'Objets de gestion'!C:C,'Objets de gestion'!E:E)) &IF(ISBLANK(H24),""," "&LOOKUP(H24,Articles!A:A,Articles!B:B)) &IF(ISBLANK(I24),""," "&LOOKUP(I24,'Objets de gestion'!C:C,'Objets de gestion'!E:E)) &IF(ISBLANK(J24),""," "&LOOKUP(J24,Articles!A:A,Articles!B:B)) &IF(ISBLANK(K24),""," "&LOOKUP(K24,'Objets de gestion'!C:C,'Objets de gestion'!E:E)) )) -> code of the portfolio of the attachment | Q24: =IF(AND(ISBLANK(A24),ISBLANK(B24),ISBLANK(C24),ISBLANK(E24),ISBLANK(L24)),"",IF(OR(ISBLANK(A24),ISBLANK(B24),ISBLANK(C24),ISBLANK(E24),ISBLANK(L24)),"-", LOOKUP(B24,'Type de champ'!B:B,'Type de champ'!C:C))) -> Varchar(??) | R24: =IF(AND(ISBLANK(A24),ISBLANK(B24),ISBLANK(E24),ISBLANK(G24),ISBLANK(L24)),"",IF(OR(ISBLANK(A24),ISBLANK(B24),ISBLANK(E24),ISBLANK(G24),ISBLANK(L24)),"-", A24)) -> tiers
A25: tiers | B25: Chaine de caractère | C25: Libellé | D25: du | E25: portefeuille | F25: de | G25: rattachement | L25: Normal | M25: =IF(AND(ISBLANK(A25),ISBLANK(B25),ISBLANK(E25),ISBLANK(G25),ISBLANK(L25)),"",IF(OR(ISBLANK(A25),ISBLANK(B25),ISBLANK(E25),ISBLANK(G25),ISBLANK(L25)),"-",LEN(Tableau47[[#This Row],[Code]]))) -> 13 | N25: =IF(AND(ISBLANK(A25),ISBLANK(B25),ISBLANK(C25),ISBLANK(E25),ISBLANK(L25)),"",IF(OR(ISBLANK(A25),ISBLANK(B25),ISBLANK(C25),ISBLANK(E25),ISBLANK(L25)),"à compléter", IF(L25="Normal", LOOKUP(B25,'Type de champ'!B:B,'Type de champ'!A:A) &IF(COUNTIF('Objets de gestion'!C:C,K25)=0,"","_"&LOOKUP(K25,'Objets de gestion'!C:C,'Objets de gestion'!F:F)) &IF(COUNTIF('Objets de gestion'!C:C,I25)=0,"","_"&LOOKUP(I25,'Objets de gestion'!C:C,'Objets de gestion'!F:F)) &IF(COUNTIF('Objets de gestion'!C:C,G25)=0,"","_"&LOOKUP(G25,'Objets de gestion'!C:C,'Objets de gestion'!F:F)) &IF(COUNTIF('Objets de gestion'!C:C,E25)=0,"","_"&LOOKUP(E25,'Objets de gestion'!C:C,'Objets de gestion'!F:F)) &IF(OR(C25="booléen",COUNTIF('Objets de gestion'!C:C,C25)=0),"","_"&LOOKUP(C25,'Objets de gestion'!C:C,'Objets de gestion'!F:F)), IF(L25="Forcé", LOOKUP(B25,'Type de champ'!B:B,'Type de champ'!A:A) &IF(COUNTIF('Objets de gestion'!C:C,E25)=0,"","_"&LOOKUP(E25,'Objets de gestion'!C:C,'Objets de gestion'!F:F)) &IF(COUNTIF('Objets de gestion'!C:C,G25)=0,"","_"&LOOKUP(G25,'Objets de gestion'!C:C,'Objets de gestion'!F:F)) &IF(COUNTIF('Objets de gestion'!C:C,I25)=0,"","_"&LOOKUP(I25,'Objets de gestion'!C:C,'Objets de gestion'!F:F)) &IF(COUNTIF('Objets de gestion'!C:C,K25)=0,"","_"&LOOKUP(K25,'Objets de gestion'!C:C,'Objets de gestion'!F:F)) &IF(OR(C25="booléen",COUNTIF('Objets de gestion'!C:C,C25)=0),"","_"&LOOKUP(C25,'Objets de gestion'!C:C,'Objets de gestion'!F:F)) )))) -> X_ATT_PTF_WRD | O25: =IF(AND(ISBLANK(A25),ISBLANK(B25),ISBLANK(C25),ISBLANK(E25),ISBLANK(L25)),"",IF(OR(ISBLANK(A25),ISBLANK(B25),ISBLANK(C25),ISBLANK(E25),ISBLANK(L25)),"-", C25&" "&IF(ISBLANK(E25),"",D25&" "&E25&" ")&IF(ISBLANK(G25),"",F25&" "&G25&" ")&IF(ISBLANK(I25),"",H25&" "&I25&" ")&IF(ISBLANK(K25),"",J25&" "&K25&" "))) -> Libellé du portefeuille de rattachement | P25: =IF(AND(ISBLANK(A25),ISBLANK(B25),ISBLANK(C25),ISBLANK(E25),ISBLANK(L25)),"",IF(OR(ISBLANK(A25),ISBLANK(B25),ISBLANK(C25),ISBLANK(E25),ISBLANK(L25)),"-", IF(ISBLANK(C25),"",LOOKUP(C25,'Objets de gestion'!C:C,'Objets de gestion'!E:E)) &IF(ISBLANK(D25),""," "&LOOKUP(D25,Articles!A:A,Articles!B:B)) &IF(ISBLANK(E25),""," "&LOOKUP(E25,'Objets de gestion'!C:C,'Objets de gestion'!E:E)) &IF(ISBLANK(F25),""," "&LOOKUP(F25,Articles!A:A,Articles!B:B)) &IF(ISBLANK(G25),""," "&LOOKUP(G25,'Objets de gestion'!C:C,'Objets de gestion'!E:E)) &IF(ISBLANK(H25),""," "&LOOKUP(H25,Articles!A:A,Articles!B:B)) &IF(ISBLANK(I25),""," "&LOOKUP(I25,'Objets de gestion'!C:C,'Objets de gestion'!E:E)) &IF(ISBLANK(J25),""," "&LOOKUP(J25,Articles!A:A,Articles!B:B)) &IF(ISBLANK(K25),""," "&LOOKUP(K25,'Objets de gestion'!C:C,'Objets de gestion'!E:E)) )) -> Wording of the portfolio of the attachment | Q25: =IF(AND(ISBLANK(A25),ISBLANK(B25),ISBLANK(C25),ISBLANK(E25),ISBLANK(L25)),"",IF(OR(ISBLANK(A25),ISBLANK(B25),ISBLANK(C25),ISBLANK(E25),ISBLANK(L25)),"-", LOOKUP(B25,'Type de champ'!B:B,'Type de champ'!C:C))) -> Varchar(??) | R25: =IF(AND(ISBLANK(A25),ISBLANK(B25),ISBLANK(E25),ISBLANK(G25),ISBLANK(L25)),"",IF(OR(ISBLANK(A25),ISBLANK(B25),ISBLANK(E25),ISBLANK(G25),ISBLANK(L25)),"-", A25)) -> tiers
A26: tiers | B26: Chaine de caractère | C26: type | D26: de | E26: rattachement | F26: du | G26: tiers | H26: au | I26: portefeuille | L26: Normal | M26: =IF(AND(ISBLANK(A26),ISBLANK(B26),ISBLANK(E26),ISBLANK(G26),ISBLANK(L26)),"",IF(OR(ISBLANK(A26),ISBLANK(B26),ISBLANK(E26),ISBLANK(G26),ISBLANK(L26)),"-",LEN(Tableau47[[#This Row],[Code]]))) -> 17 | N26: =IF(AND(ISBLANK(A26),ISBLANK(B26),ISBLANK(C26),ISBLANK(E26),ISBLANK(L26)),"",IF(OR(ISBLANK(A26),ISBLANK(B26),ISBLANK(C26),ISBLANK(E26),ISBLANK(L26)),"à compléter", IF(L26="Normal", LOOKUP(B26,'Type de champ'!B:B,'Type de champ'!A:A) &IF(COUNTIF('Objets de gestion'!C:C,K26)=0,"","_"&LOOKUP(K26,'Objets de gestion'!C:C,'Objets de gestion'!F:F)) &IF(COUNTIF('Objets de gestion'!C:C,I26)=0,"","_"&LOOKUP(I26,'Objets de gestion'!C:C,'Objets de gestion'!F:F)) &IF(COUNTIF('Objets de gestion'!C:C,G26)=0,"","_"&LOOKUP(G26,'Objets de gestion'!C:C,'Objets de gestion'!F:F)) &IF(COUNTIF('Objets de gestion'!C:C,E26)=0,"","_"&LOOKUP(E26,'Objets de gestion'!C:C,'Objets de gestion'!F:F)) &IF(OR(C26="booléen",COUNTIF('Objets de gestion'!C:C,C26)=0),"","_"&LOOKUP(C26,'Objets de gestion'!C:C,'Objets de gestion'!F:F)), IF(L26="Forcé", LOOKUP(B26,'Type de champ'!B:B,'Type de champ'!A:A) &IF(COUNTIF('Objets de gestion'!C:C,E26)=0,"","_"&LOOKUP(E26,'Objets de gestion'!C:C,'Objets de gestion'!F:F)) &IF(COUNTIF('Objets de gestion'!C:C,G26)=0,"","_"&LOOKUP(G26,'Objets de gestion'!C:C,'Objets de gestion'!F:F)) &IF(COUNTIF('Objets de gestion'!C:C,I26)=0,"","_"&LOOKUP(I26,'Objets de gestion'!C:C,'Objets de gestion'!F:F)) &IF(COUNTIF('Objets de gestion'!C:C,K26)=0,"","_"&LOOKUP(K26,'Objets de gestion'!C:C,'Objets de gestion'!F:F)) &IF(OR(C26="booléen",COUNTIF('Objets de gestion'!C:C,C26)=0),"","_"&LOOKUP(C26,'Objets de gestion'!C:C,'Objets de gestion'!F:F)) )))) -> X_PTF_TDP_ATT_TYP | O26: =IF(AND(ISBLANK(A26),ISBLANK(B26),ISBLANK(C26),ISBLANK(E26),ISBLANK(L26)),"",IF(OR(ISBLANK(A26),ISBLANK(B26),ISBLANK(C26),ISBLANK(E26),ISBLANK(L26)),"-", C26&" "&IF(ISBLANK(E26),"",D26&" "&E26&" ")&IF(ISBLANK(G26),"",F26&" "&G26&" ")&IF(ISBLANK(I26),"",H26&" "&I26&" ")&IF(ISBLANK(K26),"",J26&" "&K26&" "))) -> type de rattachement du tiers au portefeuille | P26: =IF(AND(ISBLANK(A26),ISBLANK(B26),ISBLANK(C26),ISBLANK(E26),ISBLANK(L26)),"",IF(OR(ISBLANK(A26),ISBLANK(B26),ISBLANK(C26),ISBLANK(E26),ISBLANK(L26)),"-", IF(ISBLANK(C26),"",LOOKUP(C26,'Objets de gestion'!C:C,'Objets de gestion'!E:E)) &IF(ISBLANK(D26),""," "&LOOKUP(D26,Articles!A:A,Articles!B:B)) &IF(ISBLANK(E26),""," "&LOOKUP(E26,'Objets de gestion'!C:C,'Objets de gestion'!E:E)) &IF(ISBLANK(F26),""," "&LOOKUP(F26,Articles!A:A,Articles!B:B)) &IF(ISBLANK(G26),""," "&LOOKUP(G26,'Objets de gestion'!C:C,'Objets de gestion'!E:E)) &IF(ISBLANK(H26),""," "&LOOKUP(H26,Articles!A:A,Articles!B:B)) &IF(ISBLANK(I26),""," "&LOOKUP(I26,'Objets de gestion'!C:C,'Objets de gestion'!E:E)) &IF(ISBLANK(J26),""," "&LOOKUP(J26,Articles!A:A,Articles!B:B)) &IF(ISBLANK(K26),""," "&LOOKUP(K26,'Objets de gestion'!C:C,'Objets de gestion'!E:E)) )) -> Type of the attachment of the third party to portfolio | Q26: =IF(AND(ISBLANK(A26),ISBLANK(B26),ISBLANK(C26),ISBLANK(E26),ISBLANK(L26)),"",IF(OR(ISBLANK(A26),ISBLANK(B26),ISBLANK(C26),ISBLANK(E26),ISBLANK(L26)),"-", LOOKUP(B26,'Type de champ'!B:B,'Type de champ'!C:C))) -> Varchar(??) | R26: =IF(AND(ISBLANK(A26),ISBLANK(B26),ISBLANK(E26),ISBLANK(G26),ISBLANK(L26)),"",IF(OR(ISBLANK(A26),ISBLANK(B26),ISBLANK(E26),ISBLANK(G26),ISBLANK(L26)),"-", A26)) -> tiers
A27: tiers | B27: Chaine de caractère | C27: code | D27: du | E27: type de structure | F27: de | G27: rattachement | H27: du | I27: tiers | J27: au | K27: portefeuille | L27: Normal | M27: =IF(AND(ISBLANK(A27),ISBLANK(B27),ISBLANK(E27),ISBLANK(G27),ISBLANK(L27)),"",IF(OR(ISBLANK(A27),ISBLANK(B27),ISBLANK(E27),ISBLANK(G27),ISBLANK(L27)),"-",LEN(Tableau47[[#This Row],[Code]]))) -> 24 | N27: =IF(AND(ISBLANK(A27),ISBLANK(B27),ISBLANK(C27),ISBLANK(E27),ISBLANK(L27)),"",IF(OR(ISBLANK(A27),ISBLANK(B27),ISBLANK(C27),ISBLANK(E27),ISBLANK(L27)),"à compléter", IF(L27="Normal", LOOKUP(B27,'Type de champ'!B:B,'Type de champ'!A:A) &IF(COUNTIF('Objets de gestion'!C:C,K27)=0,"","_"&LOOKUP(K27,'Objets de gestion'!C:C,'Objets de gestion'!F:F)) &IF(COUNTIF('Objets de gestion'!C:C,I27)=0,"","_"&LOOKUP(I27,'Objets de gestion'!C:C,'Objets de gestion'!F:F)) &IF(COUNTIF('Objets de gestion'!C:C,G27)=0,"","_"&LOOKUP(G27,'Objets de gestion'!C:C,'Objets de gestion'!F:F)) &IF(COUNTIF('Objets de gestion'!C:C,E27)=0,"","_"&LOOKUP(E27,'Objets de gestion'!C:C,'Objets de gestion'!F:F)) &IF(OR(C27="booléen",COUNTIF('Objets de gestion'!C:C,C27)=0),"","_"&LOOKUP(C27,'Objets de gestion'!C:C,'Objets de gestion'!F:F)), IF(L27="Forcé", LOOKUP(B27,'Type de champ'!B:B,'Type de champ'!A:A) &IF(COUNTIF('Objets de gestion'!C:C,E27)=0,"","_"&LOOKUP(E27,'Objets de gestion'!C:C,'Objets de gestion'!F:F)) &IF(COUNTIF('Objets de gestion'!C:C,G27)=0,"","_"&LOOKUP(G27,'Objets de gestion'!C:C,'Objets de gestion'!F:F)) &IF(COUNTIF('Objets de gestion'!C:C,I27)=0,"","_"&LOOKUP(I27,'Objets de gestion'!C:C,'Objets de gestion'!F:F)) &IF(COUNTIF('Objets de gestion'!C:C,K27)=0,"","_"&LOOKUP(K27,'Objets de gestion'!C:C,'Objets de gestion'!F:F)) &IF(OR(C27="booléen",COUNTIF('Objets de gestion'!C:C,C27)=0),"","_"&LOOKUP(C27,'Objets de gestion'!C:C,'Objets de gestion'!F:F)) )))) -> X_PTF_TDP_ATT_STRTYP_COD | O27: =IF(AND(ISBLANK(A27),ISBLANK(B27),ISBLANK(C27),ISBLANK(E27),ISBLANK(L27)),"",IF(OR(ISBLANK(A27),ISBLANK(B27),ISBLANK(C27),ISBLANK(E27),ISBLANK(L27)),"-", C27&" "&IF(ISBLANK(E27),"",D27&" "&E27&" ")&IF(ISBLANK(G27),"",F27&" "&G27&" ")&IF(ISBLANK(I27),"",H27&" "&I27&" ")&IF(ISBLANK(K27),"",J27&" "&K27&" "))) -> code du type de structure de rattachement du tiers au portefeuille | P27: =IF(AND(ISBLANK(A27),ISBLANK(B27),ISBLANK(C27),ISBLANK(E27),ISBLANK(L27)),"",IF(OR(ISBLANK(A27),ISBLANK(B27),ISBLANK(C27),ISBLANK(E27),ISBLANK(L27)),"-", IF(ISBLANK(C27),"",LOOKUP(C27,'Objets de gestion'!C:C,'Objets de gestion'!E:E)) &IF(ISBLANK(D27),""," "&LOOKUP(D27,Articles!A:A,Articles!B:B)) &IF(ISBLANK(E27),""," "&LOOKUP(E27,'Objets de gestion'!C:C,'Objets de gestion'!E:E)) &IF(ISBLANK(F27),""," "&LOOKUP(F27,Articles!A:A,Articles!B:B)) &IF(ISBLANK(G27),""," "&LOOKUP(G27,'Objets de gestion'!C:C,'Objets de gestion'!E:E)) &IF(ISBLANK(H27),""," "&LOOKUP(H27,Articles!A:A,Articles!B:B)) &IF(ISBLANK(I27),""," "&LOOKUP(I27,'Objets de gestion'!C:C,'Objets de gestion'!E:E)) &IF(ISBLANK(J27),""," "&LOOKUP(J27,Articles!A:A,Articles!B:B)) &IF(ISBLANK(K27),""," "&LOOKUP(K27,'Objets de gestion'!C:C,'Objets de gestion'!E:E)) )) -> code of the structure type of the attachment of the third party to portfolio | Q27: =IF(AND(ISBLANK(A27),ISBLANK(B27),ISBLANK(C27),ISBLANK(E27),ISBLANK(L27)),"",IF(OR(ISBLANK(A27),ISBLANK(B27),ISBLANK(C27),ISBLANK(E27),ISBLANK(L27)),"-", LOOKUP(B27,'Type de champ'!B:B,'Type de champ'!C:C))) -> Varchar(??) | R27: =IF(AND(ISBLANK(A27),ISBLANK(B27),ISBLANK(E27),ISBLANK(G27),ISBLANK(L27)),"",IF(OR(ISBLANK(A27),ISBLANK(B27),ISBLANK(E27),ISBLANK(G27),ISBLANK(L27)),"-", A27)) -> tiers
A28: tiers | B28: Date, Heure, Timestamp | C28: Date de fin de l'identifiant unique | D28: du | E28: Lien | F28: entre | G28: tiers | H28: et | I28: chargé de clientèle | L28: Normal | M28: =IF(AND(ISBLANK(A28),ISBLANK(B28),ISBLANK(E28),ISBLANK(G28),ISBLANK(L28)),"",IF(OR(ISBLANK(A28),ISBLANK(B28),ISBLANK(E28),ISBLANK(G28),ISBLANK(L28)),"-",LEN(Tableau47[[#This Row],[Code]]))) -> 23 | N28: =IF(AND(ISBLANK(A28),ISBLANK(B28),ISBLANK(C28),ISBLANK(E28),ISBLANK(L28)),"",IF(OR(ISBLANK(A28),ISBLANK(B28),ISBLANK(C28),ISBLANK(E28),ISBLANK(L28)),"à compléter", IF(L28="Normal", LOOKUP(B28,'Type de champ'!B:B,'Type de champ'!A:A) &IF(COUNTIF('Objets de gestion'!C:C,K28)=0,"","_"&LOOKUP(K28,'Objets de gestion'!C:C,'Objets de gestion'!F:F)) &IF(COUNTIF('Objets de gestion'!C:C,I28)=0,"","_"&LOOKUP(I28,'Objets de gestion'!C:C,'Objets de gestion'!F:F)) &IF(COUNTIF('Objets de gestion'!C:C,G28)=0,"","_"&LOOKUP(G28,'Objets de gestion'!C:C,'Objets de gestion'!F:F)) &IF(COUNTIF('Objets de gestion'!C:C,E28)=0,"","_"&LOOKUP(E28,'Objets de gestion'!C:C,'Objets de gestion'!F:F)) &IF(OR(C28="booléen",COUNTIF('Objets de gestion'!C:C,C28)=0),"","_"&LOOKUP(C28,'Objets de gestion'!C:C,'Objets de gestion'!F:F)), IF(L28="Forcé", LOOKUP(B28,'Type de champ'!B:B,'Type de champ'!A:A) &IF(COUNTIF('Objets de gestion'!C:C,E28)=0,"","_"&LOOKUP(E28,'Objets de gestion'!C:C,'Objets de gestion'!F:F)) &IF(COUNTIF('Objets de gestion'!C:C,G28)=0,"","_"&LOOKUP(G28,'Objets de gestion'!C:C,'Objets de gestion'!F:F)) &IF(COUNTIF('Objets de gestion'!C:C,I28)=0,"","_"&LOOKUP(I28,'Objets de gestion'!C:C,'Objets de gestion'!F:F)) &IF(COUNTIF('Objets de gestion'!C:C,K28)=0,"","_"&LOOKUP(K28,'Objets de gestion'!C:C,'Objets de gestion'!F:F)) &IF(OR(C28="booléen",COUNTIF('Objets de gestion'!C:C,C28)=0),"","_"&LOOKUP(C28,'Objets de gestion'!C:C,'Objets de gestion'!F:F)) )))) -> T_ACCMGR_TDP_LNK_EDAUID | O28: =IF(AND(ISBLANK(A28),ISBLANK(B28),ISBLANK(C28),ISBLANK(E28),ISBLANK(L28)),"",IF(OR(ISBLANK(A28),ISBLANK(B28),ISBLANK(C28),ISBLANK(E28),ISBLANK(L28)),"-", C28&" "&IF(ISBLANK(E28),"",D28&" "&E28&" ")&IF(ISBLANK(G28),"",F28&" "&G28&" ")&IF(ISBLANK(I28),"",H28&" "&I28&" ")&IF(ISBLANK(K28),"",J28&" "&K28&" "))) -> Date de fin de l'identifiant unique du Lien entre tiers et chargé de clientèle | P28: =IF(AND(ISBLANK(A28),ISBLANK(B28),ISBLANK(C28),ISBLANK(E28),ISBLANK(L28)),"",IF(OR(ISBLANK(A28),ISBLANK(B28),ISBLANK(C28),ISBLANK(E28),ISBLANK(L28)),"-", IF(ISBLANK(C28),"",LOOKUP(C28,'Objets de gestion'!C:C,'Objets de gestion'!E:E)) &IF(ISBLANK(D28),""," "&LOOKUP(D28,Articles!A:A,Articles!B:B)) &IF(ISBLANK(E28),""," "&LOOKUP(E28,'Objets de gestion'!C:C,'Objets de gestion'!E:E)) &IF(ISBLANK(F28),""," "&LOOKUP(F28,Articles!A:A,Articles!B:B)) &IF(ISBLANK(G28),""," "&LOOKUP(G28,'Objets de gestion'!C:C,'Objets de gestion'!E:E)) &IF(ISBLANK(H28),""," "&LOOKUP(H28,Articles!A:A,Articles!B:B)) &IF(ISBLANK(I28),""," "&LOOKUP(I28,'Objets de gestion'!C:C,'Objets de gestion'!E:E)) &IF(ISBLANK(J28),""," "&LOOKUP(J28,Articles!A:A,Articles!B:B)) &IF(ISBLANK(K28),""," "&LOOKUP(K28,'Objets de gestion'!C:C,'Objets de gestion'!E:E)) )) -> End date of UID of the Link between third party and Account Manager | Q28: =IF(AND(ISBLANK(A28),ISBLANK(B28),ISBLANK(C28),ISBLANK(E28),ISBLANK(L28)),"",IF(OR(ISBLANK(A28),ISBLANK(B28),ISBLANK(C28),ISBLANK(E28),ISBLANK(L28)),"-", LOOKUP(B28,'Type de champ'!B:B,'Type de champ'!C:C))) -> Date | R28: =IF(AND(ISBLANK(A28),ISBLANK(B28),ISBLANK(E28),ISBLANK(G28),ISBLANK(L28)),"",IF(OR(ISBLANK(A28),ISBLANK(B28),ISBLANK(E28),ISBLANK(G28),ISBLANK(L28)),"-", A28)) -> tiers
M29: =IF(AND(ISBLANK(A29),ISBLANK(B29),ISBLANK(E29),ISBLANK(G29),ISBLANK(L29)),"",IF(OR(ISBLANK(A29),ISBLANK(B29),ISBLANK(E29),ISBLANK(G29),ISBLANK(L29)),"-",LEN(Tableau47[[#This Row],[Code]]))) | N29: =IF(AND(ISBLANK(A29),ISBLANK(B29),ISBLANK(C29),ISBLANK(E29),ISBLANK(L29)),"",IF(OR(ISBLANK(A29),ISBLANK(B29),ISBLANK(C29),ISBLANK(E29),ISBLANK(L29)),"à compléter", IF(L29="Normal", LOOKUP(B29,'Type de champ'!B:B,'Type de champ'!A:A) &IF(COUNTIF('Objets de gestion'!C:C,K29)=0,"","_"&LOOKUP(K29,'Objets de gestion'!C:C,'Objets de gestion'!F:F)) &IF(COUNTIF('Objets de gestion'!C:C,I29)=0,"","_"&LOOKUP(I29,'Objets de gestion'!C:C,'Objets de gestion'!F:F)) &IF(COUNTIF('Objets de gestion'!C:C,G29)=0,"","_"&LOOKUP(G29,'Objets de gestion'!C:C,'Objets de gestion'!F:F)) &IF(COUNTIF('Objets de gestion'!C:C,E29)=0,"","_"&LOOKUP(E29,'Objets de gestion'!C:C,'Objets de gestion'!F:F)) &IF(OR(C29="booléen",COUNTIF('Objets de gestion'!C:C,C29)=0),"","_"&LOOKUP(C29,'Objets de gestion'!C:C,'Objets de gestion'!F:F)), IF(L29="Forcé", LOOKUP(B29,'Type de champ'!B:B,'Type de champ'!A:A) &IF(COUNTIF('Objets de gestion'!C:C,E29)=0,"","_"&LOOKUP(E29,'Objets de gestion'!C:C,'Objets de gestion'!F:F)) &IF(COUNTIF('Objets de gestion'!C:C,G29)=0,"","_"&LOOKUP(G29,'Objets de gestion'!C:C,'Objets de gestion'!F:F)) &IF(COUNTIF('Objets de gestion'!C:C,I29)=0,"","_"&LOOKUP(I29,'Objets de gestion'!C:C,'Objets de gestion'!F:F)) &IF(COUNTIF('Objets de gestion'!C:C,K29)=0,"","_"&LOOKUP(K29,'Objets de gestion'!C:C,'Objets de gestion'!F:F)) &IF(OR(C29="booléen",COUNTIF('Objets de gestion'!C:C,C29)=0),"","_"&LOOKUP(C29,'Objets de gestion'!C:C,'Objets de gestion'!F:F)) )))) | O29: =IF(AND(ISBLANK(A29),ISBLANK(B29),ISBLANK(C29),ISBLANK(E29),ISBLANK(L29)),"",IF(OR(ISBLANK(A29),ISBLANK(B29),ISBLANK(C29),ISBLANK(E29),ISBLANK(L29)),"-", C29&" "&IF(ISBLANK(E29),"",D29&" "&E29&" ")&IF(ISBLANK(G29),"",F29&" "&G29&" ")&IF(ISBLANK(I29),"",H29&" "&I29&" ")&IF(ISBLANK(K29),"",J29&" "&K29&" "))) | P29: =IF(AND(ISBLANK(A29),ISBLANK(B29),ISBLANK(C29),ISBLANK(E29),ISBLANK(L29)),"",IF(OR(ISBLANK(A29),ISBLANK(B29),ISBLANK(C29),ISBLANK(E29),ISBLANK(L29)),"-", IF(ISBLANK(C29),"",LOOKUP(C29,'Objets de gestion'!C:C,'Objets de gestion'!E:E)) &IF(ISBLANK(D29),""," "&LOOKUP(D29,Articles!A:A,Articles!B:B)) &IF(ISBLANK(E29),""," "&LOOKUP(E29,'Objets de gestion'!C:C,'Objets de gestion'!E:E)) &IF(ISBLANK(F29),""," "&LOOKUP(F29,Articles!A:A,Articles!B:B)) &IF(ISBLANK(G29),""," "&LOOKUP(G29,'Objets de gestion'!C:C,'Objets de gestion'!E:E)) &IF(ISBLANK(H29),""," "&LOOKUP(H29,Articles!A:A,Articles!B:B)) &IF(ISBLANK(I29),""," "&LOOKUP(I29,'Objets de gestion'!C:C,'Objets de gestion'!E:E)) &IF(ISBLANK(J29),""," "&LOOKUP(J29,Articles!A:A,Articles!B:B)) &IF(ISBLANK(K29),""," "&LOOKUP(K29,'Objets de gestion'!C:C,'Objets de gestion'!E:E)) )) | Q29: =IF(AND(ISBLANK(A29),ISBLANK(B29),ISBLANK(C29),ISBLANK(E29),ISBLANK(L29)),"",IF(OR(ISBLANK(A29),ISBLANK(B29),ISBLANK(C29),ISBLANK(E29),ISBLANK(L29)),"-", LOOKUP(B29,'Type de champ'!B:B,'Type de champ'!C:C))) | R29: =IF(AND(ISBLANK(A29),ISBLANK(B29),ISBLANK(E29),ISBLANK(G29),ISBLANK(L29)),"",IF(OR(ISBLANK(A29),ISBLANK(B29),ISBLANK(E29),ISBLANK(G29),ISBLANK(L29)),"-", A29))
A30: tiers | B30: Date, Heure, Timestamp | C30: date de rattachement | D30: du | E30: tiers | F30: au | G30: portefeuille | L30: Normal | M30: =IF(AND(ISBLANK(A30),ISBLANK(B30),ISBLANK(E30),ISBLANK(G30),ISBLANK(L30)),"",IF(OR(ISBLANK(A30),ISBLANK(B30),ISBLANK(E30),ISBLANK(G30),ISBLANK(L30)),"-",LEN(Tableau47[[#This Row],[Code]]))) -> 16 | N30: =IF(AND(ISBLANK(A30),ISBLANK(B30),ISBLANK(C30),ISBLANK(E30),ISBLANK(L30)),"",IF(OR(ISBLANK(A30),ISBLANK(B30),ISBLANK(C30),ISBLANK(E30),ISBLANK(L30)),"à compléter", IF(L30="Normal", LOOKUP(B30,'Type de champ'!B:B,'Type de champ'!A:A) &IF(COUNTIF('Objets de gestion'!C:C,K30)=0,"","_"&LOOKUP(K30,'Objets de gestion'!C:C,'Objets de gestion'!F:F)) &IF(COUNTIF('Objets de gestion'!C:C,I30)=0,"","_"&LOOKUP(I30,'Objets de gestion'!C:C,'Objets de gestion'!F:F)) &IF(COUNTIF('Objets de gestion'!C:C,G30)=0,"","_"&LOOKUP(G30,'Objets de gestion'!C:C,'Objets de gestion'!F:F)) &IF(COUNTIF('Objets de gestion'!C:C,E30)=0,"","_"&LOOKUP(E30,'Objets de gestion'!C:C,'Objets de gestion'!F:F)) &IF(OR(C30="booléen",COUNTIF('Objets de gestion'!C:C,C30)=0),"","_"&LOOKUP(C30,'Objets de gestion'!C:C,'Objets de gestion'!F:F)), IF(L30="Forcé", LOOKUP(B30,'Type de champ'!B:B,'Type de champ'!A:A) &IF(COUNTIF('Objets de gestion'!C:C,E30)=0,"","_"&LOOKUP(E30,'Objets de gestion'!C:C,'Objets de gestion'!F:F)) &IF(COUNTIF('Objets de gestion'!C:C,G30)=0,"","_"&LOOKUP(G30,'Objets de gestion'!C:C,'Objets de gestion'!F:F)) &IF(COUNTIF('Objets de gestion'!C:C,I30)=0,"","_"&LOOKUP(I30,'Objets de gestion'!C:C,'Objets de gestion'!F:F)) &IF(COUNTIF('Objets de gestion'!C:C,K30)=0,"","_"&LOOKUP(K30,'Objets de gestion'!C:C,'Objets de gestion'!F:F)) &IF(OR(C30="booléen",COUNTIF('Objets de gestion'!C:C,C30)=0),"","_"&LOOKUP(C30,'Objets de gestion'!C:C,'Objets de gestion'!F:F)) )))) -> T_PTF_TDP_ATTDAT | O30: =IF(AND(ISBLANK(A30),ISBLANK(B30),ISBLANK(C30),ISBLANK(E30),ISBLANK(L30)),"",IF(OR(ISBLANK(A30),ISBLANK(B30),ISBLANK(C30),ISBLANK(E30),ISBLANK(L30)),"-", C30&" "&IF(ISBLANK(E30),"",D30&" "&E30&" ")&IF(ISBLANK(G30),"",F30&" "&G30&" ")&IF(ISBLANK(I30),"",H30&" "&I30&" ")&IF(ISBLANK(K30),"",J30&" "&K30&" "))) -> date de rattachement du tiers au portefeuille | P30: =IF(AND(ISBLANK(A30),ISBLANK(B30),ISBLANK(C30),ISBLANK(E30),ISBLANK(L30)),"",IF(OR(ISBLANK(A30),ISBLANK(B30),ISBLANK(C30),ISBLANK(E30),ISBLANK(L30)),"-", IF(ISBLANK(C30),"",LOOKUP(C30,'Objets de gestion'!C:C,'Objets de gestion'!E:E)) &IF(ISBLANK(D30),""," "&LOOKUP(D30,Articles!A:A,Articles!B:B)) &IF(ISBLANK(E30),""," "&LOOKUP(E30,'Objets de gestion'!C:C,'Objets de gestion'!E:E)) &IF(ISBLANK(F30),""," "&LOOKUP(F30,Articles!A:A,Articles!B:B)) &IF(ISBLANK(G30),""," "&LOOKUP(G30,'Objets de gestion'!C:C,'Objets de gestion'!E:E)) &IF(ISBLANK(H30),""," "&LOOKUP(H30,Articles!A:A,Articles!B:B)) &IF(ISBLANK(I30),""," "&LOOKUP(I30,'Objets de gestion'!C:C,'Objets de gestion'!E:E)) &IF(ISBLANK(J30),""," "&LOOKUP(J30,Articles!A:A,Articles!B:B)) &IF(ISBLANK(K30),""," "&LOOKUP(K30,'Objets de gestion'!C:C,'Objets de gestion'!E:E)) )) -> attachment date of the third party to portfolio | Q30: =IF(AND(ISBLANK(A30),ISBLANK(B30),ISBLANK(C30),ISBLANK(E30),ISBLANK(L30)),"",IF(OR(ISBLANK(A30),ISBLANK(B30),ISBLANK(C30),ISBLANK(E30),ISBLANK(L30)),"-", LOOKUP(B30,'Type de champ'!B:B,'Type de champ'!C:C))) -> Date | R30: =IF(AND(ISBLANK(A30),ISBLANK(B30),ISBLANK(E30),ISBLANK(G30),ISBLANK(L30)),"",IF(OR(ISBLANK(A30),ISBLANK(B30),ISBLANK(E30),ISBLANK(G30),ISBLANK(L30)),"-", A30)) -> tiers
A31: tiers | B31: Booléen | C31: Booléen | D31: de | E31: dernière image | F31: du | G31: Lien | H31: entre | I31: tiers | J31: et | K31: chargé de clientèle | L31: Normal | M31: =IF(AND(ISBLANK(A31),ISBLANK(B31),ISBLANK(E31),ISBLANK(G31),ISBLANK(L31)),"",IF(OR(ISBLANK(A31),ISBLANK(B31),ISBLANK(E31),ISBLANK(G31),ISBLANK(L31)),"-",LEN(Tableau47[[#This Row],[Code]]))) -> 20 | N31: =IF(AND(ISBLANK(A31),ISBLANK(B31),ISBLANK(C31),ISBLANK(E31),ISBLANK(L31)),"",IF(OR(ISBLANK(A31),ISBLANK(B31),ISBLANK(C31),ISBLANK(E31),ISBLANK(L31)),"à compléter", IF(L31="Normal", LOOKUP(B31,'Type de champ'!B:B,'Type de champ'!A:A) &IF(COUNTIF('Objets de gestion'!C:C,K31)=0,"","_"&LOOKUP(K31,'Objets de gestion'!C:C,'Objets de gestion'!F:F)) &IF(COUNTIF('Objets de gestion'!C:C,I31)=0,"","_"&LOOKUP(I31,'Objets de gestion'!C:C,'Objets de gestion'!F:F)) &IF(COUNTIF('Objets de gestion'!C:C,G31)=0,"","_"&LOOKUP(G31,'Objets de gestion'!C:C,'Objets de gestion'!F:F)) &IF(COUNTIF('Objets de gestion'!C:C,E31)=0,"","_"&LOOKUP(E31,'Objets de gestion'!C:C,'Objets de gestion'!F:F)) &IF(OR(C31="booléen",COUNTIF('Objets de gestion'!C:C,C31)=0),"","_"&LOOKUP(C31,'Objets de gestion'!C:C,'Objets de gestion'!F:F)), IF(L31="Forcé", LOOKUP(B31,'Type de champ'!B:B,'Type de champ'!A:A) &IF(COUNTIF('Objets de gestion'!C:C,E31)=0,"","_"&LOOKUP(E31,'Objets de gestion'!C:C,'Objets de gestion'!F:F)) &IF(COUNTIF('Objets de gestion'!C:C,G31)=0,"","_"&LOOKUP(G31,'Objets de gestion'!C:C,'Objets de gestion'!F:F)) &IF(COUNTIF('Objets de gestion'!C:C,I31)=0,"","_"&LOOKUP(I31,'Objets de gestion'!C:C,'Objets de gestion'!F:F)) &IF(COUNTIF('Objets de gestion'!C:C,K31)=0,"","_"&LOOKUP(K31,'Objets de gestion'!C:C,'Objets de gestion'!F:F)) &IF(OR(C31="booléen",COUNTIF('Objets de gestion'!C:C,C31)=0),"","_"&LOOKUP(C31,'Objets de gestion'!C:C,'Objets de gestion'!F:F)) )))) -> B_ACCMGR_TDP_LNK_LTI | O31: =IF(AND(ISBLANK(A31),ISBLANK(B31),ISBLANK(C31),ISBLANK(E31),ISBLANK(L31)),"",IF(OR(ISBLANK(A31),ISBLANK(B31),ISBLANK(C31),ISBLANK(E31),ISBLANK(L31)),"-", C31&" "&IF(ISBLANK(E31),"",D31&" "&E31&" ")&IF(ISBLANK(G31),"",F31&" "&G31&" ")&IF(ISBLANK(I31),"",H31&" "&I31&" ")&IF(ISBLANK(K31),"",J31&" "&K31&" "))) -> Booléen de dernière image du Lien entre tiers et chargé de clientèle | P31: =IF(AND(ISBLANK(A31),ISBLANK(B31),ISBLANK(C31),ISBLANK(E31),ISBLANK(L31)),"",IF(OR(ISBLANK(A31),ISBLANK(B31),ISBLANK(C31),ISBLANK(E31),ISBLANK(L31)),"-", IF(ISBLANK(C31),"",LOOKUP(C31,'Objets de gestion'!C:C,'Objets de gestion'!E:E)) &IF(ISBLANK(D31),""," "&LOOKUP(D31,Articles!A:A,Articles!B:B)) &IF(ISBLANK(E31),""," "&LOOKUP(E31,'Objets de gestion'!C:C,'Objets de gestion'!E:E)) &IF(ISBLANK(F31),""," "&LOOKUP(F31,Articles!A:A,Articles!B:B)) &IF(ISBLANK(G31),""," "&LOOKUP(G31,'Objets de gestion'!C:C,'Objets de gestion'!E:E)) &IF(ISBLANK(H31),""," "&LOOKUP(H31,Articles!A:A,Articles!B:B)) &IF(ISBLANK(I31),""," "&LOOKUP(I31,'Objets de gestion'!C:C,'Objets de gestion'!E:E)) &IF(ISBLANK(J31),""," "&LOOKUP(J31,Articles!A:A,Articles!B:B)) &IF(ISBLANK(K31),""," "&LOOKUP(K31,'Objets de gestion'!C:C,'Objets de gestion'!E:E)) )) -> boolean of the last image of the Link between third party and Account Manager | Q31: =IF(AND(ISBLANK(A31),ISBLANK(B31),ISBLANK(C31),ISBLANK(E31),ISBLANK(L31)),"",IF(OR(ISBLANK(A31),ISBLANK(B31),ISBLANK(C31),ISBLANK(E31),ISBLANK(L31)),"-", LOOKUP(B31,'Type de champ'!B:B,'Type de champ'!C:C))) -> Boolean | R31: =IF(AND(ISBLANK(A31),ISBLANK(B31),ISBLANK(E31),ISBLANK(G31),ISBLANK(L31)),"",IF(OR(ISBLANK(A31),ISBLANK(B31),ISBLANK(E31),ISBLANK(G31),ISBLANK(L31)),"-", A31)) -> tiers
A32: tiers | B32: Date, Heure, Timestamp | C32: Date de début de l'identifiant unique | D32: du | E32: Lien | F32: entre | G32: tiers | H32: et | I32: chargé de clientèle | L32: Normal | M32: =IF(AND(ISBLANK(A32),ISBLANK(B32),ISBLANK(E32),ISBLANK(G32),ISBLANK(L32)),"",IF(OR(ISBLANK(A32),ISBLANK(B32),ISBLANK(E32),ISBLANK(G32),ISBLANK(L32)),"-",LEN(Tableau47[[#This Row],[Code]]))) -> 23 | N32: =IF(AND(ISBLANK(A32),ISBLANK(B32),ISBLANK(C32),ISBLANK(E32),ISBLANK(L32)),"",IF(OR(ISBLANK(A32),ISBLANK(B32),ISBLANK(C32),ISBLANK(E32),ISBLANK(L32)),"à compléter", IF(L32="Normal", LOOKUP(B32,'Type de champ'!B:B,'Type de champ'!A:A) &IF(COUNTIF('Objets de gestion'!C:C,K32)=0,"","_"&LOOKUP(K32,'Objets de gestion'!C:C,'Objets de gestion'!F:F)) &IF(COUNTIF('Objets de gestion'!C:C,I32)=0,"","_"&LOOKUP(I32,'Objets de gestion'!C:C,'Objets de gestion'!F:F)) &IF(COUNTIF('Objets de gestion'!C:C,G32)=0,"","_"&LOOKUP(G32,'Objets de gestion'!C:C,'Objets de gestion'!F:F)) &IF(COUNTIF('Objets de gestion'!C:C,E32)=0,"","_"&LOOKUP(E32,'Objets de gestion'!C:C,'Objets de gestion'!F:F)) &IF(OR(C32="booléen",COUNTIF('Objets de gestion'!C:C,C32)=0),"","_"&LOOKUP(C32,'Objets de gestion'!C:C,'Objets de gestion'!F:F)), IF(L32="Forcé", LOOKUP(B32,'Type de champ'!B:B,'Type de champ'!A:A) &IF(COUNTIF('Objets de gestion'!C:C,E32)=0,"","_"&LOOKUP(E32,'Objets de gestion'!C:C,'Objets de gestion'!F:F)) &IF(COUNTIF('Objets de gestion'!C:C,G32)=0,"","_"&LOOKUP(G32,'Objets de gestion'!C:C,'Objets de gestion'!F:F)) &IF(COUNTIF('Objets de gestion'!C:C,I32)=0,"","_"&LOOKUP(I32,'Objets de gestion'!C:C,'Objets de gestion'!F:F)) &IF(COUNTIF('Objets de gestion'!C:C,K32)=0,"","_"&LOOKUP(K32,'Objets de gestion'!C:C,'Objets de gestion'!F:F)) &IF(OR(C32="booléen",COUNTIF('Objets de gestion'!C:C,C32)=0),"","_"&LOOKUP(C32,'Objets de gestion'!C:C,'Objets de gestion'!F:F)) )))) -> T_ACCMGR_TDP_LNK_SDAUID | O32: =IF(AND(ISBLANK(A32),ISBLANK(B32),ISBLANK(C32),ISBLANK(E32),ISBLANK(L32)),"",IF(OR(ISBLANK(A32),ISBLANK(B32),ISBLANK(C32),ISBLANK(E32),ISBLANK(L32)),"-", C32&" "&IF(ISBLANK(E32),"",D32&" "&E32&" ")&IF(ISBLANK(G32),"",F32&" "&G32&" ")&IF(ISBLANK(I32),"",H32&" "&I32&" ")&IF(ISBLANK(K32),"",J32&" "&K32&" "))) -> Date de début de l'identifiant unique du Lien entre tiers et chargé de clientèle | P32: =IF(AND(ISBLANK(A32),ISBLANK(B32),ISBLANK(C32),ISBLANK(E32),ISBLANK(L32)),"",IF(OR(ISBLANK(A32),ISBLANK(B32),ISBLANK(C32),ISBLANK(E32),ISBLANK(L32)),"-", IF(ISBLANK(C32),"",LOOKUP(C32,'Objets de gestion'!C:C,'Objets de gestion'!E:E)) &IF(ISBLANK(D32),""," "&LOOKUP(D32,Articles!A:A,Articles!B:B)) &IF(ISBLANK(E32),""," "&LOOKUP(E32,'Objets de gestion'!C:C,'Objets de gestion'!E:E)) &IF(ISBLANK(F32),""," "&LOOKUP(F32,Articles!A:A,Articles!B:B)) &IF(ISBLANK(G32),""," "&LOOKUP(G32,'Objets de gestion'!C:C,'Objets de gestion'!E:E)) &IF(ISBLANK(H32),""," "&LOOKUP(H32,Articles!A:A,Articles!B:B)) &IF(ISBLANK(I32),""," "&LOOKUP(I32,'Objets de gestion'!C:C,'Objets de gestion'!E:E)) &IF(ISBLANK(J32),""," "&LOOKUP(J32,Articles!A:A,Articles!B:B)) &IF(ISBLANK(K32),""," "&LOOKUP(K32,'Objets de gestion'!C:C,'Objets de gestion'!E:E)) )) -> Start date of UID of the Link between third party and Account Manager | Q32: =IF(AND(ISBLANK(A32),ISBLANK(B32),ISBLANK(C32),ISBLANK(E32),ISBLANK(L32)),"",IF(OR(ISBLANK(A32),ISBLANK(B32),ISBLANK(C32),ISBLANK(E32),ISBLANK(L32)),"-", LOOKUP(B32,'Type de champ'!B:B,'Type de champ'!C:C))) -> Date | R32: =IF(AND(ISBLANK(A32),ISBLANK(B32),ISBLANK(E32),ISBLANK(G32),ISBLANK(L32)),"",IF(OR(ISBLANK(A32),ISBLANK(B32),ISBLANK(E32),ISBLANK(G32),ISBLANK(L32)),"-", A32)) -> tiers
A33: tiers | B33: Clé | C33: Identifiant unique | D33: du | E33: Lien | F33: entre | G33: tiers | H33: et | I33: chargé de clientèle | L33: Normal | M33: =IF(AND(ISBLANK(A33),ISBLANK(B33),ISBLANK(E33),ISBLANK(G33),ISBLANK(L33)),"",IF(OR(ISBLANK(A33),ISBLANK(B33),ISBLANK(E33),ISBLANK(G33),ISBLANK(L33)),"-",LEN(Tableau47[[#This Row],[Code]]))) -> 20 | N33: =IF(AND(ISBLANK(A33),ISBLANK(B33),ISBLANK(C33),ISBLANK(E33),ISBLANK(L33)),"",IF(OR(ISBLANK(A33),ISBLANK(B33),ISBLANK(C33),ISBLANK(E33),ISBLANK(L33)),"à compléter", IF(L33="Normal", LOOKUP(B33,'Type de champ'!B:B,'Type de champ'!A:A) &IF(COUNTIF('Objets de gestion'!C:C,K33)=0,"","_"&LOOKUP(K33,'Objets de gestion'!C:C,'Objets de gestion'!F:F)) &IF(COUNTIF('Objets de gestion'!C:C,I33)=0,"","_"&LOOKUP(I33,'Objets de gestion'!C:C,'Objets de gestion'!F:F)) &IF(COUNTIF('Objets de gestion'!C:C,G33)=0,"","_"&LOOKUP(G33,'Objets de gestion'!C:C,'Objets de gestion'!F:F)) &IF(COUNTIF('Objets de gestion'!C:C,E33)=0,"","_"&LOOKUP(E33,'Objets de gestion'!C:C,'Objets de gestion'!F:F)) &IF(OR(C33="booléen",COUNTIF('Objets de gestion'!C:C,C33)=0),"","_"&LOOKUP(C33,'Objets de gestion'!C:C,'Objets de gestion'!F:F)), IF(L33="Forcé", LOOKUP(B33,'Type de champ'!B:B,'Type de champ'!A:A) &IF(COUNTIF('Objets de gestion'!C:C,E33)=0,"","_"&LOOKUP(E33,'Objets de gestion'!C:C,'Objets de gestion'!F:F)) &IF(COUNTIF('Objets de gestion'!C:C,G33)=0,"","_"&LOOKUP(G33,'Objets de gestion'!C:C,'Objets de gestion'!F:F)) &IF(COUNTIF('Objets de gestion'!C:C,I33)=0,"","_"&LOOKUP(I33,'Objets de gestion'!C:C,'Objets de gestion'!F:F)) &IF(COUNTIF('Objets de gestion'!C:C,K33)=0,"","_"&LOOKUP(K33,'Objets de gestion'!C:C,'Objets de gestion'!F:F)) &IF(OR(C33="booléen",COUNTIF('Objets de gestion'!C:C,C33)=0),"","_"&LOOKUP(C33,'Objets de gestion'!C:C,'Objets de gestion'!F:F)) )))) -> K_ACCMGR_TDP_LNK_UID | O33: =IF(AND(ISBLANK(A33),ISBLANK(B33),ISBLANK(C33),ISBLANK(E33),ISBLANK(L33)),"",IF(OR(ISBLANK(A33),ISBLANK(B33),ISBLANK(C33),ISBLANK(E33),ISBLANK(L33)),"-", C33&" "&IF(ISBLANK(E33),"",D33&" "&E33&" ")&IF(ISBLANK(G33),"",F33&" "&G33&" ")&IF(ISBLANK(I33),"",H33&" "&I33&" ")&IF(ISBLANK(K33),"",J33&" "&K33&" "))) -> Identifiant unique du Lien entre tiers et chargé de clientèle | P33: =IF(AND(ISBLANK(A33),ISBLANK(B33),ISBLANK(C33),ISBLANK(E33),ISBLANK(L33)),"",IF(OR(ISBLANK(A33),ISBLANK(B33),ISBLANK(C33),ISBLANK(E33),ISBLANK(L33)),"-", IF(ISBLANK(C33),"",LOOKUP(C33,'Objets de gestion'!C:C,'Objets de gestion'!E:E)) &IF(ISBLANK(D33),""," "&LOOKUP(D33,Articles!A:A,Articles!B:B)) &IF(ISBLANK(E33),""," "&LOOKUP(E33,'Objets de gestion'!C:C,'Objets de gestion'!E:E)) &IF(ISBLANK(F33),""," "&LOOKUP(F33,Articles!A:A,Articles!B:B)) &IF(ISBLANK(G33),""," "&LOOKUP(G33,'Objets de gestion'!C:C,'Objets de gestion'!E:E)) &IF(ISBLANK(H33),""," "&LOOKUP(H33,Articles!A:A,Articles!B:B)) &IF(ISBLANK(I33),""," "&LOOKUP(I33,'Objets de gestion'!C:C,'Objets de gestion'!E:E)) &IF(ISBLANK(J33),""," "&LOOKUP(J33,Articles!A:A,Articles!B:B)) &IF(ISBLANK(K33),""," "&LOOKUP(K33,'Objets de gestion'!C:C,'Objets de gestion'!E:E)) )) -> Unique Identifier of the Link between third party and Account Manager | Q33: =IF(AND(ISBLANK(A33),ISBLANK(B33),ISBLANK(C33),ISBLANK(E33),ISBLANK(L33)),"",IF(OR(ISBLANK(A33),ISBLANK(B33),ISBLANK(C33),ISBLANK(E33),ISBLANK(L33)),"-", LOOKUP(B33,'Type de champ'!B:B,'Type de champ'!C:C))) -> Integer | R33: =IF(AND(ISBLANK(A33),ISBLANK(B33),ISBLANK(E33),ISBLANK(G33),ISBLANK(L33)),"",IF(OR(ISBLANK(A33),ISBLANK(B33),ISBLANK(E33),ISBLANK(G33),ISBLANK(L33)),"-", A33)) -> tiers
A34: tiers | B34: Chaine de caractère | C34: identifiant fonctionnel | D34: du | E34: Lien | F34: entre | G34: tiers | H34: et | I34: chargé de clientèle | L34: Normal | M34: =IF(AND(ISBLANK(A34),ISBLANK(B34),ISBLANK(E34),ISBLANK(G34),ISBLANK(L34)),"",IF(OR(ISBLANK(A34),ISBLANK(B34),ISBLANK(E34),ISBLANK(G34),ISBLANK(L34)),"-",LEN(Tableau47[[#This Row],[Code]]))) -> 23 | N34: =IF(AND(ISBLANK(A34),ISBLANK(B34),ISBLANK(C34),ISBLANK(E34),ISBLANK(L34)),"",IF(OR(ISBLANK(A34),ISBLANK(B34),ISBLANK(C34),ISBLANK(E34),ISBLANK(L34)),"à compléter", IF(L34="Normal", LOOKUP(B34,'Type de champ'!B:B,'Type de champ'!A:A) &IF(COUNTIF('Objets de gestion'!C:C,K34)=0,"","_"&LOOKUP(K34,'Objets de gestion'!C:C,'Objets de gestion'!F:F)) &IF(COUNTIF('Objets de gestion'!C:C,I34)=0,"","_"&LOOKUP(I34,'Objets de gestion'!C:C,'Objets de gestion'!F:F)) &IF(COUNTIF('Objets de gestion'!C:C,G34)=0,"","_"&LOOKUP(G34,'Objets de gestion'!C:C,'Objets de gestion'!F:F)) &IF(COUNTIF('Objets de gestion'!C:C,E34)=0,"","_"&LOOKUP(E34,'Objets de gestion'!C:C,'Objets de gestion'!F:F)) &IF(OR(C34="booléen",COUNTIF('Objets de gestion'!C:C,C34)=0),"","_"&LOOKUP(C34,'Objets de gestion'!C:C,'Objets de gestion'!F:F)), IF(L34="Forcé", LOOKUP(B34,'Type de champ'!B:B,'Type de champ'!A:A) &IF(COUNTIF('Objets de gestion'!C:C,E34)=0,"","_"&LOOKUP(E34,'Objets de gestion'!C:C,'Objets de gestion'!F:F)) &IF(COUNTIF('Objets de gestion'!C:C,G34)=0,"","_"&LOOKUP(G34,'Objets de gestion'!C:C,'Objets de gestion'!F:F)) &IF(COUNTIF('Objets de gestion'!C:C,I34)=0,"","_"&LOOKUP(I34,'Objets de gestion'!C:C,'Objets de gestion'!F:F)) &IF(COUNTIF('Objets de gestion'!C:C,K34)=0,"","_"&LOOKUP(K34,'Objets de gestion'!C:C,'Objets de gestion'!F:F)) &IF(OR(C34="booléen",COUNTIF('Objets de gestion'!C:C,C34)=0),"","_"&LOOKUP(C34,'Objets de gestion'!C:C,'Objets de gestion'!F:F)) )))) -> X_ACCMGR_TDP_LNK_FCTIDT | O34: =IF(AND(ISBLANK(A34),ISBLANK(B34),ISBLANK(C34),ISBLANK(E34),ISBLANK(L34)),"",IF(OR(ISBLANK(A34),ISBLANK(B34),ISBLANK(C34),ISBLANK(E34),ISBLANK(L34)),"-", C34&" "&IF(ISBLANK(E34),"",D34&" "&E34&" ")&IF(ISBLANK(G34),"",F34&" "&G34&" ")&IF(ISBLANK(I34),"",H34&" "&I34&" ")&IF(ISBLANK(K34),"",J34&" "&K34&" "))) -> identifiant fonctionnel du Lien entre tiers et chargé de clientèle | P34: =IF(AND(ISBLANK(A34),ISBLANK(B34),ISBLANK(C34),ISBLANK(E34),ISBLANK(L34)),"",IF(OR(ISBLANK(A34),ISBLANK(B34),ISBLANK(C34),ISBLANK(E34),ISBLANK(L34)),"-", IF(ISBLANK(C34),"",LOOKUP(C34,'Objets de gestion'!C:C,'Objets de gestion'!E:E)) &IF(ISBLANK(D34),""," "&LOOKUP(D34,Articles!A:A,Articles!B:B)) &IF(ISBLANK(E34),""," "&LOOKUP(E34,'Objets de gestion'!C:C,'Objets de gestion'!E:E)) &IF(ISBLANK(F34),""," "&LOOKUP(F34,Articles!A:A,Articles!B:B)) &IF(ISBLANK(G34),""," "&LOOKUP(G34,'Objets de gestion'!C:C,'Objets de gestion'!E:E)) &IF(ISBLANK(H34),""," "&LOOKUP(H34,Articles!A:A,Articles!B:B)) &IF(ISBLANK(I34),""," "&LOOKUP(I34,'Objets de gestion'!C:C,'Objets de gestion'!E:E)) &IF(ISBLANK(J34),""," "&LOOKUP(J34,Articles!A:A,Articles!B:B)) &IF(ISBLANK(K34),""," "&LOOKUP(K34,'Objets de gestion'!C:C,'Objets de gestion'!E:E)) )) -> functional identifier of the Link between third party and Account Manager | Q34: =IF(AND(ISBLANK(A34),ISBLANK(B34),ISBLANK(C34),ISBLANK(E34),ISBLANK(L34)),"",IF(OR(ISBLANK(A34),ISBLANK(B34),ISBLANK(C34),ISBLANK(E34),ISBLANK(L34)),"-", LOOKUP(B34,'Type de champ'!B:B,'Type de champ'!C:C))) -> Varchar(??) | R34: =IF(AND(ISBLANK(A34),ISBLANK(B34),ISBLANK(E34),ISBLANK(G34),ISBLANK(L34)),"",IF(OR(ISBLANK(A34),ISBLANK(B34),ISBLANK(E34),ISBLANK(G34),ISBLANK(L34)),"-", A34)) -> tiers

Sheet Objets de gestion
A1: Date ajout | B1: Used | C1: Nom FR | D1: Définition unique | E1: Nom EN | F1: Trigramme
A2: 44510 | C2: 1 | E2: 1 | F2: 1
A3: 44510 | C3: 2 | E3: 2 | F3: 2
A4: 44510 | C4: 3 | E4: 3 | F4: 3
A5: 44510 | C5: 4 | E5: 4 | F5: 4
A6: 44510 | C6: 5 | E6: 5 | F6: 5
A7: 44510 | C7: 6 | E7: 6 | F7: 6
A8: 44510 | C8: 7 | E8: 7 | F8: 7
A9: 44510 | C9: 8 | E9: 8 | F9: 8
A10: 44510 | C10: 9 | E10: 9 | F10: 9
A11: 43868 | C11: "a l'autorité parentale" | E11: "got the parental authority" | F11: GOTPAAAHR
A12: 43868 | C12: "a le pouvoir bancaire" | E12: "got the banking power" | F12: GOTBNKPOW
A13: 43867 | C13: "a une entreprise individuelle" | E13: "got an individual company" | F13: GOTIDVCNY
A14: 43868 | C14: "appartient au foyer fiscal" | E14: "belonging to the fiscal household" | F14: BLGFSCHHD
A15: 43868 | C15: "bénéficiaire effectif" | E15: "effective beneficiary" | F15: EFTBEN
A16: 43392 | C16: "Centre Est Europe" | E16: "Centre Est Europe" | F16: CEE
A17: 44512 | C17: 2nd meilleur | F17: TO2
A18: 44018 | C18: 36 derniers mois | E18: last 36 months | F18: LST36M
A19: 44199 | C19: à payer | E19: required to pay | F19: RTP
A20: 44199 | C20: abonné | E20: subscriber | F20: SBC
A21: 44199 | C21: absence | E21: absence | F21: ABS
A22: 43724 | C22: ACAM | D22: Autorité de Contrôle des Assurances et des Mutuelles | E22: ACAM | F22: AAM
A23: 44082 | C23: accès | E23: access | F23: AKS
A24: 44082 | C24: accès confidentiel | E24: confidential access | F24: CFDAKS
A25: 44040 | C25: accident | E25: accident | F25: ACD
A26: 44054 | C26: accident de circulation | E26: Traffic accident | F26: TFFACD
A27: 44012 | C27: accord de gestion | E27: management agreement | F27: MGTAGM
A28: 44049 | C28: accouchement | E28: delivery | F28: DLY
A29: 43719 | C29: ACEM | D29: Action Clé En Main | E29: turnkey action | F29: TNKACT
A30: 43721 | C30: ACEM réalisée | E30: turnkey action completion | F30: TNKACTCPI
A31: 44510 | C31: achat | E31: Purchase | F31: PDT
A32: 43860 | C32: acheminement | E32: transit | F32: TAS
A33: 43448 | C33: ACM | E33: ACM | F33: ACM
A34: 43760 | C34: ACORES | E34: ACORES | F34: ACE
A35: 44199 | C35: acquisition | E35: acquisition | F35: ACQ
A36: 43740 | C36: acte CCAM | E36: health care act CCAM | F36: HCACAM
A37: 43741 | C37: acte de prévention | E37: prevention health care act | F37: PVEHCA
A38: 43465 | C38: acte de soins santé de la CPAM | E38: heath care act CPAM | F38: HCACPM
A39: 43465 | C39: acte de soins santé des ACM | E39: health care act ACM | F39: HCAACM
A40: 44301 | B40: 1 | C40: Acte fondateur | E40: Founder act | F40: FUDACT
A41: 43448 | C41: acteur | D41: référentiel Acteur SIO | E41: actor | F41: AOR
A42: 43887 | C42: acteur en assurance | E42: insurance actor | F42: INSAOR
A43: 43469 | C43: acteur santé | E43: health actor | F43: HELAOR
A44: 44199 | C44: actif | E44: active | F44: ACV
A45: 44172 | C45: actif supprimable | E45: removable asset | F45: RMVAST
A46: 43608 | C46: action | E46: action | F46: ACT
A47: 44083 | C47: action du contentieux | E47: litigation action | F47: LITACT
A48: 43815 | C48: action suivante | E48: next action | F48: NXTACT
A49: 43868 | C49: actionnaire | E49: shareholder | F49: SHH
A50: 43384 | C50: activité | E50: activity | F50: AVY
A51: 44055 | C51: activité à mi-temps | E51: half-time activity | F51: HTMAVY
A52: 44049 | C52: activité à temps partiel | E52: part-time activity | F52: PRLTIMAVY
A53: 44049 | C53: activité à temps partiel thérapeutique | E53: part-time therapeutic activity | F53: PRLTIMTHPAVY
A54: 44510 | C54: actuaire | D54: relatif à l'actuariat | E54: Actuarial | F54: ATL
A55: 44199 | C55: actuel | E55: current | F55: CRN
A56: 43724 | C56: adaptation verres | E56: optical lens ajustement | F56: OPCLSNAJU
A57: 43724 | C57: ADELI | E57: ADELI | F57: ADL
A58: 43523 | C58: adhérent | E58: member | F58: MMB
A59: 44301 | B59: 1 | C59: adhérer | E59: Membership | F59: MBR
A60: 43756 | C60: adhésion | E60: membership | F60: MBR
A61: 44301 | B61: 1 | C61: adhésion obligatoire | E61: mandatory membership | F61: MPYMBR
A62: 43755 | C62: adhésion PCM | E62: PCM membership | F62: PCMMBR
A63: 43867 | C63: administrateur | E63: administrator | F63: ADM
A64: 44173 | C64: administrateur mot de passe | E64: password administrator | F64: PWDADM
A65: 43732 | C65: ADRE | D65: Référentiel adresse | E65: address repository | F65: ADRRPY
A66: 43732 | C66: adresse | E66: address | F66: ADR
A67: 44120 | C67: adresse courrier | E67: mail address | F67: MILADR
A68: 44200 | C68: Adresse ligne 1 | E68: Address line 1 | F68: ADRLN1
A69: 44200 | C69: Adresse ligne 2 | E69: Address line 2 | F69: ADRLN2
A70: 44200 | C70: Adresse ligne 3 | E70: Address line 3 | F70: ADRLN3
A71: 44200 | C71: Adresse ligne 4 | E71: Address line 4 | F71: ADRLN4
A72: 44200 | C72: Adresse ligne 5 | E72: Address line 5 | F72: ADRLN5
A73: 44200 | C73: Adresse ligne 6 | E73: Address line 6 | F73: ADRLN6
A74: 44200 | C74: Adresse ligne 7 | E74: Address line 7 | F74: ADRLN7
A75: 44200 | C75: Adresse mail | E75: Email | F75: EML
A76: 44011 | C76: affaire | E76: business | F76: BIZ
A77: 44000 | C77: affectation | E77: assignment | F77: ASN
A78: 44301 | B78: 1 | C78: affecté | E78: affected | F78: AFD
A79: 43965 | C79: affecter le SARA | E79: assign SARA | F79: ASGSAR
A80: 44049 | C80: affection | E80: disease | F80: DIE
A81: 44199 | C81: affichage | E81: display | F81: DPL
A82: 44200 | C82: Age | E82: Age | F82: AGE
A83: 43655 | C83: âge du tiers titulaire | E83: third party holder age | F83: TPHAGE
A84: 44512 | C84: agence | E84: Agency | F84: AGC
A85: 43867 | C85: agrégation | E85: aggregation | F85: AGG
A86: 43910 | C86: agregation des mouvements financiers | E86: aggregation of financial movements | F86: AGGFNCMVT
A87: 43662 | C87: agrégé | E87: aggregated | F87: AGG
A88: 44199 | C88: agrément | E88: agreement | F88: AGM
A89: 43724 | C89: agrément vitrage | E89: glazing agreement | F89: GLZAGM
A90: 43644 | C90: ajustement | E90: adjustment | F90: AJU
... A100: 44199 | C100: ancienneté | E100: seniority | F100: SNT
C101: ancienneté courante | E101: current seniority | F101: CRNSNT
A102: 43489 | C102: année | E102: year | F102: YEA
A103: 44200 | C103: Année d'acquisition | E103: Acquisition Year | F103: ACQYEA
A104: 43465 | C104: année de rétention | E104: retention year | F104: RTEYEA
A105: 44200 | C105: Année de survenance | E105: Occurrence year | F105: OCCYEA
A106: 43700 | C106: année glissante | E106: year-on-year | F106: YOY
A107: 44148 | C107: année mois jours | E107: Year months days | F107: YEAMOEDAY
A108: 43493 | C108: année précédente | E108: previous year | F108: PRVYEA
A109: 43493 | C109: année suivante | E109: next year | F109: NXTYEA
...

Sheet Articles
A1: Nom fr | B1: Nom en
A3: , | B3: ,
A4: à | B4: to
A5: à l' | B5: at
A6: à la | B6: to
A7: à qui | B7: to
A8: à un | B8: to
A9: après | B9: after
A10: au | B10: to
A11: avec | B11: with
A12: chez | B12: at
A13: d' | B13: of the
... A47: sur le | B47: on the

Sheet BIB
A1: Nom du BIB | B1: ID Table | C1: ROBIN | D1: Nom anglais | E1: Code du BIB | F1: Remarque
B2: TAC | C2: IBIT | D2: Admin console | E2: ADMCSL
A3: Abstraction / transcodification | B3: TID | C3: IBIT | D3: Abstraction / transcoding
A4: Acteur en assurance | B4: AAC | C4: IBIA | D4: Insurance Actor | E4: INSAOR
A5: Avantages | B5: FAV | C5: IBIF | D5: Advantages | E5: INSCTRADV
A6: Balances analytiques comptables | B6: FBA | C6: IBIF | D6: Analytical accounting balances | E6: CSTACGBAL
A7: Barème santé | B7: RBS | C7: IBIR | D7: Health Scale | E7: HELSCA
A8: Bascule CAM vers GEC | B8: CCG | C8: IBIC | D8: Transfer CAM to GEC | E8: TRFCAMGEC
A9: Base collecte | B9: TCO | C9: SIAD | D9: Collecte database | E9: COLDBA
A10: Base organisme | B10: RBO | C10: IBIR | D10: Organisation Repository | E10: BSEORG
A11: bénéficiaires en assurance | B11: AIB | C11: IBIA | D11: insurance beneficiary | E11: INSBEN
A12: BIB pour stocker les tables EOLE : TAWISTF, TAWISTG... | B12: VSI | C12: IBIV | E12: SIOEOLE
A13: Carte avance santé | B13: SCS | C13: IBIS | D13: Advance Health Card | E13: AHC
A14: COFIDIS Données externes | B14: OCF | C14: IBIO | D14: Cofidis external data | E14: CFSXTRDTA
A15: Collaborateurs Assurance | B15: RCB | C15: IBIR | D15: Insurance collaborators | E15: INSCBR
A16: Comptabilité | B16: FCO | C16: IBIF | D16: Accounting | E16: INSCNYACGREC
A17: Comptage Volumétrie | B17: TVC | C17: IBIT | D17: Volumetry Count
A18: Conditions et moyens de paiement | B18: CMP | C18: IBIC | D18: Payment means and conditions | E18: PMC
A19: Console du gestionnaire | B19: MCG | C19: IBIM | D19: Manager console | E19: INSMGRCON
A20: Contentieux | B20: CTX | C20: IBIC | D20: Litigation | E20: LIT
A21: contrat | B21: CCT | C21: IBIC | D21: contract | E21: INSCTR
A22: Contrat assurance téléphone | B22: CTE | C22: IBIC | D22: Insurance contract telephone | E22: INSTEL
A23: correspondant | B23: ACO | C23: IBIA | D23: corresponding | E23: INSCOR
A24: Courtier | B24: ECO | C24: IBIE | D24: broker | E24: INSBRK
A25: Datamart Contrat | B25: DCT | C25: IBID | D25: contract datamart | E25: CTR
A26: Datamart courtiers | B26: BDT | C26: IBID | D26: broker datamart | E26: BRK
A27: Déclaratif réglementaire Belgique | B27: OBR | C27: IBIO | D27: Belgian regulatory report | E27: BELRGLRPT
A28: Dettes | B28: SDE | C28: IBIS | D28: Debts | E28: INSDET
A29: Données assurances pour la Banque | B29: BDA | C29: IBIB | D29: Bank insurance data | E29: BNKINSDTA
... A31: Echéancier des contrats d’assurance | B31: FEC | C31: IBIF | D31: Schedule of insurance contracts | E31: SCHINSCTR
A32: Eole | B32: CEO | C32: IBIC | D32: Eole
A33: Etude assurance | B33: VEA | C33: IBIV | D33: Insurance study | E33: INSSTU | F33: INSSTY
A34: Financier | B34: FFI | C34: IBIF | D34: Financial | E34: INSBUSFIN
A35: Financier et échéancier des sinistres | B35: SFS | C35: IBIS | D35: Financial schedule of claim | E35: FINSCHCIM
A36: Fiscalité des contrats d'assurance | B36: FFS | C36: IBIF | D36: Insurance contract fiscality | E36: INSCTRFSC
A37: Générateur des modèles de données des vues du SIAD | B37: TMV | C37: IBIT | D37: View model generator | E37: VIEMDEGTR
A38: genesys | B38: MGE | C38: IBIM | D38: genesys | E38: INSCTCPLF
A39: Gestion des documents assurance (IDOFCD) | B39: MDO | C39: IBIM | D39: Insurance document management | E39: INSDOCMGT
A40: Gestion des FOCUS | B40: MFO | C40: IBIM | D40: Insurance monitoring Focus | E40: INSMNTFOC
A41: Gestion du personnel assurance | B41: MPA | C41: IBIM | D41: Insurance Staff Management | E41: INSSFFMGT
A42: Images Contrats Assurance | B42: CIC | C42: IBIC | D42: Insurance Contract Image | E42: ICA | F42: à créer dans MAD
A43: Lot Logmaster | B43: OIL | C43: IBIO | D43: LogMaster Lot | E43: INSLOT
A44: Paramétrage | B44: TPA | C44: IBIT | D44: Setting
A45: Prestation Santé | B45: SPS | C45: IBIS | D45: Health insurance reimbursement | E45: HIRRBT
A46: Prestation Santé au Contrôle | B46: SPC | C46: IBIS | D46: Health insurance reimbursement to control | E46: HIRRBTCTL
A47: primes | B47: FPR | C47: IBIF | D47: premiums | E47: PUMWRN
A48: produit | B48: RPR | C48: IBIR | D48: product | E48: INSPRD
A49: Progiciels financiers assurances | B49: PPF | C49: IBIP | D49: Insurance financial software | E49: INSFNCSFW
A50: Provisions sinistres | B50: SPV | C50: IBIS | D50: Claim provisions | E50: CIMPVN
A51: Purges | B51: TPU | C51: IBIT | D51: purges | E51: DTAPUG
A52: Qualification des contacts assurance | B52: MCQ | C52: IBIM | D52: Insurance contact qualification | E52: INSCTCQLN
A53: Qualité des données | B53: TQD | C53: IBIT | D53: Data quality
A54: Rapport de contrôle interne des assurances | B54: DCI | C54: IBID | D54: Insurance internal control report | E54: INSINTCTLRPT
A55: Réclamations Clients | B55: DRC | C55: IBID | D55: Customer complaint | E55: CUSCPA
A56: RECNAS | B56: DRN | C56: IBID | D56: RECNAS | E56: RECNAS
A57: RECNASSIO | B57: DRS | C57: IBID | E57: RECNASSIO
A58: Référence bancaire | B58: RBA | C58: IBIR | D58: Bank detail | E58: BKD
A59: Référentiel Garantie & Service | B59: RGS | C59: IBIR | D59: Guaranty & Service Repository | E59: WARSVCINS
A60: Référentiel Pays | B60: RPA | C60: IBIR | D60: Country | E60: CTY
A61: Référentiel postal | B61: RPO | C61: IBIR | D61: Town | E61: TWN
A62: Serveur vocal intéractif (SVI) | B62: MSV | C62: IBIM | D62: Interactive voice server | E62: IVS
A63: Sinistres IARD | B63: SSI | C63: IBIS | D63: Property & Casuality Claim | E63: PCACIM
A64: Sinistres prévoyance et emprunteur | B64: SRP | C64: IBIS | D64: Personnal risk Insurance Reimbursement | E64: PRKINSRBT
A65: Société | B65: RSO | C65: IBIR | D65: society | E65: INSCNY
A66: Suivi de l'avant vente | B66: VAV | C66: IBIV | D66: Insurance presale following | E66: INSPRESALFOL
A67: Suivi exploitation | B67: TSE | C67: IBIT | D67: Operation monitoring | E67: OPE_MNT
A68: Tarification | B68: FTA | C68: IBIF | D68: Pricing | E68: INSCTRTAR
A69: Taux Théorique des commissions bancaire et financière d’assurance | B69: VTC | C69: IBIV | D69: Theorical rate of insurance Banking and Finance Commission | E69: THORATINSBFC
... A72: Transfert PACTE | B72: LTP | C72: IBIL | D72: Transfer PACTE | E72: TRFPTE
A73: Transverse | B73: TTT | C73: IBIT
A74: tribu | B74: ATR | C74: IBIA | D74: tribu
A75: Usine à contrôles | B75: TUC | C75: IBIT | D75: Control factory | E75: CTLFTR
A76: Usine à vues | B76: TUV | C76: IBIT | D76: View Factory | E76: VIECTR
A77: Zonier | B77: RZT | C77: IBIR | D77: Zonier

Sheet Type de table
A1: Catégorie | B1: ID | C1: Nom | D1: Définition unique | E1: libellé FR | F1: Libellé EN
A2: Technique | B2: A | C2: Abstraction | D2: entité qui continet les clés techniques SID générées à partir des clés SIO | E2: Table d'abstraction | F2: Abstraction table
A3: Métier | B3: X | C3: Axe d'analyse | D3: Dimension qui servira d'axe d'analyse | E3: Axe | F3: Axis
A4: Métier | B4: M | C4: Datamart | D4: table qui agrège une table de fait et ses dimensions attenantes pour répondre à un besoin fonctionnel | E4: Datamart | F4: Datamart
A5: Métier | B5: V | C5: Domaine de valeurs | D5: entité contenant les valeurs issus des domaines de valeur du SIO et gérés dans la transcodification SID | E5: Domaine de valeurs | F5: List of values
A6: Métier | B6: F | C6: Fait | D6: entité contenant les faits | E6: Table de fait | F6: Fact table
A7: Technique | B7: G | C7: Générateur Séquence d'abstraction | D7: entité générant les séquences utilisées pour la génération des tables d'abstractions | E7: Table génératrice de séquence d'abstraction | F7: Abstraction sequence generator table
A8: Technique | B8: I | C8: Identifiant générique | D8: table qui permet d'obtenir un identifiant unique pour une données de gestion définie dans plusieurs référentiels (ex garantie générique) | E8: Table d'identifiants génériques | F8: generic identifier table
A9: Technique | B9: Z | C9: Paramétrage | D9: entité utilisée dans le SID pour passer des paramètres | E9: Table de paramètrage | F9: Parameter table
A10: Technique | B10: Q | C10: Qualité des données | D10: entité utilisée pour le suivi de la qualité de l'entrepot (usine a contrôle, contrainte d'intégrité,…) | E10: Table de qualité des données | F10: Data quality table
A11: Métier | B11: L | C11: Relation | D11: Dimension représentant un lien entre deux tables la cardinalité doit forcément etre de type N/N | E11: Table de lien entre | F11: Link table between
A12: Technique | B12: O | C12: Suivi exploitation | D12: table qui permet l'observation du SID | E12: Table de suivi d'exploitation | F12: operation monitoring table
... A16: Métier | B16: W | C16: Work | D16: table utilisée par nos traitements de chargement et non visible des utilisateurs | E16: table de travail | F16: Work table

Sheet Type de champ
A1: ID | B1: Type | C1: Format
A2: B | B2: Booléen | C2: Boolean
A3: X | B3: Chaine de caractère | C3: Varchar(??)
A4: K | B4: Clé | C4: Integer
A5: T | B5: Date, Heure, Timestamp | C5: Date
A6: M | B6: Montant | C6: Numeric(??,??)
A7: D | B7: Nombre décimal | C7: Numeric(??,??)
A8: I | B8: Nombre entier | C8: Integer
